[{"Volume": "105400", "Symbol": "ADMS", "Adj_Close": "16.08", "High": "16.290001", "Low": "15.68", "Date": "2017-02-02", "Close": "16.08", "Open": "15.92"}, {"Volume": "147600", "Symbol": "ADMS", "Adj_Close": "15.94", "High": "16.18", "Low": "15.68", "Date": "2017-02-01", "Close": "15.94", "Open": "15.97"}, {"Volume": "139000", "Symbol": "ADMS", "Adj_Close": "15.87", "High": "16.08", "Low": "14.66", "Date": "2017-01-31", "Close": "15.87", "Open": "14.75"}, {"Volume": "333000", "Symbol": "ADMS", "Adj_Close": "14.87", "High": "16.065001", "Low": "14.23", "Date": "2017-01-30", "Close": "14.87", "Open": "15.90"}, {"Volume": "68200", "Symbol": "ADMS", "Adj_Close": "15.96", "High": "16.17", "Low": "15.83", "Date": "2017-01-27", "Close": "15.96", "Open": "15.84"}, {"Volume": "92500", "Symbol": "ADMS", "Adj_Close": "15.89", "High": "16.26", "Low": "15.81", "Date": "2017-01-26", "Close": "15.89", "Open": "16.219999"}, {"Volume": "102200", "Symbol": "ADMS", "Adj_Close": "16.16", "High": "16.57", "Low": "15.90", "Date": "2017-01-25", "Close": "16.16", "Open": "16.059999"}, {"Volume": "171200", "Symbol": "ADMS", "Adj_Close": "15.95", "High": "16.25", "Low": "15.56", "Date": "2017-01-24", "Close": "15.95", "Open": "16.24"}, {"Volume": "79700", "Symbol": "ADMS", "Adj_Close": "16.120001", "High": "16.82", "Low": "16.059999", "Date": "2017-01-23", "Close": "16.120001", "Open": "16.17"}, {"Volume": "72800", "Symbol": "ADMS", "Adj_Close": "16.17", "High": "16.48", "Low": "16.049999", "Date": "2017-01-20", "Close": "16.17", "Open": "16.459999"}, {"Volume": "116400", "Symbol": "ADMS", "Adj_Close": "16.42", "High": "16.872", "Low": "16.18", "Date": "2017-01-19", "Close": "16.42", "Open": "16.610001"}, {"Volume": "131500", "Symbol": "ADMS", "Adj_Close": "16.610001", "High": "16.719999", "Low": "16.047001", "Date": "2017-01-18", "Close": "16.610001", "Open": "16.280001"}, {"Volume": "150700", "Symbol": "ADMS", "Adj_Close": "16.26", "High": "16.879999", "Low": "16.214001", "Date": "2017-01-17", "Close": "16.26", "Open": "16.879999"}, {"Volume": "143100", "Symbol": "ADMS", "Adj_Close": "17.129999", "High": "17.299999", "Low": "16.709999", "Date": "2017-01-13", "Close": "17.129999", "Open": "16.709999"}, {"Volume": "126800", "Symbol": "ADMS", "Adj_Close": "16.73", "High": "16.92", "Low": "16.32", "Date": "2017-01-12", "Close": "16.73", "Open": "16.559999"}, {"Volume": "237000", "Symbol": "ADMS", "Adj_Close": "16.709999", "High": "17.389999", "Low": "16.33", "Date": "2017-01-11", "Close": "16.709999", "Open": "17.33"}, {"Volume": "260000", "Symbol": "ADMS", "Adj_Close": "17.34", "High": "18.120001", "Low": "17.26", "Date": "2017-01-10", "Close": "17.34", "Open": "18.120001"}, {"Volume": "410400", "Symbol": "ADMS", "Adj_Close": "18.09", "High": "19.295", "Low": "18.01", "Date": "2017-01-09", "Close": "18.09", "Open": "19.209999"}, {"Volume": "526500", "Symbol": "ADMS", "Adj_Close": "19.02", "High": "19.50", "Low": "18.25", "Date": "2017-01-06", "Close": "19.02", "Open": "18.26"}, {"Volume": "128500", "Symbol": "ADMS", "Adj_Close": "18.049999", "High": "18.235001", "Low": "17.709999", "Date": "2017-01-05", "Close": "18.049999", "Open": "17.84"}, {"Volume": "310500", "Symbol": "ADMS", "Adj_Close": "18.00", "High": "18.395", "Low": "16.629999", "Date": "2017-01-04", "Close": "18.00", "Open": "16.629999"}, {"Volume": "213200", "Symbol": "ADMS", "Adj_Close": "16.59", "High": "17.040001", "Low": "16.045", "Date": "2017-01-03", "Close": "16.59", "Open": "16.99"}, {"Volume": "190000", "Symbol": "ADMS", "Adj_Close": "16.90", "High": "17.51", "Low": "16.67", "Date": "2016-12-30", "Close": "16.90", "Open": "17.48"}, {"Volume": "94200", "Symbol": "ADMS", "Adj_Close": "17.43", "High": "17.50", "Low": "17.065001", "Date": "2016-12-29", "Close": "17.43", "Open": "17.129999"}, {"Volume": "110000", "Symbol": "ADMS", "Adj_Close": "17.139999", "High": "17.26", "Low": "16.75", "Date": "2016-12-28", "Close": "17.139999", "Open": "17.15"}, {"Volume": "130100", "Symbol": "ADMS", "Adj_Close": "17.200001", "High": "17.737", "Low": "16.92", "Date": "2016-12-27", "Close": "17.200001", "Open": "17.440001"}, {"Volume": "94300", "Symbol": "ADMS", "Adj_Close": "17.42", "High": "17.450001", "Low": "16.49", "Date": "2016-12-23", "Close": "17.42", "Open": "16.610001"}, {"Volume": "109200", "Symbol": "ADMS", "Adj_Close": "16.639999", "High": "16.77", "Low": "16.049999", "Date": "2016-12-22", "Close": "16.639999", "Open": "16.34"}, {"Volume": "98600", "Symbol": "ADMS", "Adj_Close": "16.35", "High": "16.73", "Low": "16.049999", "Date": "2016-12-21", "Close": "16.35", "Open": "16.58"}, {"Volume": "129900", "Symbol": "ADMS", "Adj_Close": "16.60", "High": "16.65", "Low": "16.059999", "Date": "2016-12-20", "Close": "16.60", "Open": "16.309999"}, {"Volume": "126200", "Symbol": "ADMS", "Adj_Close": "16.17", "High": "16.74", "Low": "15.83", "Date": "2016-12-19", "Close": "16.17", "Open": "15.98"}, {"Volume": "209800", "Symbol": "ADMS", "Adj_Close": "15.98", "High": "16.24", "Low": "15.69", "Date": "2016-12-16", "Close": "15.98", "Open": "15.69"}, {"Volume": "381400", "Symbol": "ADMS", "Adj_Close": "15.58", "High": "15.93", "Low": "15.35", "Date": "2016-12-15", "Close": "15.58", "Open": "15.54"}, {"Volume": "98300", "Symbol": "ADMS", "Adj_Close": "15.48", "High": "15.78", "Low": "15.12", "Date": "2016-12-14", "Close": "15.48", "Open": "15.63"}, {"Volume": "96800", "Symbol": "ADMS", "Adj_Close": "15.66", "High": "15.95", "Low": "15.54", "Date": "2016-12-13", "Close": "15.66", "Open": "15.79"}, {"Volume": "121900", "Symbol": "ADMS", "Adj_Close": "15.64", "High": "15.79", "Low": "15.36", "Date": "2016-12-12", "Close": "15.64", "Open": "15.56"}, {"Volume": "117800", "Symbol": "ADMS", "Adj_Close": "15.66", "High": "16.67", "Low": "15.56", "Date": "2016-12-09", "Close": "15.66", "Open": "16.08"}, {"Volume": "134200", "Symbol": "ADMS", "Adj_Close": "15.91", "High": "16.049999", "Low": "15.14", "Date": "2016-12-08", "Close": "15.91", "Open": "15.39"}, {"Volume": "178400", "Symbol": "ADMS", "Adj_Close": "15.51", "High": "15.72", "Low": "14.80", "Date": "2016-12-07", "Close": "15.51", "Open": "15.52"}, {"Volume": "118000", "Symbol": "ADMS", "Adj_Close": "15.75", "High": "15.94", "Low": "15.10", "Date": "2016-12-06", "Close": "15.75", "Open": "15.58"}, {"Volume": "165100", "Symbol": "ADMS", "Adj_Close": "15.54", "High": "15.95", "Low": "15.15", "Date": "2016-12-05", "Close": "15.54", "Open": "15.67"}, {"Volume": "123600", "Symbol": "ADMS", "Adj_Close": "15.53", "High": "15.94", "Low": "14.50", "Date": "2016-12-02", "Close": "15.53", "Open": "14.55"}, {"Volume": "175900", "Symbol": "ADMS", "Adj_Close": "14.55", "High": "15.245", "Low": "14.31", "Date": "2016-12-01", "Close": "14.55", "Open": "15.09"}, {"Volume": "98700", "Symbol": "ADMS", "Adj_Close": "15.00", "High": "15.55", "Low": "14.86", "Date": "2016-11-30", "Close": "15.00", "Open": "15.20"}, {"Volume": "123000", "Symbol": "ADMS", "Adj_Close": "15.15", "High": "15.58", "Low": "14.94", "Date": "2016-11-29", "Close": "15.15", "Open": "15.11"}, {"Volume": "88100", "Symbol": "ADMS", "Adj_Close": "15.21", "High": "15.94", "Low": "15.08", "Date": "2016-11-28", "Close": "15.21", "Open": "15.94"}, {"Volume": "88600", "Symbol": "ADMS", "Adj_Close": "16.01", "High": "16.110001", "Low": "15.725", "Date": "2016-11-25", "Close": "16.01", "Open": "16.049999"}, {"Volume": "118100", "Symbol": "ADMS", "Adj_Close": "16.049999", "High": "16.08", "Low": "14.63", "Date": "2016-11-23", "Close": "16.049999", "Open": "15.10"}, {"Volume": "110800", "Symbol": "ADMS", "Adj_Close": "15.29", "High": "15.955", "Low": "15.16", "Date": "2016-11-22", "Close": "15.29", "Open": "15.84"}, {"Volume": "123100", "Symbol": "ADMS", "Adj_Close": "15.81", "High": "16.389999", "Low": "15.735", "Date": "2016-11-21", "Close": "15.81", "Open": "16.01"}, {"Volume": "73600", "Symbol": "ADMS", "Adj_Close": "15.97", "High": "16.139999", "Low": "15.77", "Date": "2016-11-18", "Close": "15.97", "Open": "16.129999"}, {"Volume": "82000", "Symbol": "ADMS", "Adj_Close": "16.10", "High": "16.280001", "Low": "15.86", "Date": "2016-11-17", "Close": "16.10", "Open": "16.040001"}, {"Volume": "122400", "Symbol": "ADMS", "Adj_Close": "16.07", "High": "16.389999", "Low": "15.84", "Date": "2016-11-16", "Close": "16.07", "Open": "16.01"}, {"Volume": "145500", "Symbol": "ADMS", "Adj_Close": "16.10", "High": "16.440001", "Low": "15.78", "Date": "2016-11-15", "Close": "16.10", "Open": "16.299999"}, {"Volume": "198900", "Symbol": "ADMS", "Adj_Close": "16.42", "High": "16.43", "Low": "15.60", "Date": "2016-11-14", "Close": "16.42", "Open": "16.049999"}, {"Volume": "194900", "Symbol": "ADMS", "Adj_Close": "15.94", "High": "16.188999", "Low": "15.75", "Date": "2016-11-11", "Close": "15.94", "Open": "15.90"}, {"Volume": "211300", "Symbol": "ADMS", "Adj_Close": "15.88", "High": "16.450001", "Low": "15.46", "Date": "2016-11-10", "Close": "15.88", "Open": "16.00"}, {"Volume": "260400", "Symbol": "ADMS", "Adj_Close": "15.69", "High": "15.945", "Low": "14.80", "Date": "2016-11-09", "Close": "15.69", "Open": "14.80"}, {"Volume": "137700", "Symbol": "ADMS", "Adj_Close": "14.49", "High": "14.72", "Low": "13.95", "Date": "2016-11-08", "Close": "14.49", "Open": "14.09"}, {"Volume": "136100", "Symbol": "ADMS", "Adj_Close": "14.26", "High": "14.46", "Low": "13.93", "Date": "2016-11-07", "Close": "14.26", "Open": "14.23"}, {"Volume": "303800", "Symbol": "ADMS", "Adj_Close": "13.93", "High": "14.38", "Low": "12.10", "Date": "2016-11-04", "Close": "13.93", "Open": "12.25"}, {"Volume": "229200", "Symbol": "ADMS", "Adj_Close": "12.24", "High": "13.61", "Low": "12.21", "Date": "2016-11-03", "Close": "12.24", "Open": "13.61"}, {"Volume": "87300", "Symbol": "ADMS", "Adj_Close": "13.56", "High": "13.94", "Low": "13.55", "Date": "2016-11-02", "Close": "13.56", "Open": "13.93"}, {"Volume": "104100", "Symbol": "ADMS", "Adj_Close": "14.00", "High": "14.11", "Low": "13.71", "Date": "2016-11-01", "Close": "14.00", "Open": "13.79"}, {"Volume": "169800", "Symbol": "ADMS", "Adj_Close": "13.74", "High": "13.93", "Low": "13.40", "Date": "2016-10-31", "Close": "13.74", "Open": "13.72"}, {"Volume": "155900", "Symbol": "ADMS", "Adj_Close": "13.71", "High": "14.20", "Low": "13.45", "Date": "2016-10-28", "Close": "13.71", "Open": "14.20"}, {"Volume": "115700", "Symbol": "ADMS", "Adj_Close": "14.33", "High": "14.83", "Low": "14.255", "Date": "2016-10-27", "Close": "14.33", "Open": "14.50"}, {"Volume": "83100", "Symbol": "ADMS", "Adj_Close": "14.35", "High": "14.70", "Low": "14.211", "Date": "2016-10-26", "Close": "14.35", "Open": "14.47"}, {"Volume": "72400", "Symbol": "ADMS", "Adj_Close": "14.52", "High": "14.79", "Low": "14.47", "Date": "2016-10-25", "Close": "14.52", "Open": "14.51"}, {"Volume": "111300", "Symbol": "ADMS", "Adj_Close": "14.51", "High": "14.74", "Low": "14.42", "Date": "2016-10-24", "Close": "14.51", "Open": "14.74"}, {"Volume": "91600", "Symbol": "ADMS", "Adj_Close": "14.59", "High": "14.93", "Low": "14.26", "Date": "2016-10-21", "Close": "14.59", "Open": "14.47"}, {"Volume": "103300", "Symbol": "ADMS", "Adj_Close": "14.55", "High": "14.63", "Low": "14.105", "Date": "2016-10-20", "Close": "14.55", "Open": "14.23"}, {"Volume": "98400", "Symbol": "ADMS", "Adj_Close": "14.24", "High": "14.70", "Low": "14.08", "Date": "2016-10-19", "Close": "14.24", "Open": "14.70"}, {"Volume": "106000", "Symbol": "ADMS", "Adj_Close": "14.68", "High": "14.80", "Low": "14.40", "Date": "2016-10-18", "Close": "14.68", "Open": "14.69"}, {"Volume": "240800", "Symbol": "ADMS", "Adj_Close": "14.52", "High": "14.72", "Low": "14.08", "Date": "2016-10-17", "Close": "14.52", "Open": "14.50"}, {"Volume": "170400", "Symbol": "ADMS", "Adj_Close": "14.45", "High": "15.26", "Low": "14.45", "Date": "2016-10-14", "Close": "14.45", "Open": "15.26"}, {"Volume": "117000", "Symbol": "ADMS", "Adj_Close": "15.10", "High": "15.29", "Low": "14.89", "Date": "2016-10-13", "Close": "15.10", "Open": "15.06"}, {"Volume": "166200", "Symbol": "ADMS", "Adj_Close": "15.25", "High": "15.99", "Low": "15.101", "Date": "2016-10-12", "Close": "15.25", "Open": "15.92"}, {"Volume": "170600", "Symbol": "ADMS", "Adj_Close": "15.95", "High": "16.77", "Low": "15.86", "Date": "2016-10-11", "Close": "15.95", "Open": "16.32"}, {"Volume": "172900", "Symbol": "ADMS", "Adj_Close": "16.610001", "High": "16.67", "Low": "16.10", "Date": "2016-10-10", "Close": "16.610001", "Open": "16.10"}, {"Volume": "170300", "Symbol": "ADMS", "Adj_Close": "15.94", "High": "15.99", "Low": "15.61", "Date": "2016-10-07", "Close": "15.94", "Open": "15.97"}, {"Volume": "137800", "Symbol": "ADMS", "Adj_Close": "16.004999", "High": "16.469999", "Low": "15.82", "Date": "2016-10-06", "Close": "16.004999", "Open": "16.43"}, {"Volume": "150400", "Symbol": "ADMS", "Adj_Close": "16.60", "High": "17.059999", "Low": "16.42", "Date": "2016-10-05", "Close": "16.60", "Open": "16.540001"}, {"Volume": "140600", "Symbol": "ADMS", "Adj_Close": "16.379999", "High": "16.65", "Low": "16.215", "Date": "2016-10-04", "Close": "16.379999", "Open": "16.42"}, {"Volume": "192600", "Symbol": "ADMS", "Adj_Close": "16.42", "High": "16.517", "Low": "15.96", "Date": "2016-10-03", "Close": "16.42", "Open": "16.35"}, {"Volume": "179000", "Symbol": "ADMS", "Adj_Close": "16.41", "High": "16.74", "Low": "16.10", "Date": "2016-09-30", "Close": "16.41", "Open": "16.74"}, {"Volume": "239800", "Symbol": "ADMS", "Adj_Close": "16.50", "High": "17.518999", "Low": "16.445", "Date": "2016-09-29", "Close": "16.50", "Open": "17.41"}, {"Volume": "162800", "Symbol": "ADMS", "Adj_Close": "17.459999", "High": "17.48", "Low": "17.040001", "Date": "2016-09-28", "Close": "17.459999", "Open": "17.33"}, {"Volume": "246800", "Symbol": "ADMS", "Adj_Close": "17.299999", "High": "17.639999", "Low": "17.200001", "Date": "2016-09-27", "Close": "17.299999", "Open": "17.629999"}, {"Volume": "161100", "Symbol": "ADMS", "Adj_Close": "17.65", "High": "17.799", "Low": "17.08", "Date": "2016-09-26", "Close": "17.65", "Open": "17.35"}, {"Volume": "187400", "Symbol": "ADMS", "Adj_Close": "17.35", "High": "18.190001", "Low": "17.299999", "Date": "2016-09-23", "Close": "17.35", "Open": "18.08"}, {"Volume": "261200", "Symbol": "ADMS", "Adj_Close": "18.07", "High": "18.40", "Low": "17.540001", "Date": "2016-09-22", "Close": "18.07", "Open": "18.09"}, {"Volume": "594100", "Symbol": "ADMS", "Adj_Close": "17.809999", "High": "19.50", "Low": "17.16", "Date": "2016-09-21", "Close": "17.809999", "Open": "19.450001"}, {"Volume": "309300", "Symbol": "ADMS", "Adj_Close": "18.09", "High": "18.280001", "Low": "17.530001", "Date": "2016-09-20", "Close": "18.09", "Open": "17.709999"}, {"Volume": "222600", "Symbol": "ADMS", "Adj_Close": "17.68", "High": "17.982", "Low": "17.51", "Date": "2016-09-19", "Close": "17.68", "Open": "17.610001"}, {"Volume": "234700", "Symbol": "ADMS", "Adj_Close": "17.42", "High": "17.49", "Low": "16.450001", "Date": "2016-09-16", "Close": "17.42", "Open": "16.83"}, {"Volume": "283700", "Symbol": "ADMS", "Adj_Close": "16.860001", "High": "17.370001", "Low": "16.459999", "Date": "2016-09-15", "Close": "16.860001", "Open": "16.59"}, {"Volume": "233000", "Symbol": "ADMS", "Adj_Close": "16.450001", "High": "16.60", "Low": "15.821", "Date": "2016-09-14", "Close": "16.450001", "Open": "15.98"}, {"Volume": "197300", "Symbol": "ADMS", "Adj_Close": "15.89", "High": "16.02", "Low": "15.249", "Date": "2016-09-13", "Close": "15.89", "Open": "15.74"}, {"Volume": "168400", "Symbol": "ADMS", "Adj_Close": "15.77", "High": "15.85", "Low": "15.09", "Date": "2016-09-12", "Close": "15.77", "Open": "15.12"}, {"Volume": "244000", "Symbol": "ADMS", "Adj_Close": "15.11", "High": "16.040001", "Low": "15.06", "Date": "2016-09-09", "Close": "15.11", "Open": "15.91"}, {"Volume": "406000", "Symbol": "ADMS", "Adj_Close": "16.129999", "High": "16.450001", "Low": "15.80", "Date": "2016-09-08", "Close": "16.129999", "Open": "16.26"}, {"Volume": "199200", "Symbol": "ADMS", "Adj_Close": "15.63", "High": "15.82", "Low": "15.25", "Date": "2016-09-07", "Close": "15.63", "Open": "15.25"}, {"Volume": "158000", "Symbol": "ADMS", "Adj_Close": "15.19", "High": "15.35", "Low": "14.70", "Date": "2016-09-06", "Close": "15.19", "Open": "14.85"}, {"Volume": "269200", "Symbol": "ADMS", "Adj_Close": "14.76", "High": "15.10", "Low": "14.49", "Date": "2016-09-02", "Close": "14.76", "Open": "15.05"}, {"Volume": "441300", "Symbol": "ADMS", "Adj_Close": "15.07", "High": "15.12", "Low": "13.74", "Date": "2016-09-01", "Close": "15.07", "Open": "13.74"}, {"Volume": "690100", "Symbol": "ADMS", "Adj_Close": "13.67", "High": "14.50", "Low": "13.10", "Date": "2016-08-31", "Close": "13.67", "Open": "13.10"}, {"Volume": "171600", "Symbol": "ADMS", "Adj_Close": "12.99", "High": "13.16", "Low": "12.86", "Date": "2016-08-30", "Close": "12.99", "Open": "13.07"}, {"Volume": "141700", "Symbol": "ADMS", "Adj_Close": "13.11", "High": "13.27", "Low": "12.95", "Date": "2016-08-29", "Close": "13.11", "Open": "13.15"}, {"Volume": "292500", "Symbol": "ADMS", "Adj_Close": "13.11", "High": "13.47", "Low": "12.90", "Date": "2016-08-26", "Close": "13.11", "Open": "13.35"}, {"Volume": "274000", "Symbol": "ADMS", "Adj_Close": "13.31", "High": "14.02", "Low": "13.24", "Date": "2016-08-25", "Close": "13.31", "Open": "13.69"}, {"Volume": "391300", "Symbol": "ADMS", "Adj_Close": "13.72", "High": "14.50", "Low": "13.54", "Date": "2016-08-24", "Close": "13.72", "Open": "14.28"}, {"Volume": "108200", "Symbol": "ADMS", "Adj_Close": "14.30", "High": "14.42", "Low": "14.15", "Date": "2016-08-23", "Close": "14.30", "Open": "14.21"}, {"Volume": "201100", "Symbol": "ADMS", "Adj_Close": "14.11", "High": "14.24", "Low": "13.93", "Date": "2016-08-22", "Close": "14.11", "Open": "14.18"}, {"Volume": "234000", "Symbol": "ADMS", "Adj_Close": "14.03", "High": "14.37", "Low": "13.86", "Date": "2016-08-19", "Close": "14.03", "Open": "14.27"}, {"Volume": "169900", "Symbol": "ADMS", "Adj_Close": "14.32", "High": "14.39", "Low": "13.91", "Date": "2016-08-18", "Close": "14.32", "Open": "13.91"}, {"Volume": "157000", "Symbol": "ADMS", "Adj_Close": "13.93", "High": "14.08", "Low": "13.65", "Date": "2016-08-17", "Close": "13.93", "Open": "14.00"}, {"Volume": "138700", "Symbol": "ADMS", "Adj_Close": "14.01", "High": "14.25", "Low": "13.89", "Date": "2016-08-16", "Close": "14.01", "Open": "14.19"}, {"Volume": "214800", "Symbol": "ADMS", "Adj_Close": "14.21", "High": "14.47", "Low": "13.52", "Date": "2016-08-15", "Close": "14.21", "Open": "13.52"}, {"Volume": "158700", "Symbol": "ADMS", "Adj_Close": "13.50", "High": "13.57", "Low": "13.31", "Date": "2016-08-12", "Close": "13.50", "Open": "13.51"}, {"Volume": "272800", "Symbol": "ADMS", "Adj_Close": "13.45", "High": "13.55", "Low": "12.84", "Date": "2016-08-11", "Close": "13.45", "Open": "13.03"}, {"Volume": "230300", "Symbol": "ADMS", "Adj_Close": "12.95", "High": "13.24", "Low": "12.81", "Date": "2016-08-10", "Close": "12.95", "Open": "13.20"}, {"Volume": "115000", "Symbol": "ADMS", "Adj_Close": "13.25", "High": "13.509", "Low": "13.11", "Date": "2016-08-09", "Close": "13.25", "Open": "13.31"}, {"Volume": "233400", "Symbol": "ADMS", "Adj_Close": "13.25", "High": "13.81", "Low": "13.10", "Date": "2016-08-08", "Close": "13.25", "Open": "13.72"}, {"Volume": "380600", "Symbol": "ADMS", "Adj_Close": "13.68", "High": "14.37", "Low": "13.31", "Date": "2016-08-05", "Close": "13.68", "Open": "14.37"}, {"Volume": "83200", "Symbol": "ADMS", "Adj_Close": "14.51", "High": "15.089", "Low": "14.49", "Date": "2016-08-04", "Close": "14.51", "Open": "14.89"}, {"Volume": "84100", "Symbol": "ADMS", "Adj_Close": "14.83", "High": "14.83", "Low": "14.20", "Date": "2016-08-03", "Close": "14.83", "Open": "14.45"}, {"Volume": "169900", "Symbol": "ADMS", "Adj_Close": "14.46", "High": "14.94", "Low": "14.14", "Date": "2016-08-02", "Close": "14.46", "Open": "14.80"}, {"Volume": "183100", "Symbol": "ADMS", "Adj_Close": "14.80", "High": "15.20", "Low": "14.71", "Date": "2016-08-01", "Close": "14.80", "Open": "15.16"}, {"Volume": "781000", "Symbol": "ADMS", "Adj_Close": "15.10", "High": "15.32", "Low": "13.93", "Date": "2016-07-29", "Close": "15.10", "Open": "14.36"}, {"Volume": "170200", "Symbol": "ADMS", "Adj_Close": "14.36", "High": "14.775", "Low": "14.26", "Date": "2016-07-28", "Close": "14.36", "Open": "14.58"}, {"Volume": "200700", "Symbol": "ADMS", "Adj_Close": "14.60", "High": "14.79", "Low": "14.18", "Date": "2016-07-27", "Close": "14.60", "Open": "14.30"}, {"Volume": "292700", "Symbol": "ADMS", "Adj_Close": "14.24", "High": "14.57", "Low": "14.12", "Date": "2016-07-26", "Close": "14.24", "Open": "14.45"}, {"Volume": "363500", "Symbol": "ADMS", "Adj_Close": "14.53", "High": "16.030001", "Low": "14.47", "Date": "2016-07-25", "Close": "14.53", "Open": "15.37"}, {"Volume": "176800", "Symbol": "ADMS", "Adj_Close": "15.51", "High": "16.406", "Low": "15.37", "Date": "2016-07-22", "Close": "15.51", "Open": "16.24"}, {"Volume": "531200", "Symbol": "ADMS", "Adj_Close": "16.24", "High": "16.469999", "Low": "14.90", "Date": "2016-07-21", "Close": "16.24", "Open": "14.90"}, {"Volume": "316700", "Symbol": "ADMS", "Adj_Close": "14.81", "High": "14.99", "Low": "14.70", "Date": "2016-07-20", "Close": "14.81", "Open": "14.93"}, {"Volume": "270500", "Symbol": "ADMS", "Adj_Close": "14.82", "High": "15.76", "Low": "14.73", "Date": "2016-07-19", "Close": "14.82", "Open": "15.40"}, {"Volume": "143400", "Symbol": "ADMS", "Adj_Close": "15.18", "High": "15.53", "Low": "14.99", "Date": "2016-07-18", "Close": "15.18", "Open": "15.48"}, {"Volume": "197400", "Symbol": "ADMS", "Adj_Close": "15.50", "High": "15.76", "Low": "15.26", "Date": "2016-07-15", "Close": "15.50", "Open": "15.58"}, {"Volume": "259900", "Symbol": "ADMS", "Adj_Close": "15.47", "High": "16.280001", "Low": "15.33", "Date": "2016-07-14", "Close": "15.47", "Open": "16.280001"}, {"Volume": "319200", "Symbol": "ADMS", "Adj_Close": "16.139999", "High": "16.870001", "Low": "16.040001", "Date": "2016-07-13", "Close": "16.139999", "Open": "16.700001"}, {"Volume": "324500", "Symbol": "ADMS", "Adj_Close": "16.620001", "High": "16.77", "Low": "15.70", "Date": "2016-07-12", "Close": "16.620001", "Open": "15.73"}, {"Volume": "155100", "Symbol": "ADMS", "Adj_Close": "15.65", "High": "15.95", "Low": "15.46", "Date": "2016-07-11", "Close": "15.65", "Open": "15.77"}, {"Volume": "237800", "Symbol": "ADMS", "Adj_Close": "15.69", "High": "15.75", "Low": "15.21", "Date": "2016-07-08", "Close": "15.69", "Open": "15.75"}, {"Volume": "188600", "Symbol": "ADMS", "Adj_Close": "15.49", "High": "16.23", "Low": "15.31", "Date": "2016-07-07", "Close": "15.49", "Open": "15.80"}, {"Volume": "233900", "Symbol": "ADMS", "Adj_Close": "15.84", "High": "15.95", "Low": "15.15", "Date": "2016-07-06", "Close": "15.84", "Open": "15.23"}, {"Volume": "141400", "Symbol": "ADMS", "Adj_Close": "15.38", "High": "15.547", "Low": "14.99", "Date": "2016-07-05", "Close": "15.38", "Open": "15.48"}, {"Volume": "258200", "Symbol": "ADMS", "Adj_Close": "15.55", "High": "15.61", "Low": "15.03", "Date": "2016-07-01", "Close": "15.55", "Open": "15.18"}, {"Volume": "209300", "Symbol": "ADMS", "Adj_Close": "15.14", "High": "16.24", "Low": "14.50", "Date": "2016-06-30", "Close": "15.14", "Open": "15.50"}, {"Volume": "275700", "Symbol": "ADMS", "Adj_Close": "15.48", "High": "15.74", "Low": "15.41", "Date": "2016-06-29", "Close": "15.48", "Open": "15.65"}, {"Volume": "432500", "Symbol": "ADMS", "Adj_Close": "15.52", "High": "15.69", "Low": "14.69", "Date": "2016-06-28", "Close": "15.52", "Open": "15.05"}, {"Volume": "407800", "Symbol": "ADMS", "Adj_Close": "14.72", "High": "15.745", "Low": "14.42", "Date": "2016-06-27", "Close": "14.72", "Open": "15.30"}, {"Volume": "919300", "Symbol": "ADMS", "Adj_Close": "15.52", "High": "15.91", "Low": "15.14", "Date": "2016-06-24", "Close": "15.52", "Open": "15.50"}, {"Volume": "247700", "Symbol": "ADMS", "Adj_Close": "16.24", "High": "16.67", "Low": "15.98", "Date": "2016-06-23", "Close": "16.24", "Open": "16.389999"}, {"Volume": "300100", "Symbol": "ADMS", "Adj_Close": "16.389999", "High": "17.10", "Low": "15.94", "Date": "2016-06-22", "Close": "16.389999", "Open": "16.969999"}, {"Volume": "333100", "Symbol": "ADMS", "Adj_Close": "16.620001", "High": "18.35", "Low": "16.299999", "Date": "2016-06-21", "Close": "16.620001", "Open": "18.129999"}, {"Volume": "320100", "Symbol": "ADMS", "Adj_Close": "18.059999", "High": "18.60", "Low": "17.41", "Date": "2016-06-20", "Close": "18.059999", "Open": "17.82"}, {"Volume": "320400", "Symbol": "ADMS", "Adj_Close": "17.50", "High": "17.870001", "Low": "17.030001", "Date": "2016-06-17", "Close": "17.50", "Open": "17.030001"}, {"Volume": "179500", "Symbol": "ADMS", "Adj_Close": "16.870001", "High": "17.40", "Low": "16.469999", "Date": "2016-06-16", "Close": "16.870001", "Open": "16.90"}, {"Volume": "134400", "Symbol": "ADMS", "Adj_Close": "16.27", "High": "16.549999", "Low": "16.01", "Date": "2016-06-15", "Close": "16.27", "Open": "16.209999"}, {"Volume": "271100", "Symbol": "ADMS", "Adj_Close": "16.120001", "High": "16.67", "Low": "15.41", "Date": "2016-06-14", "Close": "16.120001", "Open": "16.27"}, {"Volume": "221900", "Symbol": "ADMS", "Adj_Close": "15.87", "High": "16.379999", "Low": "15.70", "Date": "2016-06-13", "Close": "15.87", "Open": "15.89"}, {"Volume": "292400", "Symbol": "ADMS", "Adj_Close": "15.97", "High": "17.34", "Low": "15.51", "Date": "2016-06-10", "Close": "15.97", "Open": "16.68"}, {"Volume": "143200", "Symbol": "ADMS", "Adj_Close": "17.00", "High": "17.584999", "Low": "16.870001", "Date": "2016-06-09", "Close": "17.00", "Open": "17.09"}, {"Volume": "106900", "Symbol": "ADMS", "Adj_Close": "17.290001", "High": "17.35", "Low": "16.85", "Date": "2016-06-08", "Close": "17.290001", "Open": "17.32"}, {"Volume": "124200", "Symbol": "ADMS", "Adj_Close": "17.23", "High": "17.42", "Low": "16.790001", "Date": "2016-06-07", "Close": "17.23", "Open": "17.25"}, {"Volume": "163300", "Symbol": "ADMS", "Adj_Close": "17.375", "High": "17.59", "Low": "16.85", "Date": "2016-06-06", "Close": "17.375", "Open": "17.17"}, {"Volume": "161000", "Symbol": "ADMS", "Adj_Close": "17.030001", "High": "17.445", "Low": "16.25", "Date": "2016-06-03", "Close": "17.030001", "Open": "17.43"}, {"Volume": "192700", "Symbol": "ADMS", "Adj_Close": "17.559999", "High": "17.709999", "Low": "16.969999", "Date": "2016-06-02", "Close": "17.559999", "Open": "16.99"}, {"Volume": "166700", "Symbol": "ADMS", "Adj_Close": "17.07", "High": "17.26", "Low": "16.110001", "Date": "2016-06-01", "Close": "17.07", "Open": "16.780001"}, {"Volume": "139200", "Symbol": "ADMS", "Adj_Close": "16.82", "High": "17.00", "Low": "16.530001", "Date": "2016-05-31", "Close": "16.82", "Open": "16.530001"}, {"Volume": "148600", "Symbol": "ADMS", "Adj_Close": "16.379999", "High": "16.41", "Low": "15.95", "Date": "2016-05-27", "Close": "16.379999", "Open": "16.24"}, {"Volume": "99300", "Symbol": "ADMS", "Adj_Close": "16.139999", "High": "16.43", "Low": "16.139999", "Date": "2016-05-26", "Close": "16.139999", "Open": "16.280001"}, {"Volume": "147200", "Symbol": "ADMS", "Adj_Close": "16.27", "High": "16.450001", "Low": "16.129999", "Date": "2016-05-25", "Close": "16.27", "Open": "16.299999"}, {"Volume": "166100", "Symbol": "ADMS", "Adj_Close": "16.15", "High": "16.309999", "Low": "15.88", "Date": "2016-05-24", "Close": "16.15", "Open": "16.083"}, {"Volume": "150800", "Symbol": "ADMS", "Adj_Close": "16.049999", "High": "16.43", "Low": "15.80", "Date": "2016-05-23", "Close": "16.049999", "Open": "15.89"}, {"Volume": "195300", "Symbol": "ADMS", "Adj_Close": "15.83", "High": "15.95", "Low": "14.99", "Date": "2016-05-20", "Close": "15.83", "Open": "15.21"}, {"Volume": "191300", "Symbol": "ADMS", "Adj_Close": "15.04", "High": "15.69", "Low": "14.93", "Date": "2016-05-19", "Close": "15.04", "Open": "15.29"}, {"Volume": "276100", "Symbol": "ADMS", "Adj_Close": "15.43", "High": "15.55", "Low": "15.09", "Date": "2016-05-18", "Close": "15.43", "Open": "15.09"}, {"Volume": "240100", "Symbol": "ADMS", "Adj_Close": "15.22", "High": "15.62", "Low": "15.10", "Date": "2016-05-17", "Close": "15.22", "Open": "15.44"}, {"Volume": "353700", "Symbol": "ADMS", "Adj_Close": "15.40", "High": "15.51", "Low": "14.47", "Date": "2016-05-16", "Close": "15.40", "Open": "14.50"}, {"Volume": "211900", "Symbol": "ADMS", "Adj_Close": "14.58", "High": "14.84", "Low": "14.11", "Date": "2016-05-13", "Close": "14.58", "Open": "14.23"}, {"Volume": "238000", "Symbol": "ADMS", "Adj_Close": "14.28", "High": "14.75", "Low": "13.94", "Date": "2016-05-12", "Close": "14.28", "Open": "14.75"}, {"Volume": "350100", "Symbol": "ADMS", "Adj_Close": "14.81", "High": "16.299999", "Low": "14.73", "Date": "2016-05-11", "Close": "14.81", "Open": "15.04"}, {"Volume": "251900", "Symbol": "ADMS", "Adj_Close": "15.10", "High": "15.30", "Low": "14.72", "Date": "2016-05-10", "Close": "15.10", "Open": "15.14"}, {"Volume": "225700", "Symbol": "ADMS", "Adj_Close": "15.10", "High": "15.46", "Low": "14.44", "Date": "2016-05-09", "Close": "15.10", "Open": "14.76"}, {"Volume": "242400", "Symbol": "ADMS", "Adj_Close": "14.70", "High": "15.07", "Low": "14.50", "Date": "2016-05-06", "Close": "14.70", "Open": "15.07"}, {"Volume": "245900", "Symbol": "ADMS", "Adj_Close": "14.96", "High": "15.99", "Low": "14.96", "Date": "2016-05-05", "Close": "14.96", "Open": "15.92"}, {"Volume": "226200", "Symbol": "ADMS", "Adj_Close": "15.73", "High": "16.18", "Low": "15.43", "Date": "2016-05-04", "Close": "15.73", "Open": "16.07"}, {"Volume": "264400", "Symbol": "ADMS", "Adj_Close": "16.15", "High": "16.93", "Low": "16.129999", "Date": "2016-05-03", "Close": "16.15", "Open": "16.82"}, {"Volume": "211200", "Symbol": "ADMS", "Adj_Close": "17.00", "High": "17.030001", "Low": "16.299999", "Date": "2016-05-02", "Close": "17.00", "Open": "16.90"}, {"Volume": "412100", "Symbol": "ADMS", "Adj_Close": "16.879999", "High": "17.27", "Low": "16.290001", "Date": "2016-04-29", "Close": "16.879999", "Open": "16.57"}, {"Volume": "1013900", "Symbol": "ADMS", "Adj_Close": "16.690001", "High": "19.00", "Low": "14.58", "Date": "2016-04-28", "Close": "16.690001", "Open": "18.959999"}, {"Volume": "446700", "Symbol": "ADMS", "Adj_Close": "17.50", "High": "18.00", "Low": "17.25", "Date": "2016-04-27", "Close": "17.50", "Open": "17.549999"}, {"Volume": "271200", "Symbol": "ADMS", "Adj_Close": "17.620001", "High": "18.49", "Low": "17.549999", "Date": "2016-04-26", "Close": "17.620001", "Open": "18.49"}, {"Volume": "136300", "Symbol": "ADMS", "Adj_Close": "18.379999", "High": "19.15", "Low": "18.26", "Date": "2016-04-25", "Close": "18.379999", "Open": "18.85"}, {"Volume": "288700", "Symbol": "ADMS", "Adj_Close": "18.83", "High": "18.83", "Low": "17.700001", "Date": "2016-04-22", "Close": "18.83", "Open": "18.110001"}, {"Volume": "180200", "Symbol": "ADMS", "Adj_Close": "18.08", "High": "18.299999", "Low": "17.209999", "Date": "2016-04-21", "Close": "18.08", "Open": "17.24"}, {"Volume": "275100", "Symbol": "ADMS", "Adj_Close": "17.280001", "High": "18.17", "Low": "16.75", "Date": "2016-04-20", "Close": "17.280001", "Open": "18.16"}, {"Volume": "291700", "Symbol": "ADMS", "Adj_Close": "17.700001", "High": "18.978001", "Low": "17.52", "Date": "2016-04-19", "Close": "17.700001", "Open": "18.790001"}, {"Volume": "333700", "Symbol": "ADMS", "Adj_Close": "18.59", "High": "18.860001", "Low": "17.76", "Date": "2016-04-18", "Close": "18.59", "Open": "18.00"}, {"Volume": "241400", "Symbol": "ADMS", "Adj_Close": "18.059999", "High": "18.33", "Low": "17.809999", "Date": "2016-04-15", "Close": "18.059999", "Open": "18.09"}, {"Volume": "204600", "Symbol": "ADMS", "Adj_Close": "18.23", "High": "18.440001", "Low": "17.26", "Date": "2016-04-14", "Close": "18.23", "Open": "17.809999"}, {"Volume": "299300", "Symbol": "ADMS", "Adj_Close": "17.809999", "High": "17.950001", "Low": "16.57", "Date": "2016-04-13", "Close": "17.809999", "Open": "16.75"}, {"Volume": "160400", "Symbol": "ADMS", "Adj_Close": "16.60", "High": "16.950001", "Low": "16.16", "Date": "2016-04-12", "Close": "16.60", "Open": "16.690001"}, {"Volume": "156600", "Symbol": "ADMS", "Adj_Close": "16.73", "High": "17.41", "Low": "16.620001", "Date": "2016-04-11", "Close": "16.73", "Open": "17.17"}, {"Volume": "256500", "Symbol": "ADMS", "Adj_Close": "17.10", "High": "17.709999", "Low": "16.76", "Date": "2016-04-08", "Close": "17.10", "Open": "17.709999"}, {"Volume": "274000", "Symbol": "ADMS", "Adj_Close": "17.43", "High": "17.799999", "Low": "17.129999", "Date": "2016-04-07", "Close": "17.43", "Open": "17.35"}, {"Volume": "357600", "Symbol": "ADMS", "Adj_Close": "17.34", "High": "17.450001", "Low": "16.219", "Date": "2016-04-06", "Close": "17.34", "Open": "16.389999"}, {"Volume": "242600", "Symbol": "ADMS", "Adj_Close": "16.360001", "High": "16.531", "Low": "15.82", "Date": "2016-04-05", "Close": "16.360001", "Open": "16.25"}, {"Volume": "245500", "Symbol": "ADMS", "Adj_Close": "16.32", "High": "16.540001", "Low": "15.34", "Date": "2016-04-04", "Close": "16.32", "Open": "15.71"}, {"Volume": "354600", "Symbol": "ADMS", "Adj_Close": "15.65", "High": "16.02", "Low": "14.43", "Date": "2016-04-01", "Close": "15.65", "Open": "14.52"}, {"Volume": "272700", "Symbol": "ADMS", "Adj_Close": "14.46", "High": "14.87", "Low": "13.73", "Date": "2016-03-31", "Close": "14.46", "Open": "14.06"}, {"Volume": "365700", "Symbol": "ADMS", "Adj_Close": "14.12", "High": "15.08", "Low": "14.02", "Date": "2016-03-30", "Close": "14.12", "Open": "14.55"}, {"Volume": "304100", "Symbol": "ADMS", "Adj_Close": "14.54", "High": "14.57", "Low": "13.81", "Date": "2016-03-29", "Close": "14.54", "Open": "14.17"}, {"Volume": "503500", "Symbol": "ADMS", "Adj_Close": "14.16", "High": "14.595", "Low": "13.72", "Date": "2016-03-28", "Close": "14.16", "Open": "14.23"}, {"Volume": "255000", "Symbol": "ADMS", "Adj_Close": "14.17", "High": "14.385", "Low": "13.305", "Date": "2016-03-24", "Close": "14.17", "Open": "13.46"}, {"Volume": "280400", "Symbol": "ADMS", "Adj_Close": "13.59", "High": "14.28", "Low": "13.301", "Date": "2016-03-23", "Close": "13.59", "Open": "14.13"}, {"Volume": "280400", "Symbol": "ADMS", "Adj_Close": "14.12", "High": "14.41", "Low": "13.712", "Date": "2016-03-22", "Close": "14.12", "Open": "13.82"}, {"Volume": "526200", "Symbol": "ADMS", "Adj_Close": "13.91", "High": "14.44", "Low": "12.57", "Date": "2016-03-21", "Close": "13.91", "Open": "12.63"}, {"Volume": "487200", "Symbol": "ADMS", "Adj_Close": "12.64", "High": "12.765", "Low": "12.07", "Date": "2016-03-18", "Close": "12.64", "Open": "12.51"}, {"Volume": "516500", "Symbol": "ADMS", "Adj_Close": "12.42", "High": "13.18", "Low": "12.09", "Date": "2016-03-17", "Close": "12.42", "Open": "12.88"}, {"Volume": "178600", "Symbol": "ADMS", "Adj_Close": "12.99", "High": "13.46", "Low": "12.93", "Date": "2016-03-16", "Close": "12.99", "Open": "13.28"}, {"Volume": "298400", "Symbol": "ADMS", "Adj_Close": "13.35", "High": "14.76", "Low": "13.26", "Date": "2016-03-15", "Close": "13.35", "Open": "14.75"}, {"Volume": "245800", "Symbol": "ADMS", "Adj_Close": "14.89", "High": "15.33", "Low": "14.19", "Date": "2016-03-14", "Close": "14.89", "Open": "14.19"}, {"Volume": "227700", "Symbol": "ADMS", "Adj_Close": "14.27", "High": "14.30", "Low": "13.66", "Date": "2016-03-11", "Close": "14.27", "Open": "13.74"}, {"Volume": "238500", "Symbol": "ADMS", "Adj_Close": "13.64", "High": "14.28", "Low": "13.30", "Date": "2016-03-10", "Close": "13.64", "Open": "13.95"}, {"Volume": "315000", "Symbol": "ADMS", "Adj_Close": "13.81", "High": "14.09", "Low": "13.51", "Date": "2016-03-09", "Close": "13.81", "Open": "14.00"}, {"Volume": "411900", "Symbol": "ADMS", "Adj_Close": "13.98", "High": "15.30", "Low": "13.90", "Date": "2016-03-08", "Close": "13.98", "Open": "15.25"}, {"Volume": "358000", "Symbol": "ADMS", "Adj_Close": "15.29", "High": "15.62", "Low": "13.28", "Date": "2016-03-07", "Close": "15.29", "Open": "13.52"}, {"Volume": "436300", "Symbol": "ADMS", "Adj_Close": "13.66", "High": "14.25", "Low": "13.38", "Date": "2016-03-04", "Close": "13.66", "Open": "14.19"}, {"Volume": "352000", "Symbol": "ADMS", "Adj_Close": "14.27", "High": "14.42", "Low": "13.73", "Date": "2016-03-03", "Close": "14.27", "Open": "13.99"}, {"Volume": "236100", "Symbol": "ADMS", "Adj_Close": "13.92", "High": "14.06", "Low": "12.295", "Date": "2016-03-02", "Close": "13.92", "Open": "13.18"}, {"Volume": "276400", "Symbol": "ADMS", "Adj_Close": "13.20", "High": "13.31", "Low": "12.28", "Date": "2016-03-01", "Close": "13.20", "Open": "12.99"}, {"Volume": "357500", "Symbol": "ADMS", "Adj_Close": "12.80", "High": "13.33", "Low": "12.50", "Date": "2016-02-29", "Close": "12.80", "Open": "13.12"}, {"Volume": "350900", "Symbol": "ADMS", "Adj_Close": "13.20", "High": "13.47", "Low": "12.75", "Date": "2016-02-26", "Close": "13.20", "Open": "13.00"}, {"Volume": "388100", "Symbol": "ADMS", "Adj_Close": "12.87", "High": "13.105", "Low": "12.02", "Date": "2016-02-25", "Close": "12.87", "Open": "12.90"}, {"Volume": "1016900", "Symbol": "ADMS", "Adj_Close": "12.80", "High": "14.54", "Low": "12.65", "Date": "2016-02-24", "Close": "12.80", "Open": "14.44"}, {"Volume": "366100", "Symbol": "ADMS", "Adj_Close": "14.80", "High": "15.13", "Low": "14.50", "Date": "2016-02-23", "Close": "14.80", "Open": "14.61"}, {"Volume": "163000", "Symbol": "ADMS", "Adj_Close": "14.76", "High": "15.50", "Low": "14.69", "Date": "2016-02-22", "Close": "14.76", "Open": "15.05"}, {"Volume": "149800", "Symbol": "ADMS", "Adj_Close": "14.93", "High": "15.06", "Low": "14.32", "Date": "2016-02-19", "Close": "14.93", "Open": "14.70"}, {"Volume": "216600", "Symbol": "ADMS", "Adj_Close": "14.77", "High": "15.53", "Low": "14.66", "Date": "2016-02-18", "Close": "14.77", "Open": "15.37"}, {"Volume": "314800", "Symbol": "ADMS", "Adj_Close": "15.42", "High": "16.139999", "Low": "14.61", "Date": "2016-02-17", "Close": "15.42", "Open": "14.72"}, {"Volume": "436800", "Symbol": "ADMS", "Adj_Close": "14.52", "High": "14.925", "Low": "13.85", "Date": "2016-02-16", "Close": "14.52", "Open": "14.46"}, {"Volume": "236700", "Symbol": "ADMS", "Adj_Close": "14.31", "High": "14.37", "Low": "13.47", "Date": "2016-02-12", "Close": "14.31", "Open": "13.81"}, {"Volume": "204000", "Symbol": "ADMS", "Adj_Close": "13.52", "High": "13.80", "Low": "13.15", "Date": "2016-02-11", "Close": "13.52", "Open": "13.22"}, {"Volume": "355600", "Symbol": "ADMS", "Adj_Close": "13.59", "High": "14.45", "Low": "13.34", "Date": "2016-02-10", "Close": "13.59", "Open": "13.77"}, {"Volume": "329400", "Symbol": "ADMS", "Adj_Close": "13.50", "High": "14.74", "Low": "13.47", "Date": "2016-02-09", "Close": "13.50", "Open": "14.05"}, {"Volume": "329600", "Symbol": "ADMS", "Adj_Close": "14.28", "High": "15.12", "Low": "13.76", "Date": "2016-02-08", "Close": "14.28", "Open": "15.00"}, {"Volume": "392200", "Symbol": "ADMS", "Adj_Close": "15.25", "High": "16.50", "Low": "15.04", "Date": "2016-02-05", "Close": "15.25", "Open": "16.25"}, {"Volume": "330300", "Symbol": "ADMS", "Adj_Close": "16.389999", "High": "17.190001", "Low": "16.030001", "Date": "2016-02-04", "Close": "16.389999", "Open": "16.40"}, {"Volume": "480000", "Symbol": "ADMS", "Adj_Close": "16.620001", "High": "17.299999", "Low": "16.18", "Date": "2016-02-03", "Close": "16.620001", "Open": "17.10"}, {"Volume": "324100", "Symbol": "ADMS", "Adj_Close": "16.77", "High": "17.18", "Low": "16.547001", "Date": "2016-02-02", "Close": "16.77", "Open": "16.950001"}, {"Volume": "427900", "Symbol": "ADMS", "Adj_Close": "17.139999", "High": "17.719999", "Low": "16.690001", "Date": "2016-02-01", "Close": "17.139999", "Open": "17.08"}, {"Volume": "765100", "Symbol": "ADMS", "Adj_Close": "17.139999", "High": "17.556", "Low": "16.50", "Date": "2016-01-29", "Close": "17.139999", "Open": "16.959999"}, {"Volume": "507900", "Symbol": "ADMS", "Adj_Close": "17.02", "High": "18.799999", "Low": "16.940001", "Date": "2016-01-28", "Close": "17.02", "Open": "18.790001"}, {"Volume": "481800", "Symbol": "ADMS", "Adj_Close": "18.629999", "High": "20.74", "Low": "18.52", "Date": "2016-01-27", "Close": "18.629999", "Open": "20.51"}, {"Volume": "304000", "Symbol": "ADMS", "Adj_Close": "20.639999", "High": "21.58", "Low": "20.02", "Date": "2016-01-26", "Close": "20.639999", "Open": "21.58"}, {"Volume": "286500", "Symbol": "ADMS", "Adj_Close": "21.34", "High": "22.18", "Low": "20.73", "Date": "2016-01-25", "Close": "21.34", "Open": "21.65"}, {"Volume": "336100", "Symbol": "ADMS", "Adj_Close": "22.209999", "High": "23.200001", "Low": "20.440001", "Date": "2016-01-22", "Close": "22.209999", "Open": "21.41"}, {"Volume": "279400", "Symbol": "ADMS", "Adj_Close": "20.74", "High": "22.15", "Low": "20.25", "Date": "2016-01-21", "Close": "20.74", "Open": "21.35"}, {"Volume": "376600", "Symbol": "ADMS", "Adj_Close": "21.67", "High": "22.530001", "Low": "19.90", "Date": "2016-01-20", "Close": "21.67", "Open": "21.879999"}, {"Volume": "619300", "Symbol": "ADMS", "Adj_Close": "22.00", "High": "25.889999", "Low": "21.15", "Date": "2016-01-19", "Close": "22.00", "Open": "25.77"}, {"Volume": "493300", "Symbol": "ADMS", "Adj_Close": "25.01", "High": "25.639999", "Low": "23.885", "Date": "2016-01-15", "Close": "25.01", "Open": "24.75"}, {"Volume": "452100", "Symbol": "ADMS", "Adj_Close": "25.549999", "High": "26.07", "Low": "23.00", "Date": "2016-01-14", "Close": "25.549999", "Open": "23.85"}, {"Volume": "320200", "Symbol": "ADMS", "Adj_Close": "23.870001", "High": "25.110001", "Low": "23.35", "Date": "2016-01-13", "Close": "23.870001", "Open": "24.700001"}, {"Volume": "241100", "Symbol": "ADMS", "Adj_Close": "23.959999", "High": "25.145", "Low": "23.110001", "Date": "2016-01-12", "Close": "23.959999", "Open": "24.360001"}, {"Volume": "464600", "Symbol": "ADMS", "Adj_Close": "23.469999", "High": "24.709999", "Low": "22.50", "Date": "2016-01-11", "Close": "23.469999", "Open": "24.33"}, {"Volume": "489900", "Symbol": "ADMS", "Adj_Close": "24.48", "High": "24.98", "Low": "23.16", "Date": "2016-01-08", "Close": "24.48", "Open": "24.33"}, {"Volume": "1505100", "Symbol": "ADMS", "Adj_Close": "24.309999", "High": "24.879999", "Low": "22.33", "Date": "2016-01-07", "Close": "24.309999", "Open": "22.40"}, {"Volume": "427600", "Symbol": "ADMS", "Adj_Close": "23.639999", "High": "26.00", "Low": "23.40", "Date": "2016-01-06", "Close": "23.639999", "Open": "25.43"}, {"Volume": "325600", "Symbol": "ADMS", "Adj_Close": "26.059999", "High": "27.50", "Low": "25.610001", "Date": "2016-01-05", "Close": "26.059999", "Open": "27.08"}, {"Volume": "279600", "Symbol": "ADMS", "Adj_Close": "27.91", "High": "28.23", "Low": "27.09", "Date": "2016-01-04", "Close": "27.91", "Open": "27.700001"}, {"Volume": "246600", "Symbol": "ADMS", "Adj_Close": "28.32", "High": "28.73", "Low": "27.799999", "Date": "2015-12-31", "Close": "28.32", "Open": "28.57"}, {"Volume": "236800", "Symbol": "ADMS", "Adj_Close": "28.58", "High": "29.674999", "Low": "28.549999", "Date": "2015-12-30", "Close": "28.58", "Open": "28.940001"}, {"Volume": "459400", "Symbol": "ADMS", "Adj_Close": "29.280001", "High": "30.280001", "Low": "28.620001", "Date": "2015-12-29", "Close": "29.280001", "Open": "29.389999"}, {"Volume": "1263400", "Symbol": "ADMS", "Adj_Close": "29.43", "High": "31.84", "Low": "28.780001", "Date": "2015-12-28", "Close": "29.43", "Open": "29.67"}, {"Volume": "3282800", "Symbol": "ADMS", "Adj_Close": "29.959999", "High": "31.82", "Low": "28.50", "Date": "2015-12-24", "Close": "29.959999", "Open": "29.959999"}, {"Volume": "7821500", "Symbol": "ADMS", "Adj_Close": "30.85", "High": "30.969999", "Low": "22.50", "Date": "2015-12-23", "Close": "30.85", "Open": "22.76"}, {"Volume": "110700", "Symbol": "ADMS", "Adj_Close": "16.860001", "High": "16.969999", "Low": "15.91", "Date": "2015-12-22", "Close": "16.860001", "Open": "16.559999"}, {"Volume": "230000", "Symbol": "ADMS", "Adj_Close": "16.51", "High": "16.60", "Low": "14.82", "Date": "2015-12-21", "Close": "16.51", "Open": "14.88"}, {"Volume": "660800", "Symbol": "ADMS", "Adj_Close": "14.79", "High": "15.175", "Low": "14.71", "Date": "2015-12-18", "Close": "14.79", "Open": "14.71"}, {"Volume": "171500", "Symbol": "ADMS", "Adj_Close": "14.83", "High": "15.29", "Low": "14.75", "Date": "2015-12-17", "Close": "14.83", "Open": "15.11"}, {"Volume": "142000", "Symbol": "ADMS", "Adj_Close": "14.98", "High": "15.41", "Low": "14.702", "Date": "2015-12-16", "Close": "14.98", "Open": "15.04"}, {"Volume": "241200", "Symbol": "ADMS", "Adj_Close": "14.89", "High": "15.49", "Low": "14.60", "Date": "2015-12-15", "Close": "14.89", "Open": "15.22"}, {"Volume": "93500", "Symbol": "ADMS", "Adj_Close": "15.03", "High": "15.38", "Low": "14.77", "Date": "2015-12-14", "Close": "15.03", "Open": "14.89"}, {"Volume": "100600", "Symbol": "ADMS", "Adj_Close": "14.85", "High": "15.42", "Low": "14.625", "Date": "2015-12-11", "Close": "14.85", "Open": "15.30"}, {"Volume": "146100", "Symbol": "ADMS", "Adj_Close": "15.66", "High": "15.98", "Low": "15.50", "Date": "2015-12-10", "Close": "15.66", "Open": "15.78"}, {"Volume": "71600", "Symbol": "ADMS", "Adj_Close": "15.87", "High": "16.129999", "Low": "15.69", "Date": "2015-12-09", "Close": "15.87", "Open": "15.94"}, {"Volume": "171000", "Symbol": "ADMS", "Adj_Close": "15.94", "High": "16.475", "Low": "15.68", "Date": "2015-12-08", "Close": "15.94", "Open": "15.68"}, {"Volume": "65900", "Symbol": "ADMS", "Adj_Close": "15.91", "High": "16.23", "Low": "15.60", "Date": "2015-12-07", "Close": "15.91", "Open": "16.23"}, {"Volume": "65700", "Symbol": "ADMS", "Adj_Close": "16.41", "High": "16.629999", "Low": "15.67", "Date": "2015-12-04", "Close": "16.41", "Open": "16.370001"}, {"Volume": "96600", "Symbol": "ADMS", "Adj_Close": "16.290001", "High": "17.00", "Low": "16.104", "Date": "2015-12-03", "Close": "16.290001", "Open": "16.50"}, {"Volume": "63200", "Symbol": "ADMS", "Adj_Close": "16.52", "High": "17.00", "Low": "16.41", "Date": "2015-12-02", "Close": "16.52", "Open": "16.41"}, {"Volume": "65100", "Symbol": "ADMS", "Adj_Close": "16.51", "High": "16.549999", "Low": "15.87", "Date": "2015-12-01", "Close": "16.51", "Open": "16.00"}, {"Volume": "97000", "Symbol": "ADMS", "Adj_Close": "15.97", "High": "16.559999", "Low": "15.60", "Date": "2015-11-30", "Close": "15.97", "Open": "16.32"}, {"Volume": "20700", "Symbol": "ADMS", "Adj_Close": "16.280001", "High": "16.530001", "Low": "15.69", "Date": "2015-11-27", "Close": "16.280001", "Open": "15.86"}, {"Volume": "33500", "Symbol": "ADMS", "Adj_Close": "15.93", "High": "15.96", "Low": "15.55", "Date": "2015-11-25", "Close": "15.93", "Open": "15.57"}, {"Volume": "40100", "Symbol": "ADMS", "Adj_Close": "15.65", "High": "15.86", "Low": "15.45", "Date": "2015-11-24", "Close": "15.65", "Open": "15.75"}, {"Volume": "61400", "Symbol": "ADMS", "Adj_Close": "15.89", "High": "16.50", "Low": "15.77", "Date": "2015-11-23", "Close": "15.89", "Open": "16.18"}, {"Volume": "69800", "Symbol": "ADMS", "Adj_Close": "16.26", "High": "16.59", "Low": "15.59", "Date": "2015-11-20", "Close": "16.26", "Open": "15.84"}, {"Volume": "96900", "Symbol": "ADMS", "Adj_Close": "15.74", "High": "15.84", "Low": "15.56", "Date": "2015-11-19", "Close": "15.74", "Open": "15.72"}, {"Volume": "110300", "Symbol": "ADMS", "Adj_Close": "15.70", "High": "15.87", "Low": "14.93", "Date": "2015-11-18", "Close": "15.70", "Open": "15.34"}, {"Volume": "103000", "Symbol": "ADMS", "Adj_Close": "15.32", "High": "15.96", "Low": "15.00", "Date": "2015-11-17", "Close": "15.32", "Open": "15.00"}, {"Volume": "127900", "Symbol": "ADMS", "Adj_Close": "15.29", "High": "15.63", "Low": "14.882", "Date": "2015-11-16", "Close": "15.29", "Open": "15.63"}, {"Volume": "71600", "Symbol": "ADMS", "Adj_Close": "15.74", "High": "15.97", "Low": "15.00", "Date": "2015-11-13", "Close": "15.74", "Open": "15.14"}, {"Volume": "62200", "Symbol": "ADMS", "Adj_Close": "15.16", "High": "15.83", "Low": "15.11", "Date": "2015-11-12", "Close": "15.16", "Open": "15.83"}, {"Volume": "72300", "Symbol": "ADMS", "Adj_Close": "15.99", "High": "16.299999", "Low": "15.33", "Date": "2015-11-11", "Close": "15.99", "Open": "15.67"}, {"Volume": "70700", "Symbol": "ADMS", "Adj_Close": "15.66", "High": "16.15", "Low": "15.38", "Date": "2015-11-10", "Close": "15.66", "Open": "15.68"}, {"Volume": "142500", "Symbol": "ADMS", "Adj_Close": "15.67", "High": "16.42", "Low": "15.605", "Date": "2015-11-09", "Close": "15.67", "Open": "16.370001"}, {"Volume": "85200", "Symbol": "ADMS", "Adj_Close": "16.42", "High": "17.01", "Low": "15.89", "Date": "2015-11-06", "Close": "16.42", "Open": "16.540001"}, {"Volume": "102400", "Symbol": "ADMS", "Adj_Close": "16.540001", "High": "17.09", "Low": "15.88", "Date": "2015-11-05", "Close": "16.540001", "Open": "17.09"}, {"Volume": "112100", "Symbol": "ADMS", "Adj_Close": "17.120001", "High": "17.129999", "Low": "16.416", "Date": "2015-11-04", "Close": "17.120001", "Open": "16.59"}, {"Volume": "140500", "Symbol": "ADMS", "Adj_Close": "16.610001", "High": "16.67", "Low": "15.39", "Date": "2015-11-03", "Close": "16.610001", "Open": "16.139999"}, {"Volume": "136500", "Symbol": "ADMS", "Adj_Close": "16.120001", "High": "16.32", "Low": "14.79", "Date": "2015-11-02", "Close": "16.120001", "Open": "14.87"}, {"Volume": "112200", "Symbol": "ADMS", "Adj_Close": "14.76", "High": "14.89", "Low": "14.29", "Date": "2015-10-30", "Close": "14.76", "Open": "14.75"}, {"Volume": "80000", "Symbol": "ADMS", "Adj_Close": "14.76", "High": "15.40", "Low": "14.70", "Date": "2015-10-29", "Close": "14.76", "Open": "15.10"}, {"Volume": "72000", "Symbol": "ADMS", "Adj_Close": "15.15", "High": "15.17", "Low": "14.25", "Date": "2015-10-28", "Close": "15.15", "Open": "14.25"}, {"Volume": "140400", "Symbol": "ADMS", "Adj_Close": "14.26", "High": "14.50", "Low": "13.98", "Date": "2015-10-27", "Close": "14.26", "Open": "14.17"}, {"Volume": "78400", "Symbol": "ADMS", "Adj_Close": "14.21", "High": "14.45", "Low": "13.97", "Date": "2015-10-26", "Close": "14.21", "Open": "14.12"}, {"Volume": "82400", "Symbol": "ADMS", "Adj_Close": "14.13", "High": "14.31", "Low": "13.51", "Date": "2015-10-23", "Close": "14.13", "Open": "13.56"}, {"Volume": "334700", "Symbol": "ADMS", "Adj_Close": "13.56", "High": "13.76", "Low": "12.73", "Date": "2015-10-22", "Close": "13.56", "Open": "13.56"}, {"Volume": "246500", "Symbol": "ADMS", "Adj_Close": "13.33", "High": "14.53", "Low": "13.11", "Date": "2015-10-21", "Close": "13.33", "Open": "14.53"}, {"Volume": "149100", "Symbol": "ADMS", "Adj_Close": "14.42", "High": "14.909", "Low": "14.30", "Date": "2015-10-20", "Close": "14.42", "Open": "14.76"}, {"Volume": "163600", "Symbol": "ADMS", "Adj_Close": "14.79", "High": "15.39", "Low": "14.38", "Date": "2015-10-19", "Close": "14.79", "Open": "14.84"}, {"Volume": "129900", "Symbol": "ADMS", "Adj_Close": "14.89", "High": "15.53", "Low": "14.67", "Date": "2015-10-16", "Close": "14.89", "Open": "15.38"}, {"Volume": "129600", "Symbol": "ADMS", "Adj_Close": "15.32", "High": "15.41", "Low": "14.25", "Date": "2015-10-15", "Close": "15.32", "Open": "14.86"}, {"Volume": "108700", "Symbol": "ADMS", "Adj_Close": "14.92", "High": "15.61", "Low": "14.84", "Date": "2015-10-14", "Close": "14.92", "Open": "15.13"}, {"Volume": "144400", "Symbol": "ADMS", "Adj_Close": "15.06", "High": "16.16", "Low": "15.03", "Date": "2015-10-13", "Close": "15.06", "Open": "15.10"}, {"Volume": "125100", "Symbol": "ADMS", "Adj_Close": "15.31", "High": "15.75", "Low": "15.23", "Date": "2015-10-12", "Close": "15.31", "Open": "15.71"}, {"Volume": "109100", "Symbol": "ADMS", "Adj_Close": "15.66", "High": "16.049999", "Low": "15.34", "Date": "2015-10-09", "Close": "15.66", "Open": "15.52"}, {"Volume": "54700", "Symbol": "ADMS", "Adj_Close": "15.42", "High": "15.60", "Low": "15.05", "Date": "2015-10-08", "Close": "15.42", "Open": "15.48"}, {"Volume": "105500", "Symbol": "ADMS", "Adj_Close": "15.63", "High": "15.807", "Low": "14.65", "Date": "2015-10-07", "Close": "15.63", "Open": "15.10"}, {"Volume": "144000", "Symbol": "ADMS", "Adj_Close": "15.10", "High": "15.82", "Low": "14.30", "Date": "2015-10-06", "Close": "15.10", "Open": "15.82"}, {"Volume": "192600", "Symbol": "ADMS", "Adj_Close": "15.93", "High": "17.049999", "Low": "15.611", "Date": "2015-10-05", "Close": "15.93", "Open": "16.75"}, {"Volume": "123600", "Symbol": "ADMS", "Adj_Close": "16.66", "High": "17.16", "Low": "16.040001", "Date": "2015-10-02", "Close": "16.66", "Open": "16.59"}, {"Volume": "132400", "Symbol": "ADMS", "Adj_Close": "16.809999", "High": "17.200001", "Low": "16.219999", "Date": "2015-10-01", "Close": "16.809999", "Open": "16.83"}, {"Volume": "141000", "Symbol": "ADMS", "Adj_Close": "16.74", "High": "17.25", "Low": "16.379999", "Date": "2015-09-30", "Close": "16.74", "Open": "16.52"}, {"Volume": "110000", "Symbol": "ADMS", "Adj_Close": "16.370001", "High": "17.52", "Low": "16.08", "Date": "2015-09-29", "Close": "16.370001", "Open": "17.17"}, {"Volume": "174500", "Symbol": "ADMS", "Adj_Close": "17.07", "High": "17.60", "Low": "16.59", "Date": "2015-09-28", "Close": "17.07", "Open": "17.549999"}, {"Volume": "181700", "Symbol": "ADMS", "Adj_Close": "17.75", "High": "19.040001", "Low": "17.41", "Date": "2015-09-25", "Close": "17.75", "Open": "19.040001"}, {"Volume": "107500", "Symbol": "ADMS", "Adj_Close": "18.77", "High": "19.08", "Low": "18.51", "Date": "2015-09-24", "Close": "18.77", "Open": "19.07"}, {"Volume": "152200", "Symbol": "ADMS", "Adj_Close": "19.280001", "High": "19.860001", "Low": "18.77", "Date": "2015-09-23", "Close": "19.280001", "Open": "19.16"}, {"Volume": "231600", "Symbol": "ADMS", "Adj_Close": "19.200001", "High": "20.15", "Low": "18.67", "Date": "2015-09-22", "Close": "19.200001", "Open": "19.98"}, {"Volume": "92800", "Symbol": "ADMS", "Adj_Close": "20.02", "High": "21.23", "Low": "19.690001", "Date": "2015-09-21", "Close": "20.02", "Open": "21.23"}, {"Volume": "312200", "Symbol": "ADMS", "Adj_Close": "21.129999", "High": "21.860001", "Low": "20.690001", "Date": "2015-09-18", "Close": "21.129999", "Open": "20.690001"}, {"Volume": "90300", "Symbol": "ADMS", "Adj_Close": "20.940001", "High": "21.139999", "Low": "19.209999", "Date": "2015-09-17", "Close": "20.940001", "Open": "19.50"}, {"Volume": "87800", "Symbol": "ADMS", "Adj_Close": "19.59", "High": "20.52", "Low": "19.32", "Date": "2015-09-16", "Close": "19.59", "Open": "19.950001"}, {"Volume": "123700", "Symbol": "ADMS", "Adj_Close": "19.93", "High": "20.360001", "Low": "19.309999", "Date": "2015-09-15", "Close": "19.93", "Open": "19.76"}, {"Volume": "29900", "Symbol": "ADMS", "Adj_Close": "19.82", "High": "20.26", "Low": "19.50", "Date": "2015-09-14", "Close": "19.82", "Open": "19.889999"}, {"Volume": "54200", "Symbol": "ADMS", "Adj_Close": "19.93", "High": "19.959999", "Low": "19.125", "Date": "2015-09-11", "Close": "19.93", "Open": "19.43"}, {"Volume": "159500", "Symbol": "ADMS", "Adj_Close": "19.43", "High": "19.629999", "Low": "18.73", "Date": "2015-09-10", "Close": "19.43", "Open": "18.73"}, {"Volume": "58200", "Symbol": "ADMS", "Adj_Close": "18.90", "High": "20.50", "Low": "18.809999", "Date": "2015-09-09", "Close": "18.90", "Open": "19.98"}, {"Volume": "88800", "Symbol": "ADMS", "Adj_Close": "19.75", "High": "19.99", "Low": "19.09", "Date": "2015-09-08", "Close": "19.75", "Open": "19.129999"}, {"Volume": "44800", "Symbol": "ADMS", "Adj_Close": "19.00", "High": "19.200001", "Low": "18.40", "Date": "2015-09-04", "Close": "19.00", "Open": "18.639999"}, {"Volume": "81900", "Symbol": "ADMS", "Adj_Close": "18.93", "High": "19.879999", "Low": "18.879999", "Date": "2015-09-03", "Close": "18.93", "Open": "19.879999"}, {"Volume": "64600", "Symbol": "ADMS", "Adj_Close": "19.790001", "High": "19.870001", "Low": "19.27", "Date": "2015-09-02", "Close": "19.790001", "Open": "19.870001"}, {"Volume": "56700", "Symbol": "ADMS", "Adj_Close": "19.58", "High": "20.08", "Low": "19.455", "Date": "2015-09-01", "Close": "19.58", "Open": "19.790001"}, {"Volume": "69700", "Symbol": "ADMS", "Adj_Close": "20.059999", "High": "20.834999", "Low": "19.799999", "Date": "2015-08-31", "Close": "20.059999", "Open": "20.50"}, {"Volume": "107200", "Symbol": "ADMS", "Adj_Close": "20.610001", "High": "20.700001", "Low": "19.790001", "Date": "2015-08-28", "Close": "20.610001", "Open": "19.889999"}, {"Volume": "71800", "Symbol": "ADMS", "Adj_Close": "20.059999", "High": "20.358", "Low": "19.424999", "Date": "2015-08-27", "Close": "20.059999", "Open": "19.90"}, {"Volume": "77700", "Symbol": "ADMS", "Adj_Close": "19.73", "High": "19.780001", "Low": "18.690001", "Date": "2015-08-26", "Close": "19.73", "Open": "19.76"}, {"Volume": "119200", "Symbol": "ADMS", "Adj_Close": "19.26", "High": "20.07", "Low": "18.969999", "Date": "2015-08-25", "Close": "19.26", "Open": "19.77"}, {"Volume": "160200", "Symbol": "ADMS", "Adj_Close": "18.92", "High": "19.82", "Low": "18.799999", "Date": "2015-08-24", "Close": "18.92", "Open": "19.09"}, {"Volume": "127400", "Symbol": "ADMS", "Adj_Close": "20.07", "High": "20.58", "Low": "19.059999", "Date": "2015-08-21", "Close": "20.07", "Open": "19.43"}, {"Volume": "110400", "Symbol": "ADMS", "Adj_Close": "19.85", "High": "20.459999", "Low": "19.799999", "Date": "2015-08-20", "Close": "19.85", "Open": "20.049999"}, {"Volume": "106900", "Symbol": "ADMS", "Adj_Close": "20.24", "High": "20.629999", "Low": "19.610001", "Date": "2015-08-19", "Close": "20.24", "Open": "20.459999"}, {"Volume": "89300", "Symbol": "ADMS", "Adj_Close": "20.629999", "High": "21.969999", "Low": "20.49", "Date": "2015-08-18", "Close": "20.629999", "Open": "21.870001"}, {"Volume": "83900", "Symbol": "ADMS", "Adj_Close": "21.969999", "High": "22.190001", "Low": "21.639999", "Date": "2015-08-17", "Close": "21.969999", "Open": "22.02"}, {"Volume": "129600", "Symbol": "ADMS", "Adj_Close": "22.15", "High": "22.290001", "Low": "21.059999", "Date": "2015-08-14", "Close": "22.15", "Open": "22.049999"}, {"Volume": "219800", "Symbol": "ADMS", "Adj_Close": "22.15", "High": "23.959999", "Low": "22.10", "Date": "2015-08-13", "Close": "22.15", "Open": "22.700001"}, {"Volume": "259500", "Symbol": "ADMS", "Adj_Close": "22.90", "High": "23.57", "Low": "22.450001", "Date": "2015-08-12", "Close": "22.90", "Open": "23.57"}, {"Volume": "78500", "Symbol": "ADMS", "Adj_Close": "23.620001", "High": "24.35", "Low": "23.40", "Date": "2015-08-11", "Close": "23.620001", "Open": "23.60"}, {"Volume": "94400", "Symbol": "ADMS", "Adj_Close": "23.83", "High": "24.23", "Low": "23.360001", "Date": "2015-08-10", "Close": "23.83", "Open": "23.940001"}, {"Volume": "56500", "Symbol": "ADMS", "Adj_Close": "23.77", "High": "24.032", "Low": "22.700001", "Date": "2015-08-07", "Close": "23.77", "Open": "23.799999"}, {"Volume": "65600", "Symbol": "ADMS", "Adj_Close": "23.85", "High": "25.405001", "Low": "23.709999", "Date": "2015-08-06", "Close": "23.85", "Open": "24.74"}, {"Volume": "53000", "Symbol": "ADMS", "Adj_Close": "24.610001", "High": "25.75", "Low": "24.50", "Date": "2015-08-05", "Close": "24.610001", "Open": "24.77"}, {"Volume": "85900", "Symbol": "ADMS", "Adj_Close": "24.73", "High": "25.84", "Low": "24.57", "Date": "2015-08-04", "Close": "24.73", "Open": "24.719999"}, {"Volume": "84100", "Symbol": "ADMS", "Adj_Close": "24.74", "High": "25.26", "Low": "24.450001", "Date": "2015-08-03", "Close": "24.74", "Open": "24.51"}, {"Volume": "161900", "Symbol": "ADMS", "Adj_Close": "24.76", "High": "25.190001", "Low": "24.42", "Date": "2015-07-31", "Close": "24.76", "Open": "25.00"}, {"Volume": "70800", "Symbol": "ADMS", "Adj_Close": "24.93", "High": "25.24", "Low": "24.360001", "Date": "2015-07-30", "Close": "24.93", "Open": "25.24"}, {"Volume": "167300", "Symbol": "ADMS", "Adj_Close": "25.370001", "High": "26.90", "Low": "25.120001", "Date": "2015-07-29", "Close": "25.370001", "Open": "26.58"}, {"Volume": "98700", "Symbol": "ADMS", "Adj_Close": "26.540001", "High": "27.120001", "Low": "25.41", "Date": "2015-07-28", "Close": "26.540001", "Open": "26.17"}, {"Volume": "75900", "Symbol": "ADMS", "Adj_Close": "26.15", "High": "26.690001", "Low": "25.58", "Date": "2015-07-27", "Close": "26.15", "Open": "26.43"}, {"Volume": "90700", "Symbol": "ADMS", "Adj_Close": "26.799999", "High": "27.860001", "Low": "26.695", "Date": "2015-07-24", "Close": "26.799999", "Open": "27.48"}, {"Volume": "99000", "Symbol": "ADMS", "Adj_Close": "27.530001", "High": "28.235001", "Low": "27.370001", "Date": "2015-07-23", "Close": "27.530001", "Open": "27.879999"}, {"Volume": "149700", "Symbol": "ADMS", "Adj_Close": "27.75", "High": "28.299", "Low": "26.635", "Date": "2015-07-22", "Close": "27.75", "Open": "26.68"}, {"Volume": "197400", "Symbol": "ADMS", "Adj_Close": "26.92", "High": "27.209999", "Low": "25.673", "Date": "2015-07-21", "Close": "26.92", "Open": "26.73"}, {"Volume": "305900", "Symbol": "ADMS", "Adj_Close": "26.639999", "High": "30.077999", "Low": "26.200001", "Date": "2015-07-20", "Close": "26.639999", "Open": "29.91"}, {"Volume": "148700", "Symbol": "ADMS", "Adj_Close": "29.799999", "High": "29.91", "Low": "28.10", "Date": "2015-07-17", "Close": "29.799999", "Open": "29.25"}, {"Volume": "102400", "Symbol": "ADMS", "Adj_Close": "29.10", "High": "29.809999", "Low": "28.700001", "Date": "2015-07-16", "Close": "29.10", "Open": "29.110001"}, {"Volume": "314200", "Symbol": "ADMS", "Adj_Close": "28.950001", "High": "30.860001", "Low": "28.360001", "Date": "2015-07-15", "Close": "28.950001", "Open": "28.50"}, {"Volume": "237000", "Symbol": "ADMS", "Adj_Close": "28.50", "High": "29.74", "Low": "27.540001", "Date": "2015-07-14", "Close": "28.50", "Open": "28.99"}, {"Volume": "121900", "Symbol": "ADMS", "Adj_Close": "28.959999", "High": "29.610001", "Low": "27.393999", "Date": "2015-07-13", "Close": "28.959999", "Open": "27.73"}, {"Volume": "114500", "Symbol": "ADMS", "Adj_Close": "27.41", "High": "27.75", "Low": "26.43", "Date": "2015-07-10", "Close": "27.41", "Open": "26.77"}, {"Volume": "38900", "Symbol": "ADMS", "Adj_Close": "26.58", "High": "27.979", "Low": "26.27", "Date": "2015-07-09", "Close": "26.58", "Open": "26.860001"}, {"Volume": "117800", "Symbol": "ADMS", "Adj_Close": "26.52", "High": "27.860001", "Low": "26.01", "Date": "2015-07-08", "Close": "26.52", "Open": "27.18"}, {"Volume": "100700", "Symbol": "ADMS", "Adj_Close": "27.299999", "High": "27.889999", "Low": "26.33", "Date": "2015-07-07", "Close": "27.299999", "Open": "26.950001"}, {"Volume": "112700", "Symbol": "ADMS", "Adj_Close": "26.93", "High": "27.379999", "Low": "25.40", "Date": "2015-07-06", "Close": "26.93", "Open": "25.91"}, {"Volume": "70700", "Symbol": "ADMS", "Adj_Close": "26.469999", "High": "26.58", "Low": "25.969999", "Date": "2015-07-02", "Close": "26.469999", "Open": "26.49"}, {"Volume": "104600", "Symbol": "ADMS", "Adj_Close": "26.48", "High": "26.969999", "Low": "26.10", "Date": "2015-07-01", "Close": "26.48", "Open": "26.370001"}, {"Volume": "103600", "Symbol": "ADMS", "Adj_Close": "26.219999", "High": "26.49", "Low": "25.92", "Date": "2015-06-30", "Close": "26.219999", "Open": "26.030001"}, {"Volume": "152200", "Symbol": "ADMS", "Adj_Close": "25.879999", "High": "26.75", "Low": "25.15", "Date": "2015-06-29", "Close": "25.879999", "Open": "25.91"}, {"Volume": "1114200", "Symbol": "ADMS", "Adj_Close": "26.030001", "High": "27.200001", "Low": "25.309999", "Date": "2015-06-26", "Close": "26.030001", "Open": "27.040001"}, {"Volume": "221100", "Symbol": "ADMS", "Adj_Close": "26.940001", "High": "27.24", "Low": "25.84", "Date": "2015-06-25", "Close": "26.940001", "Open": "27.01"}, {"Volume": "272000", "Symbol": "ADMS", "Adj_Close": "26.65", "High": "27.50", "Low": "25.90", "Date": "2015-06-24", "Close": "26.65", "Open": "26.10"}, {"Volume": "224400", "Symbol": "ADMS", "Adj_Close": "26.059999", "High": "26.700001", "Low": "24.879999", "Date": "2015-06-23", "Close": "26.059999", "Open": "26.40"}, {"Volume": "259100", "Symbol": "ADMS", "Adj_Close": "26.309999", "High": "27.09", "Low": "26.08", "Date": "2015-06-22", "Close": "26.309999", "Open": "26.99"}, {"Volume": "234500", "Symbol": "ADMS", "Adj_Close": "26.65", "High": "27.33", "Low": "26.50", "Date": "2015-06-19", "Close": "26.65", "Open": "26.98"}, {"Volume": "453600", "Symbol": "ADMS", "Adj_Close": "27.059999", "High": "27.60", "Low": "24.291", "Date": "2015-06-18", "Close": "27.059999", "Open": "24.43"}, {"Volume": "177300", "Symbol": "ADMS", "Adj_Close": "24.27", "High": "25.549999", "Low": "23.66", "Date": "2015-06-17", "Close": "24.27", "Open": "24.799999"}, {"Volume": "578000", "Symbol": "ADMS", "Adj_Close": "24.59", "High": "25.91", "Low": "21.639999", "Date": "2015-06-16", "Close": "24.59", "Open": "22.10"}, {"Volume": "425400", "Symbol": "ADMS", "Adj_Close": "22.08", "High": "22.73", "Low": "19.32", "Date": "2015-06-15", "Close": "22.08", "Open": "19.32"}, {"Volume": "816900", "Symbol": "ADMS", "Adj_Close": "19.450001", "High": "20.43", "Low": "19.01", "Date": "2015-06-12", "Close": "19.450001", "Open": "19.90"}, {"Volume": "241600", "Symbol": "ADMS", "Adj_Close": "19.940001", "High": "19.969999", "Low": "19.375999", "Date": "2015-06-11", "Close": "19.940001", "Open": "19.969999"}, {"Volume": "248200", "Symbol": "ADMS", "Adj_Close": "19.99", "High": "20.00", "Low": "18.370001", "Date": "2015-06-10", "Close": "19.99", "Open": "18.58"}, {"Volume": "160400", "Symbol": "ADMS", "Adj_Close": "18.940001", "High": "19.17", "Low": "18.610001", "Date": "2015-06-09", "Close": "18.940001", "Open": "19.030001"}, {"Volume": "120100", "Symbol": "ADMS", "Adj_Close": "19.139999", "High": "19.50", "Low": "18.50", "Date": "2015-06-08", "Close": "19.139999", "Open": "19.27"}, {"Volume": "87000", "Symbol": "ADMS", "Adj_Close": "19.35", "High": "19.620001", "Low": "18.51", "Date": "2015-06-05", "Close": "19.35", "Open": "18.950001"}, {"Volume": "140800", "Symbol": "ADMS", "Adj_Close": "19.120001", "High": "19.91", "Low": "18.870001", "Date": "2015-06-04", "Close": "19.120001", "Open": "19.790001"}, {"Volume": "213800", "Symbol": "ADMS", "Adj_Close": "19.950001", "High": "20.00", "Low": "18.690001", "Date": "2015-06-03", "Close": "19.950001", "Open": "19.00"}, {"Volume": "321800", "Symbol": "ADMS", "Adj_Close": "18.99", "High": "19.00", "Low": "17.775999", "Date": "2015-06-02", "Close": "18.99", "Open": "17.93"}, {"Volume": "71700", "Symbol": "ADMS", "Adj_Close": "18.040001", "High": "18.08", "Low": "17.92", "Date": "2015-06-01", "Close": "18.040001", "Open": "17.93"}, {"Volume": "224700", "Symbol": "ADMS", "Adj_Close": "17.99", "High": "18.129999", "Low": "17.799999", "Date": "2015-05-29", "Close": "17.99", "Open": "17.969999"}, {"Volume": "42000", "Symbol": "ADMS", "Adj_Close": "18.00", "High": "18.09", "Low": "17.799999", "Date": "2015-05-28", "Close": "18.00", "Open": "18.00"}, {"Volume": "81100", "Symbol": "ADMS", "Adj_Close": "18.00", "High": "18.02", "Low": "17.41", "Date": "2015-05-27", "Close": "18.00", "Open": "17.41"}, {"Volume": "34600", "Symbol": "ADMS", "Adj_Close": "17.49", "High": "17.52", "Low": "17.07", "Date": "2015-05-26", "Close": "17.49", "Open": "17.40"}, {"Volume": "33000", "Symbol": "ADMS", "Adj_Close": "17.43", "High": "17.620001", "Low": "17.18", "Date": "2015-05-22", "Close": "17.43", "Open": "17.620001"}, {"Volume": "26900", "Symbol": "ADMS", "Adj_Close": "17.58", "High": "17.799999", "Low": "17.549999", "Date": "2015-05-21", "Close": "17.58", "Open": "17.700001"}, {"Volume": "41000", "Symbol": "ADMS", "Adj_Close": "17.639999", "High": "17.806", "Low": "17.610001", "Date": "2015-05-20", "Close": "17.639999", "Open": "17.709999"}, {"Volume": "44100", "Symbol": "ADMS", "Adj_Close": "17.709999", "High": "18.01", "Low": "17.620001", "Date": "2015-05-19", "Close": "17.709999", "Open": "17.84"}, {"Volume": "71900", "Symbol": "ADMS", "Adj_Close": "17.91", "High": "18.10", "Low": "17.84", "Date": "2015-05-18", "Close": "17.91", "Open": "17.879999"}, {"Volume": "28500", "Symbol": "ADMS", "Adj_Close": "17.84", "High": "17.91", "Low": "17.610001", "Date": "2015-05-15", "Close": "17.84", "Open": "17.85"}, {"Volume": "40000", "Symbol": "ADMS", "Adj_Close": "17.969999", "High": "18.091999", "Low": "17.482", "Date": "2015-05-14", "Close": "17.969999", "Open": "17.870001"}, {"Volume": "38300", "Symbol": "ADMS", "Adj_Close": "17.799999", "High": "18.02", "Low": "17.50", "Date": "2015-05-13", "Close": "17.799999", "Open": "17.915001"}, {"Volume": "76500", "Symbol": "ADMS", "Adj_Close": "17.83", "High": "18.059999", "Low": "17.60", "Date": "2015-05-12", "Close": "17.83", "Open": "17.879999"}, {"Volume": "54100", "Symbol": "ADMS", "Adj_Close": "17.82", "High": "17.959999", "Low": "17.33", "Date": "2015-05-11", "Close": "17.82", "Open": "17.49"}, {"Volume": "35300", "Symbol": "ADMS", "Adj_Close": "17.530001", "High": "17.780001", "Low": "17.379999", "Date": "2015-05-08", "Close": "17.530001", "Open": "17.780001"}, {"Volume": "46500", "Symbol": "ADMS", "Adj_Close": "17.66", "High": "17.799999", "Low": "17.27", "Date": "2015-05-07", "Close": "17.66", "Open": "17.459999"}, {"Volume": "34400", "Symbol": "ADMS", "Adj_Close": "17.530001", "High": "17.58", "Low": "17.219", "Date": "2015-05-06", "Close": "17.530001", "Open": "17.51"}, {"Volume": "27500", "Symbol": "ADMS", "Adj_Close": "17.360001", "High": "17.92", "Low": "17.15", "Date": "2015-05-05", "Close": "17.360001", "Open": "17.620001"}, {"Volume": "77200", "Symbol": "ADMS", "Adj_Close": "17.780001", "High": "17.950001", "Low": "16.809999", "Date": "2015-05-04", "Close": "17.780001", "Open": "16.82"}, {"Volume": "52800", "Symbol": "ADMS", "Adj_Close": "16.889999", "High": "17.41", "Low": "16.549999", "Date": "2015-05-01", "Close": "16.889999", "Open": "17.27"}, {"Volume": "140800", "Symbol": "ADMS", "Adj_Close": "17.27", "High": "17.76", "Low": "16.860001", "Date": "2015-04-30", "Close": "17.27", "Open": "17.65"}, {"Volume": "56700", "Symbol": "ADMS", "Adj_Close": "17.68", "High": "18.00", "Low": "17.40", "Date": "2015-04-29", "Close": "17.68", "Open": "17.48"}, {"Volume": "119800", "Symbol": "ADMS", "Adj_Close": "17.52", "High": "17.99", "Low": "17.059999", "Date": "2015-04-28", "Close": "17.52", "Open": "17.379999"}, {"Volume": "61000", "Symbol": "ADMS", "Adj_Close": "17.450001", "High": "17.948", "Low": "17.17", "Date": "2015-04-27", "Close": "17.450001", "Open": "17.809999"}, {"Volume": "52800", "Symbol": "ADMS", "Adj_Close": "17.700001", "High": "18.25", "Low": "17.66", "Date": "2015-04-24", "Close": "17.700001", "Open": "17.809999"}, {"Volume": "132200", "Symbol": "ADMS", "Adj_Close": "17.73", "High": "18.24", "Low": "17.469999", "Date": "2015-04-23", "Close": "17.73", "Open": "17.74"}, {"Volume": "48100", "Symbol": "ADMS", "Adj_Close": "17.620001", "High": "17.993999", "Low": "17.540001", "Date": "2015-04-22", "Close": "17.620001", "Open": "17.83"}, {"Volume": "72500", "Symbol": "ADMS", "Adj_Close": "17.83", "High": "18.358", "Low": "17.75", "Date": "2015-04-21", "Close": "17.83", "Open": "17.98"}, {"Volume": "197900", "Symbol": "ADMS", "Adj_Close": "17.82", "High": "18.01", "Low": "17.379999", "Date": "2015-04-20", "Close": "17.82", "Open": "17.75"}, {"Volume": "56600", "Symbol": "ADMS", "Adj_Close": "17.780001", "High": "17.950001", "Low": "17.440001", "Date": "2015-04-17", "Close": "17.780001", "Open": "17.75"}, {"Volume": "135500", "Symbol": "ADMS", "Adj_Close": "17.870001", "High": "17.92", "Low": "17.610001", "Date": "2015-04-16", "Close": "17.870001", "Open": "17.690001"}, {"Volume": "69100", "Symbol": "ADMS", "Adj_Close": "17.790001", "High": "18.035999", "Low": "17.469999", "Date": "2015-04-15", "Close": "17.790001", "Open": "17.719999"}, {"Volume": "47900", "Symbol": "ADMS", "Adj_Close": "17.719999", "High": "18.00", "Low": "17.389999", "Date": "2015-04-14", "Close": "17.719999", "Open": "18.00"}, {"Volume": "138100", "Symbol": "ADMS", "Adj_Close": "17.809999", "High": "17.99", "Low": "17.15", "Date": "2015-04-13", "Close": "17.809999", "Open": "17.77"}, {"Volume": "351300", "Symbol": "ADMS", "Adj_Close": "17.940001", "High": "19.68", "Low": "17.50", "Date": "2015-04-10", "Close": "17.940001", "Open": "19.10"}, {"Volume": "62200", "Symbol": "ADMS", "Adj_Close": "17.139999", "High": "17.33", "Low": "16.91", "Date": "2015-04-09", "Close": "17.139999", "Open": "17.17"}, {"Volume": "51600", "Symbol": "ADMS", "Adj_Close": "17.049999", "High": "17.559999", "Low": "16.950001", "Date": "2015-04-08", "Close": "17.049999", "Open": "17.52"}, {"Volume": "108300", "Symbol": "ADMS", "Adj_Close": "17.59", "High": "17.906", "Low": "17.02", "Date": "2015-04-07", "Close": "17.59", "Open": "17.190001"}, {"Volume": "54700", "Symbol": "ADMS", "Adj_Close": "17.33", "High": "17.940001", "Low": "17.15", "Date": "2015-04-06", "Close": "17.33", "Open": "17.440001"}, {"Volume": "29900", "Symbol": "ADMS", "Adj_Close": "17.709999", "High": "17.940001", "Low": "17.35", "Date": "2015-04-02", "Close": "17.709999", "Open": "17.50"}, {"Volume": "50900", "Symbol": "ADMS", "Adj_Close": "17.469999", "High": "17.559999", "Low": "16.99", "Date": "2015-04-01", "Close": "17.469999", "Open": "17.540001"}, {"Volume": "27400", "Symbol": "ADMS", "Adj_Close": "17.49", "High": "17.60", "Low": "17.280001", "Date": "2015-03-31", "Close": "17.49", "Open": "17.34"}, {"Volume": "70400", "Symbol": "ADMS", "Adj_Close": "17.469999", "High": "17.700001", "Low": "17.10", "Date": "2015-03-30", "Close": "17.469999", "Open": "17.17"}, {"Volume": "39100", "Symbol": "ADMS", "Adj_Close": "17.50", "High": "17.60", "Low": "16.709999", "Date": "2015-03-27", "Close": "17.50", "Open": "16.75"}, {"Volume": "68600", "Symbol": "ADMS", "Adj_Close": "16.719999", "High": "16.879999", "Low": "16.200001", "Date": "2015-03-26", "Close": "16.719999", "Open": "16.700001"}, {"Volume": "81000", "Symbol": "ADMS", "Adj_Close": "16.719999", "High": "17.74", "Low": "16.700001", "Date": "2015-03-25", "Close": "16.719999", "Open": "17.639999"}, {"Volume": "94800", "Symbol": "ADMS", "Adj_Close": "17.690001", "High": "17.950001", "Low": "17.471001", "Date": "2015-03-24", "Close": "17.690001", "Open": "17.75"}, {"Volume": "49400", "Symbol": "ADMS", "Adj_Close": "17.75", "High": "18.00", "Low": "17.65", "Date": "2015-03-23", "Close": "17.75", "Open": "17.969999"}, {"Volume": "82900", "Symbol": "ADMS", "Adj_Close": "17.940001", "High": "18.00", "Low": "17.58", "Date": "2015-03-20", "Close": "17.940001", "Open": "17.98"}, {"Volume": "112100", "Symbol": "ADMS", "Adj_Close": "17.99", "High": "18.00", "Low": "17.50", "Date": "2015-03-19", "Close": "17.99", "Open": "17.90"}, {"Volume": "154200", "Symbol": "ADMS", "Adj_Close": "17.98", "High": "18.15", "Low": "17.700001", "Date": "2015-03-18", "Close": "17.98", "Open": "17.959999"}, {"Volume": "166000", "Symbol": "ADMS", "Adj_Close": "17.92", "High": "18.00", "Low": "17.32", "Date": "2015-03-17", "Close": "17.92", "Open": "17.41"}, {"Volume": "46900", "Symbol": "ADMS", "Adj_Close": "17.41", "High": "17.450001", "Low": "17.25", "Date": "2015-03-16", "Close": "17.41", "Open": "17.360001"}, {"Volume": "521300", "Symbol": "ADMS", "Adj_Close": "17.41", "High": "17.552999", "Low": "17.18", "Date": "2015-03-13", "Close": "17.41", "Open": "17.32"}, {"Volume": "48200", "Symbol": "ADMS", "Adj_Close": "17.24", "High": "17.280001", "Low": "16.798", "Date": "2015-03-12", "Close": "17.24", "Open": "16.879999"}, {"Volume": "39600", "Symbol": "ADMS", "Adj_Close": "16.690001", "High": "16.799999", "Low": "16.290001", "Date": "2015-03-11", "Close": "16.690001", "Open": "16.360001"}, {"Volume": "50600", "Symbol": "ADMS", "Adj_Close": "16.34", "High": "16.540001", "Low": "16.040001", "Date": "2015-03-10", "Close": "16.34", "Open": "16.469999"}, {"Volume": "35000", "Symbol": "ADMS", "Adj_Close": "16.559999", "High": "17.049999", "Low": "16.50", "Date": "2015-03-09", "Close": "16.559999", "Open": "17.049999"}, {"Volume": "34600", "Symbol": "ADMS", "Adj_Close": "16.860001", "High": "17.50", "Low": "16.76", "Date": "2015-03-06", "Close": "16.860001", "Open": "17.43"}, {"Volume": "169200", "Symbol": "ADMS", "Adj_Close": "17.40", "High": "17.700001", "Low": "17.139999", "Date": "2015-03-05", "Close": "17.40", "Open": "17.15"}, {"Volume": "75200", "Symbol": "ADMS", "Adj_Close": "17.360001", "High": "17.41", "Low": "17.08", "Date": "2015-03-04", "Close": "17.360001", "Open": "17.389999"}, {"Volume": "32200", "Symbol": "ADMS", "Adj_Close": "17.25", "High": "17.32", "Low": "17.049999", "Date": "2015-03-03", "Close": "17.25", "Open": "17.32"}, {"Volume": "58100", "Symbol": "ADMS", "Adj_Close": "17.299999", "High": "17.389999", "Low": "16.57", "Date": "2015-03-02", "Close": "17.299999", "Open": "16.969999"}, {"Volume": "52400", "Symbol": "ADMS", "Adj_Close": "17.280001", "High": "17.355", "Low": "16.92", "Date": "2015-02-27", "Close": "17.280001", "Open": "17.190001"}, {"Volume": "41300", "Symbol": "ADMS", "Adj_Close": "17.200001", "High": "17.23", "Low": "16.728001", "Date": "2015-02-26", "Close": "17.200001", "Open": "17.120001"}, {"Volume": "40400", "Symbol": "ADMS", "Adj_Close": "17.309999", "High": "17.41", "Low": "17.17", "Date": "2015-02-25", "Close": "17.309999", "Open": "17.25"}, {"Volume": "34700", "Symbol": "ADMS", "Adj_Close": "17.26", "High": "17.549999", "Low": "17.07", "Date": "2015-02-24", "Close": "17.26", "Open": "17.379999"}, {"Volume": "32700", "Symbol": "ADMS", "Adj_Close": "17.450001", "High": "17.51", "Low": "17.219999", "Date": "2015-02-23", "Close": "17.450001", "Open": "17.309999"}, {"Volume": "48000", "Symbol": "ADMS", "Adj_Close": "17.280001", "High": "17.51", "Low": "16.959999", "Date": "2015-02-20", "Close": "17.280001", "Open": "17.51"}, {"Volume": "59500", "Symbol": "ADMS", "Adj_Close": "17.40", "High": "17.768", "Low": "17.209999", "Date": "2015-02-19", "Close": "17.40", "Open": "17.42"}, {"Volume": "628500", "Symbol": "ADMS", "Adj_Close": "17.379999", "High": "17.40", "Low": "16.790001", "Date": "2015-02-18", "Close": "17.379999", "Open": "16.83"}, {"Volume": "26800", "Symbol": "ADMS", "Adj_Close": "16.93", "High": "17.00", "Low": "16.540001", "Date": "2015-02-17", "Close": "16.93", "Open": "16.540001"}, {"Volume": "23200", "Symbol": "ADMS", "Adj_Close": "16.98", "High": "17.049999", "Low": "16.725", "Date": "2015-02-13", "Close": "16.98", "Open": "17.049999"}, {"Volume": "22100", "Symbol": "ADMS", "Adj_Close": "16.950001", "High": "16.99", "Low": "16.57", "Date": "2015-02-12", "Close": "16.950001", "Open": "16.700001"}, {"Volume": "40800", "Symbol": "ADMS", "Adj_Close": "16.690001", "High": "17.040001", "Low": "16.51", "Date": "2015-02-11", "Close": "16.690001", "Open": "16.940001"}, {"Volume": "48900", "Symbol": "ADMS", "Adj_Close": "16.98", "High": "17.09", "Low": "16.629999", "Date": "2015-02-10", "Close": "16.98", "Open": "16.889999"}, {"Volume": "45900", "Symbol": "ADMS", "Adj_Close": "16.85", "High": "17.08", "Low": "16.540001", "Date": "2015-02-09", "Close": "16.85", "Open": "16.540001"}, {"Volume": "42000", "Symbol": "ADMS", "Adj_Close": "16.67", "High": "17.10", "Low": "16.50", "Date": "2015-02-06", "Close": "16.67", "Open": "16.84"}, {"Volume": "153400", "Symbol": "ADMS", "Adj_Close": "17.110001", "High": "17.440001", "Low": "16.84", "Date": "2015-02-05", "Close": "17.110001", "Open": "16.870001"}, {"Volume": "51600", "Symbol": "ADMS", "Adj_Close": "16.950001", "High": "17.00", "Low": "16.389999", "Date": "2015-02-04", "Close": "16.950001", "Open": "16.530001"}, {"Volume": "84200", "Symbol": "ADMS", "Adj_Close": "16.66", "High": "17.09", "Low": "16.219999", "Date": "2015-02-03", "Close": "16.66", "Open": "16.93"}, {"Volume": "43700", "Symbol": "ADMS", "Adj_Close": "16.959999", "High": "17.00", "Low": "16.452", "Date": "2015-02-02", "Close": "16.959999", "Open": "16.77"}, {"Volume": "45600", "Symbol": "ADMS", "Adj_Close": "16.83", "High": "17.24", "Low": "16.572001", "Date": "2015-01-30", "Close": "16.83", "Open": "17.139999"}, {"Volume": "60400", "Symbol": "ADMS", "Adj_Close": "17.16", "High": "17.23", "Low": "16.690001", "Date": "2015-01-29", "Close": "17.16", "Open": "17.23"}, {"Volume": "106900", "Symbol": "ADMS", "Adj_Close": "17.030001", "High": "17.24", "Low": "16.33", "Date": "2015-01-28", "Close": "17.030001", "Open": "17.10"}, {"Volume": "86800", "Symbol": "ADMS", "Adj_Close": "17.049999", "High": "17.25", "Low": "16.879999", "Date": "2015-01-27", "Close": "17.049999", "Open": "16.879999"}, {"Volume": "43000", "Symbol": "ADMS", "Adj_Close": "17.129999", "High": "17.214001", "Low": "16.68", "Date": "2015-01-26", "Close": "17.129999", "Open": "17.01"}, {"Volume": "53000", "Symbol": "ADMS", "Adj_Close": "17.01", "High": "17.049999", "Low": "16.51", "Date": "2015-01-23", "Close": "17.01", "Open": "16.82"}, {"Volume": "83700", "Symbol": "ADMS", "Adj_Close": "16.790001", "High": "16.92", "Low": "16.129999", "Date": "2015-01-22", "Close": "16.790001", "Open": "16.620001"}, {"Volume": "171000", "Symbol": "ADMS", "Adj_Close": "16.60", "High": "17.40", "Low": "16.02", "Date": "2015-01-21", "Close": "16.60", "Open": "17.110001"}, {"Volume": "79300", "Symbol": "ADMS", "Adj_Close": "17.379999", "High": "17.59", "Low": "16.969999", "Date": "2015-01-20", "Close": "17.379999", "Open": "17.41"}, {"Volume": "76200", "Symbol": "ADMS", "Adj_Close": "17.309999", "High": "17.360001", "Low": "16.809999", "Date": "2015-01-16", "Close": "17.309999", "Open": "16.84"}, {"Volume": "106200", "Symbol": "ADMS", "Adj_Close": "16.93", "High": "17.540001", "Low": "16.809999", "Date": "2015-01-15", "Close": "16.93", "Open": "17.43"}, {"Volume": "95100", "Symbol": "ADMS", "Adj_Close": "17.48", "High": "17.57", "Low": "16.799999", "Date": "2015-01-14", "Close": "17.48", "Open": "16.799999"}, {"Volume": "73300", "Symbol": "ADMS", "Adj_Close": "16.93", "High": "17.219999", "Low": "16.60", "Date": "2015-01-13", "Close": "16.93", "Open": "17.040001"}, {"Volume": "36200", "Symbol": "ADMS", "Adj_Close": "16.969999", "High": "17.10", "Low": "16.653", "Date": "2015-01-12", "Close": "16.969999", "Open": "16.92"}, {"Volume": "55400", "Symbol": "ADMS", "Adj_Close": "16.860001", "High": "17.158001", "Low": "16.23", "Date": "2015-01-09", "Close": "16.860001", "Open": "17.02"}, {"Volume": "54100", "Symbol": "ADMS", "Adj_Close": "16.92", "High": "17.361", "Low": "16.832001", "Date": "2015-01-08", "Close": "16.92", "Open": "17.09"}, {"Volume": "91700", "Symbol": "ADMS", "Adj_Close": "16.98", "High": "17.17", "Low": "16.40", "Date": "2015-01-07", "Close": "16.98", "Open": "16.51"}, {"Volume": "116300", "Symbol": "ADMS", "Adj_Close": "16.50", "High": "16.934999", "Low": "16.129999", "Date": "2015-01-06", "Close": "16.50", "Open": "16.700001"}, {"Volume": "162300", "Symbol": "ADMS", "Adj_Close": "16.68", "High": "17.60", "Low": "16.41", "Date": "2015-01-05", "Close": "16.68", "Open": "17.59"}, {"Volume": "180400", "Symbol": "ADMS", "Adj_Close": "17.49", "High": "17.940001", "Low": "17.209999", "Date": "2015-01-02", "Close": "17.49", "Open": "17.48"}]