{"prices": {"current_page": 1, "total_pages": 1, "page_size": 50000, "api_call_credits": 1, "data": [{"ex_dividend": 0.0, "volume": 5871.0, "adj_low": 23.95, "adj_open": 23.95, "adj_close": 24.88, "high": 25.0, "adj_volume": 5871.0, "low": 23.95, "date": "2017-02-07", "close": 24.88, "open": 23.95, "adj_high": 25.0, "split_ratio": 1.0}, {"ex_dividend": 0.0, "volume": 5284.0, "adj_low": 23.0, "adj_open": 23.0, "adj_close": 23.93, "high": 24.0, "adj_volume": 5284.0, "low": 23.0, "date": "2017-02-06", "close": 23.93, "open": 23.0, "adj_high": 24.0, "split_ratio": 1.0}, {"ex_dividend": 0.0, "volume": 5456.0, "adj_low": 22.816, "adj_open": 23.0, "adj_close": 23.49, "high": 23.5, "adj_volume": 5456.0, "low": 22.816, "date": "2017-02-03", "close": 23.49, "open": 23.0, "adj_high": 23.5, "split_ratio": 1.0}, {"ex_dividend": 0.0, "volume": 3505.0, "adj_low": 22.66, "adj_open": 22.97, "adj_close": 23.0, "high": 23.0, "adj_volume": 3505.0, "low": 22.66, "date": "2017-02-02", "close": 23.0, "open": 22.97, "adj_high": 23.0, "split_ratio": 1.0}, {"ex_dividend": 0.0, "volume": 7157.0, "adj_low": 22.22, "adj_open": 22.88, "adj_close": 23.0, "high": 23.0, "adj_volume": 7157.0, "low": 22.22, "date": "2017-02-01", "close": 23.0, "open": 22.88, "adj_high": 23.0, "split_ratio": 1.0}, {"ex_dividend": 0.0, "volume": 3457.0, "adj_low": 22.8119, "adj_open": 23.455, "adj_close": 22.95, "high": 23.46, "adj_volume": 3457.0, "low": 22.8119, "date": "2017-01-31", "close": 22.95, "open": 23.455, "adj_high": 23.46, "split_ratio": 1.0}, {"ex_dividend": 0.0, "volume": 4859.0, "adj_low": 22.98, "adj_open": 23.001, "adj_close": 23.44, "high": 23.8, "adj_volume": 4859.0, "low": 22.98, "date": "2017-01-30", "close": 23.44, "open": 23.001, "adj_high": 23.8, "split_ratio": 1.0}, {"ex_dividend": 0.0, "volume": 475.0, "adj_low": 21.52, "adj_open": 21.52, "adj_close": 23.6, "high": 23.6, "adj_volume": 475.0, "low": 21.52, "date": "2017-01-27", "close": 23.6, "open": 21.52, "adj_high": 23.6, "split_ratio": 1.0}, {"ex_dividend": 0.0, "volume": 3288.0, "adj_low": 22.25, "adj_open": 23.48, "adj_close": 23.35, "high": 23.48, "adj_volume": 3288.0, "low": 22.25, "date": "2017-01-26", "close": 23.35, "open": 23.48, "adj_high": 23.48, "split_ratio": 1.0}, {"ex_dividend": 0.0, "volume": 3054.0, "adj_low": 22.05, "adj_open": 22.05, "adj_close": 22.7277, "high": 23.94, "adj_volume": 3054.0, "low": 22.05, "date": "2017-01-25", "close": 22.7277, "open": 22.05, "adj_high": 23.94, "split_ratio": 1.0}, {"ex_dividend": 0.0, "volume": 461.0, "adj_low": 22.3024, "adj_open": 22.3024, "adj_close": 22.7, "high": 22.7, "adj_volume": 461.0, "low": 22.3024, "date": "2017-01-24", "close": 22.7, "open": 22.3024, "adj_high": 22.7, "split_ratio": 1.0}, {"ex_dividend": 0.0, "volume": 3677.0, "adj_low": 21.89, "adj_open": 22.64, "adj_close": 22.64, "high": 22.69, "adj_volume": 3677.0, "low": 21.89, "date": "2017-01-23", "close": 22.64, "open": 22.64, "adj_high": 22.69, "split_ratio": 1.0}, {"ex_dividend": 0.0, "volume": 2331.0, "adj_low": 22.2, "adj_open": 22.69, "adj_close": 22.7, "high": 22.7, "adj_volume": 2331.0, "low": 22.2, "date": "2017-01-20", "close": 22.7, "open": 22.69, "adj_high": 22.7, "split_ratio": 1.0}, {"ex_dividend": 0.0, "volume": 9170.0, "adj_low": 22.0193, "adj_open": 22.22, "adj_close": 22.7, "high": 23.05, "adj_volume": 9170.0, "low": 22.0193, "date": "2017-01-19", "close": 22.7, "open": 22.22, "adj_high": 23.05, "split_ratio": 1.0}, {"ex_dividend": 0.0, "volume": 4587.0, "adj_low": 22.38, "adj_open": 22.38, "adj_close": 22.77, "high": 23.24, "adj_volume": 4587.0, "low": 22.38, "date": "2017-01-18", "close": 22.77, "open": 22.38, "adj_high": 23.24, "split_ratio": 1.0}, {"ex_dividend": 0.0, "volume": 4438.0, "adj_low": 22.6, "adj_open": 23.13, "adj_close": 22.98, "high": 23.8946, "adj_volume": 4438.0, "low": 22.6, "date": "2017-01-17", "close": 22.98, "open": 23.13, "adj_high": 23.8946, "split_ratio": 1.0}, {"ex_dividend": 0.0, "volume": 1350.0, "adj_low": 23.28, "adj_open": 23.5498, "adj_close": 23.5, "high": 23.5498, "adj_volume": 1350.0, "low": 23.28, "date": "2017-01-13", "close": 23.5, "open": 23.5498, "adj_high": 23.5498, "split_ratio": 1.0}, {"ex_dividend": 0.0, "volume": 669.0, "adj_low": 22.6339, "adj_open": 23.83, "adj_close": 23.75, "high": 23.83, "adj_volume": 669.0, "low": 22.6339, "date": "2017-01-12", "close": 23.75, "open": 23.83, "adj_high": 23.83, "split_ratio": 1.0}, {"ex_dividend": 0.0, "volume": 5874.0, "adj_low": 23.0, "adj_open": 23.1, "adj_close": 23.35, "high": 23.95, "adj_volume": 5874.0, "low": 23.0, "date": "2017-01-11", "close": 23.35, "open": 23.1, "adj_high": 23.95, "split_ratio": 1.0}, {"ex_dividend": 0.0, "volume": 1305.0, "adj_low": 22.6349, "adj_open": 22.6349, "adj_close": 23.94, "high": 23.95, "adj_volume": 1305.0, "low": 22.6349, "date": "2017-01-10", "close": 23.94, "open": 22.6349, "adj_high": 23.95, "split_ratio": 1.0}, {"ex_dividend": 0.0, "volume": 1807.0, "adj_low": 23.18, "adj_open": 23.24, "adj_close": 23.18, "high": 23.24, "adj_volume": 1807.0, "low": 23.18, "date": "2017-01-09", "close": 23.18, "open": 23.24, "adj_high": 23.24, "split_ratio": 1.0}, {"ex_dividend": 0.0, "volume": 17133.0, "adj_low": 22.25, "adj_open": 23.55, "adj_close": 22.99, "high": 23.55, "adj_volume": 17133.0, "low": 22.25, "date": "2017-01-06", "close": 22.99, "open": 23.55, "adj_high": 23.55, "split_ratio": 1.0}, {"ex_dividend": 0.0, "volume": 3016.0, "adj_low": 22.515, "adj_open": 22.515, "adj_close": 23.95, "high": 24.0, "adj_volume": 3016.0, "low": 22.515, "date": "2017-01-05", "close": 23.95, "open": 22.515, "adj_high": 24.0, "split_ratio": 1.0}, {"ex_dividend": 0.0, "volume": 7444.0, "adj_low": 22.5, "adj_open": 22.5, "adj_close": 24.0, "high": 24.0, "adj_volume": 7444.0, "low": 22.5, "date": "2017-01-04", "close": 24.0, "open": 22.5, "adj_high": 24.0, "split_ratio": 1.0}, {"ex_dividend": 0.0, "volume": 4672.0, "adj_low": 23.5, "adj_open": 23.95, "adj_close": 24.09, "high": 24.1, "adj_volume": 4672.0, "low": 23.5, "date": "2017-01-03", "close": 24.09, "open": 23.95, "adj_high": 24.1, "split_ratio": 1.0}, {"ex_dividend": 0.0, "volume": 2937.0, "adj_low": 23.32, "adj_open": 23.53, "adj_close": 23.9272, "high": 23.9272, "adj_volume": 2937.0, "low": 23.32, "date": "2016-12-30", "close": 23.9272, "open": 23.53, "adj_high": 23.9272, "split_ratio": 1.0}, {"ex_dividend": 0.0, "volume": 12212.0, "adj_low": 23.135, "adj_open": 23.19, "adj_close": 23.62, "high": 23.75, "adj_volume": 12212.0, "low": 23.135, "date": "2016-12-29", "close": 23.62, "open": 23.19, "adj_high": 23.75, "split_ratio": 1.0}, {"ex_dividend": 0.0, "volume": 2686.0, "adj_low": 22.68, "adj_open": 22.98, "adj_close": 23.49, "high": 23.49, "adj_volume": 2686.0, "low": 22.68, "date": "2016-12-28", "close": 23.49, "open": 22.98, "adj_high": 23.49, "split_ratio": 1.0}, {"ex_dividend": 0.0, "volume": 1538.0, "adj_low": 22.5, "adj_open": 22.6445, "adj_close": 22.85, "high": 22.85, "adj_volume": 1538.0, "low": 22.5, "date": "2016-12-27", "close": 22.85, "open": 22.6445, "adj_high": 22.85, "split_ratio": 1.0}, {"ex_dividend": 0.0, "volume": 2389.0, "adj_low": 22.6, "adj_open": 22.92, "adj_close": 22.66, "high": 22.92, "adj_volume": 2389.0, "low": 22.6, "date": "2016-12-23", "close": 22.66, "open": 22.92, "adj_high": 22.92, "split_ratio": 1.0}, {"ex_dividend": 0.0, "volume": 7116.0, "adj_low": 22.47, "adj_open": 22.5, "adj_close": 22.58, "high": 22.65, "adj_volume": 7116.0, "low": 22.47, "date": "2016-12-22", "close": 22.58, "open": 22.5, "adj_high": 22.65, "split_ratio": 1.0}, {"ex_dividend": 0.0, "volume": 8612.0, "adj_low": 22.401, "adj_open": 23.5, "adj_close": 22.55, "high": 23.5, "adj_volume": 8612.0, "low": 22.401, "date": "2016-12-21", "close": 22.55, "open": 23.5, "adj_high": 23.5, "split_ratio": 1.0}, {"ex_dividend": 0.0, "volume": 7743.0, "adj_low": 22.7, "adj_open": 24.249, "adj_close": 23.5, "high": 24.25, "adj_volume": 7743.0, "low": 22.7, "date": "2016-12-20", "close": 23.5, "open": 24.249, "adj_high": 24.25, "split_ratio": 1.0}, {"ex_dividend": 0.0, "volume": 5481.0, "adj_low": 22.0, "adj_open": 22.01, "adj_close": 24.035, "high": 24.035, "adj_volume": 5481.0, "low": 22.0, "date": "2016-12-19", "close": 24.035, "open": 22.01, "adj_high": 24.035, "split_ratio": 1.0}, {"ex_dividend": 0.16, "volume": 44505.0, "adj_low": 22.8, "adj_open": 23.2899, "adj_close": 23.19, "high": 23.3, "adj_volume": 44505.0, "low": 22.8, "date": "2016-12-16", "close": 23.19, "open": 23.2899, "adj_high": 23.3, "split_ratio": 1.0}, {"ex_dividend": 0.0, "volume": 38114.0, "adj_low": 21.8293875802998, "adj_open": 21.8492505353319, "adj_close": 22.4451391862955, "high": 24.27, "adj_volume": 38114.0, "low": 21.98, "date": "2016-12-15", "close": 22.6, "open": 22.0, "adj_high": 24.1036959314775, "split_ratio": 1.0}, {"ex_dividend": 0.0, "volume": 13484.0, "adj_low": 21.6010629122056, "adj_open": 22.0975374732334, "adj_close": 22.0975374732334, "high": 22.25, "adj_volume": 13484.0, "low": 21.7501, "date": "2016-12-14", "close": 22.25, "open": 22.25, "adj_high": 22.0975374732334, "split_ratio": 1.0}, {"ex_dividend": 0.0, "volume": 6533.0, "adj_low": 20.9156916488223, "adj_open": 22.0662533190578, "adj_close": 21.4221970021413, "high": 22.2185, "adj_volume": 6533.0, "low": 21.06, "date": "2016-12-13", "close": 21.57, "open": 22.2185, "adj_high": 22.0662533190578, "split_ratio": 1.0}, {"ex_dividend": 0.0, "volume": 6021.0, "adj_low": 20.6674047109208, "adj_open": 20.6674047109208, "adj_close": 21.6903468950749, "high": 21.9, "adj_volume": 6021.0, "low": 20.81, "date": "2016-12-12", "close": 21.84, "open": 20.81, "adj_high": 21.7499357601713, "split_ratio": 1.0}, {"ex_dividend": 0.0, "volume": 6686.0, "adj_low": 20.2701456102784, "adj_open": 21.8492505353319, "adj_close": 20.8561027837259, "high": 22.0, "adj_volume": 6686.0, "low": 20.41, "date": "2016-12-09", "close": 21.0, "open": 22.0, "adj_high": 21.8492505353319, "split_ratio": 1.0}, {"ex_dividend": 0.0, "volume": 6539.0, "adj_low": 20.5531927194861, "adj_open": 20.5531927194861, "adj_close": 21.0547323340471, "high": 22.11, "adj_volume": 6539.0, "low": 20.695, "date": "2016-12-08", "close": 21.2, "open": 20.695, "adj_high": 21.9584967880086, "split_ratio": 1.0}, {"ex_dividend": 0.0, "volume": 9421.0, "adj_low": 20.7766509635974, "adj_open": 21.6506209850107, "adj_close": 20.8958286937901, "high": 22.0, "adj_volume": 9421.0, "low": 20.92, "date": "2016-12-07", "close": 21.04, "open": 21.8, "adj_high": 21.8492505353319, "split_ratio": 1.0}, {"ex_dividend": 0.0, "volume": 16787.0, "adj_low": 20.041721627409, "adj_open": 21.869113490364, "adj_close": 21.2533618843683, "high": 22.2376, "adj_volume": 16787.0, "low": 20.18, "date": "2016-12-06", "close": 21.4, "open": 22.02, "adj_high": 22.0852224411135, "split_ratio": 1.0}, {"ex_dividend": 0.0, "volume": 25845.0, "adj_low": 18.9691220556745, "adj_open": 19.5650107066381, "adj_close": 21.6009635974304, "high": 23.74, "adj_volume": 25845.0, "low": 19.1, "date": "2016-12-05", "close": 21.75, "open": 19.7, "adj_high": 23.5773276231263, "split_ratio": 1.0}, {"ex_dividend": 0.0, "volume": 1881.0, "adj_low": 19.20747751606, "adj_open": 19.2670663811563, "adj_close": 19.6047366167024, "high": 19.79, "adj_volume": 1881.0, "low": 19.34, "date": "2016-12-02", "close": 19.74, "open": 19.4, "adj_high": 19.6543940042827, "split_ratio": 1.0}, {"ex_dividend": 0.0, "volume": 3289.0, "adj_low": 19.0386423982869, "adj_open": 19.7636402569593, "adj_close": 19.4061070663812, "high": 19.9, "adj_volume": 3289.0, "low": 19.17, "date": "2016-12-01", "close": 19.54, "open": 19.9, "adj_high": 19.7636402569593, "split_ratio": 1.0}, {"ex_dividend": 0.0, "volume": 7246.0, "adj_low": 18.6711777301927, "adj_open": 18.7703931905782, "adj_close": 19.7735717344754, "high": 19.91, "adj_volume": 7246.0, "low": 18.8, "date": "2016-11-30", "close": 19.91, "open": 18.8999, "adj_high": 19.7735717344754, "split_ratio": 1.0}, {"ex_dividend": 0.0, "volume": 5467.0, "adj_low": 18.4129593147752, "adj_open": 18.4725481798715, "adj_close": 18.6711777301927, "high": 18.97, "adj_volume": 5467.0, "low": 18.54, "date": "2016-11-29", "close": 18.8, "open": 18.6, "adj_high": 18.8400128479657, "split_ratio": 1.0}, {"ex_dividend": 0.0, "volume": 2740.0, "adj_low": 18.4725481798715, "adj_open": 18.6006642398287, "adj_close": 18.5718629550321, "high": 18.8, "adj_volume": 2740.0, "low": 18.6, "date": "2016-11-28", "close": 18.7, "open": 18.729, "adj_high": 18.6711777301927, "split_ratio": 1.0}, {"ex_dividend": 0.0, "volume": 100.0, "adj_low": 18.4924111349036, "adj_open": 18.4924111349036, "adj_close": 18.4924111349036, "high": 18.62, "adj_volume": 100.0, "low": 18.62, "date": "2016-11-25", "close": 18.62, "open": 18.62, "adj_high": 18.4924111349036, "split_ratio": 1.0}, {"ex_dividend": 0.0, "volume": 15857.0, "adj_low": 17.9848133190578, "adj_open": 18.1746038543897, "adj_close": 18.6016573875803, "high": 18.73, "adj_volume": 15857.0, "low": 18.1089, "date": "2016-11-23", "close": 18.73, "open": 18.3, "adj_high": 18.6016573875803, "split_ratio": 1.0}, {"ex_dividend": 0.0, "volume": 22343.0, "adj_low": 17.8866903211991, "adj_open": 18.0400323340471, "adj_close": 18.5420685224839, "high": 18.73, "adj_volume": 22343.0, "low": 18.0101, "date": "2016-11-22", "close": 18.67, "open": 18.1645, "adj_high": 18.6016573875803, "split_ratio": 1.0}, {"ex_dividend": 0.0, "volume": 4736.0, "adj_low": 18.0853198715203, "adj_open": 18.0853198715203, "adj_close": 18.1746038543897, "high": 18.45, "adj_volume": 4736.0, "low": 18.2101, "date": "2016-11-21", "close": 18.3, "open": 18.2101, "adj_high": 18.3235760171306, "split_ratio": 1.0}, {"ex_dividend": 0.0, "volume": 5309.0, "adj_low": 17.735731862955, "adj_open": 18.0355631691649, "adj_close": 18.0402309635974, "high": 18.17, "adj_volume": 5309.0, "low": 17.8581, "date": "2016-11-18", "close": 18.1647, "open": 18.16, "adj_high": 18.0454946466809, "split_ratio": 1.0}, {"ex_dividend": 0.0, "volume": 10408.0, "adj_low": 17.6025507494647, "adj_open": 18.8201498929336, "adj_close": 18.0752890792291, "high": 18.95, "adj_volume": 10408.0, "low": 17.724, "date": "2016-11-17", "close": 18.2, "open": 18.95, "adj_high": 18.8201498929336, "split_ratio": 1.0}, {"ex_dividend": 0.0, "volume": 2686.0, "adj_low": 18.2341927194861, "adj_open": 18.3434389721627, "adj_close": 18.3235760171306, "high": 18.47, "adj_volume": 2686.0, "low": 18.36, "date": "2016-11-16", "close": 18.45, "open": 18.47, "adj_high": 18.3434389721627, "split_ratio": 1.0}, {"ex_dividend": 0.0, "volume": 9170.0, "adj_low": 18.0752890792291, "adj_open": 18.1527546038544, "adj_close": 18.2405488650964, "high": 18.4594, "adj_volume": 9170.0, "low": 18.2, "date": "2016-11-15", "close": 18.3664, "open": 18.278, "adj_high": 18.3329116059957, "split_ratio": 1.0}, {"ex_dividend": 0.0, "volume": 1517.0, "adj_low": 17.9263169164882, "adj_open": 17.9263169164882, "adj_close": 18.1845353319058, "high": 18.31, "adj_volume": 1517.0, "low": 18.05, "date": "2016-11-14", "close": 18.31, "open": 18.05, "adj_high": 18.1845353319058, "split_ratio": 1.0}, {"ex_dividend": 0.0, "volume": 3191.0, "adj_low": 17.5272701498929, "adj_open": 17.6283725910064, "adj_close": 17.6283725910064, "high": 17.75, "adj_volume": 3191.0, "low": 17.6482, "date": "2016-11-11", "close": 17.75, "open": 17.75, "adj_high": 17.6283725910064, "split_ratio": 1.0}, {"ex_dividend": 0.0, "volume": 7848.0, "adj_low": 17.3204967880086, "adj_open": 17.8170706638116, "adj_close": 17.8170706638116, "high": 18.0, "adj_volume": 7848.0, "low": 17.44, "date": "2016-11-10", "close": 17.94, "open": 17.94, "adj_high": 17.8766595289079, "split_ratio": 1.0}, {"ex_dividend": 0.0, "volume": 1832.0, "adj_low": 17.3403597430407, "adj_open": 17.3719418415418, "adj_close": 17.8667280513919, "high": 17.99, "adj_volume": 1832.0, "low": 17.46, "date": "2016-11-09", "close": 17.99, "open": 17.4918, "adj_high": 17.8667280513919, "split_ratio": 1.0}, {"ex_dividend": 0.0, "volume": 1217.0, "adj_low": 17.2038019271949, "adj_open": 17.2038019271949, "adj_close": 17.2038019271949, "high": 17.3225, "adj_volume": 1217.0, "low": 17.3225, "date": "2016-11-08", "close": 17.3225, "open": 17.3225, "adj_high": 17.2038019271949, "split_ratio": 1.0}, {"ex_dividend": 0.0, "volume": 3158.0, "adj_low": 16.903374732334, "adj_open": 17.1644732762313, "adj_close": 17.3701541755889, "high": 17.49, "adj_volume": 3158.0, "low": 17.02, "date": "2016-11-07", "close": 17.49, "open": 17.2829, "adj_high": 17.3701541755889, "split_ratio": 1.0}, {"ex_dividend": 0.0, "volume": 592.0, "adj_low": 16.9331691648822, "adj_open": 16.9331691648822, "adj_close": 16.9331691648822, "high": 17.05, "adj_volume": 592.0, "low": 17.05, "date": "2016-11-04", "close": 17.05, "open": 17.05, "adj_high": 16.9331691648822, "split_ratio": 1.0}, {"ex_dividend": 0.0, "volume": 210.0, "adj_low": 17.1846341755889, "adj_open": 17.3621096788009, "adj_close": 17.1846341755889, "high": 17.4819, "adj_volume": 210.0, "low": 17.3032, "date": "2016-11-03", "close": 17.3032, "open": 17.4819, "adj_high": 17.3621096788009, "split_ratio": 1.0}, {"ex_dividend": 0.0, "volume": 3101.0, "adj_low": 17.032583254818, "adj_open": 17.3602226980728, "adj_close": 17.2112505353319, "high": 17.48, "adj_volume": 3101.0, "low": 17.1501, "date": "2016-11-02", "close": 17.33, "open": 17.48, "adj_high": 17.3602226980728, "split_ratio": 1.0}, {"ex_dividend": 0.0, "volume": 5888.0, "adj_low": 16.903374732334, "adj_open": 16.9331691648822, "adj_close": 16.9785560171306, "high": 17.5, "adj_volume": 5888.0, "low": 17.02, "date": "2016-11-01", "close": 17.0957, "open": 17.05, "adj_high": 17.3800856531049, "split_ratio": 1.0}, {"ex_dividend": 0.0, "volume": 1500.0, "adj_low": 17.3800856531049, "adj_open": 17.5936124197002, "adj_close": 17.3800856531049, "high": 17.715, "adj_volume": 1500.0, "low": 17.5, "date": "2016-10-31", "close": 17.5, "open": 17.715, "adj_high": 17.5936124197002, "split_ratio": 1.0}, {"ex_dividend": 0.0, "volume": 5750.0, "adj_low": 17.3304282655246, "adj_open": 17.3304282655246, "adj_close": 17.5091948608137, "high": 17.63, "adj_volume": 5750.0, "low": 17.45, "date": "2016-10-28", "close": 17.63, "open": 17.45, "adj_high": 17.5091948608137, "split_ratio": 1.0}, {"ex_dividend": 0.0, "volume": 1665.0, "adj_low": 16.7047451820128, "adj_open": 16.7047451820128, "adj_close": 17.3006338329764, "high": 17.5, "adj_volume": 1665.0, "low": 16.82, "date": "2016-10-27", "close": 17.42, "open": 16.82, "adj_high": 17.3800856531049, "split_ratio": 1.0}, {"ex_dividend": 0.0, "volume": 0.0, "adj_low": 17.0920728051392, "adj_open": 17.0920728051392, "adj_close": 17.0920728051392, "high": 17.21, "adj_volume": 0.0, "low": 17.21, "date": "2016-10-26", "close": 17.21, "open": 17.21, "adj_high": 17.0920728051392, "split_ratio": 1.0}, {"ex_dividend": 0.0, "volume": 0.0, "adj_low": 17.0920728051392, "adj_open": 17.0920728051392, "adj_close": 17.0920728051392, "high": 17.21, "adj_volume": 0.0, "low": 17.21, "date": "2016-10-25", "close": 17.21, "open": 17.21, "adj_high": 17.0920728051392, "split_ratio": 1.0}, {"ex_dividend": 0.0, "volume": 11766.0, "adj_low": 15.6122826552463, "adj_open": 15.6122826552463, "adj_close": 17.0920728051392, "high": 17.3, "adj_volume": 11766.0, "low": 15.72, "date": "2016-10-24", "close": 17.21, "open": 15.72, "adj_high": 17.1814561027837, "split_ratio": 1.0}, {"ex_dividend": 0.0, "volume": 3490.0, "adj_low": 16.7544025695931, "adj_open": 16.7544025695931, "adj_close": 17.0722098501071, "high": 17.25, "adj_volume": 3490.0, "low": 16.87, "date": "2016-10-21", "close": 17.19, "open": 16.87, "adj_high": 17.1317987152034, "split_ratio": 1.0}, {"ex_dividend": 0.0, "volume": 13519.0, "adj_low": 17.0779701070664, "adj_open": 17.1814561027837, "adj_close": 17.2509764453961, "high": 17.4, "adj_volume": 13519.0, "low": 17.1958, "date": "2016-10-20", "close": 17.37, "open": 17.3, "adj_high": 17.2807708779443, "split_ratio": 1.0}, {"ex_dividend": 0.0, "volume": 6500.0, "adj_low": 17.1237542184154, "adj_open": 17.3533699785867, "adj_close": 17.3304282655246, "high": 17.49, "adj_volume": 6500.0, "low": 17.2419, "date": "2016-10-19", "close": 17.45, "open": 17.4731, "adj_high": 17.3701541755889, "split_ratio": 1.0}, {"ex_dividend": 0.0, "volume": 2798.0, "adj_low": 16.7047451820128, "adj_open": 16.7610566595289, "adj_close": 17.0126209850107, "high": 17.31, "adj_volume": 2798.0, "low": 16.82, "date": "2016-10-18", "close": 17.13, "open": 16.8767, "adj_high": 17.1913875802998, "split_ratio": 1.0}, {"ex_dividend": 0.0, "volume": 2704.0, "adj_low": 16.6602521627409, "adj_open": 17.5583556745182, "adj_close": 17.062278372591, "high": 17.6795, "adj_volume": 2704.0, "low": 16.7752, "date": "2016-10-17", "close": 17.18, "open": 17.6795, "adj_high": 17.5583556745182, "split_ratio": 1.0}, {"ex_dividend": 0.0, "volume": 24054.0, "adj_low": 16.5649099785867, "adj_open": 16.6193344753747, "adj_close": 16.8636488222698, "high": 17.2, "adj_volume": 24054.0, "low": 16.6792, "date": "2016-10-14", "close": 16.98, "open": 16.734, "adj_high": 17.0821413276231, "split_ratio": 1.0}, {"ex_dividend": 0.0, "volume": 157.0, "adj_low": 16.5339237687366, "adj_open": 16.5339237687366, "adj_close": 16.5339237687366, "high": 16.648, "adj_volume": 157.0, "low": 16.648, "date": "2016-10-13", "close": 16.648, "open": 16.648, "adj_high": 16.5339237687366, "split_ratio": 1.0}, {"ex_dividend": 0.0, "volume": 10943.0, "adj_low": 16.5359100642398, "adj_open": 17.1715246252677, "adj_close": 16.536009379015, "high": 17.29, "adj_volume": 10943.0, "low": 16.65, "date": "2016-10-12", "close": 16.6501, "open": 17.29, "adj_high": 17.1715246252677, "split_ratio": 1.0}, {"ex_dividend": 0.0, "volume": 5475.0, "adj_low": 16.8835117773019, "adj_open": 16.8835117773019, "adj_close": 16.8836110920771, "high": 17.6272, "adj_volume": 5475.0, "low": 17.0, "date": "2016-10-11", "close": 17.0001, "open": 17.0, "adj_high": 17.5064140471092, "split_ratio": 1.0}, {"ex_dividend": 0.0, "volume": 8761.0, "adj_low": 16.5954989293362, "adj_open": 16.8338543897216, "adj_close": 16.5954989293362, "high": 16.9977, "adj_volume": 8761.0, "low": 16.71, "date": "2016-10-10", "close": 16.71, "open": 16.95, "adj_high": 16.8812275374732, "split_ratio": 1.0}, {"ex_dividend": 0.0, "volume": 4032.0, "adj_low": 16.2759039828694, "adj_open": 16.3174175588865, "adj_close": 16.5954989293362, "high": 16.78, "adj_volume": 4032.0, "low": 16.3882, "date": "2016-10-07", "close": 16.71, "open": 16.43, "adj_high": 16.6650192719486, "split_ratio": 1.0}, {"ex_dividend": 0.0, "volume": 6302.0, "adj_low": 16.1710275802998, "adj_open": 16.3174175588865, "adj_close": 16.2081713062098, "high": 16.43, "adj_volume": 6302.0, "low": 16.2826, "date": "2016-10-06", "close": 16.32, "open": 16.43, "adj_high": 16.3174175588865, "split_ratio": 1.0}, {"ex_dividend": 0.0, "volume": 2277.0, "adj_low": 16.1589111777302, "adj_open": 16.1589111777302, "adj_close": 16.2876231263383, "high": 16.42, "adj_volume": 2277.0, "low": 16.2704, "date": "2016-10-05", "close": 16.4, "open": 16.2704, "adj_high": 16.3074860813704, "split_ratio": 1.0}, {"ex_dividend": 0.0, "volume": 4701.0, "adj_low": 16.1252434689507, "adj_open": 16.2975546038544, "adj_close": 16.2181027837259, "high": 16.41, "adj_volume": 4701.0, "low": 16.2365, "date": "2016-10-04", "close": 16.33, "open": 16.41, "adj_high": 16.2975546038544, "split_ratio": 1.0}, {"ex_dividend": 0.0, "volume": 6358.0, "adj_low": 16.1386509635974, "adj_open": 16.1883083511777, "adj_close": 16.1386509635974, "high": 16.4299, "adj_volume": 6358.0, "low": 16.25, "date": "2016-10-03", "close": 16.25, "open": 16.3, "adj_high": 16.3173182441113, "split_ratio": 1.0}, {"ex_dividend": 0.0, "volume": 1945.0, "adj_low": 16.059199143469, "adj_open": 16.2553458244111, "adj_close": 16.1386509635974, "high": 16.41, "adj_volume": 1945.0, "low": 16.17, "date": "2016-09-30", "close": 16.25, "open": 16.3675, "adj_high": 16.2975546038544, "split_ratio": 1.0}, {"ex_dividend": 0.0, "volume": 2405.0, "adj_low": 15.9499528907923, "adj_open": 15.9499528907923, "adj_close": 16.0492676659529, "high": 16.3999, "adj_volume": 2405.0, "low": 16.06, "date": "2016-09-29", "close": 16.16, "open": 16.06, "adj_high": 16.2875238115632, "split_ratio": 1.0}, {"ex_dividend": 0.0, "volume": 18541.0, "adj_low": 15.7940286937901, "adj_open": 16.208866509636, "adj_close": 15.8903640256959, "high": 16.3207, "adj_volume": 18541.0, "low": 15.903, "date": "2016-09-28", "close": 16.0, "open": 16.3207, "adj_high": 16.208866509636, "split_ratio": 1.0}, {"ex_dividend": 0.0, "volume": 37579.0, "adj_low": 15.6619400428266, "adj_open": 16.3174175588865, "adj_close": 16.1485824411135, "high": 16.43, "adj_volume": 37579.0, "low": 15.77, "date": "2016-09-27", "close": 16.26, "open": 16.43, "adj_high": 16.3174175588865, "split_ratio": 1.0}, {"ex_dividend": 0.0, "volume": 14347.0, "adj_low": 16.1386509635974, "adj_open": 16.3273490364026, "adj_close": 16.3174175588865, "high": 16.4433, "adj_volume": 14347.0, "low": 16.25, "date": "2016-09-26", "close": 16.43, "open": 16.44, "adj_high": 16.3306264239829, "split_ratio": 1.0}, {"ex_dividend": 0.0, "volume": 3740.0, "adj_low": 16.069130620985, "adj_open": 16.3074860813704, "adj_close": 16.3371811991435, "high": 16.4499, "adj_volume": 3740.0, "low": 16.18, "date": "2016-09-23", "close": 16.4499, "open": 16.42, "adj_high": 16.3371811991435, "split_ratio": 1.0}, {"ex_dividend": 0.0, "volume": 4742.0, "adj_low": 16.0286101927195, "adj_open": 16.1386509635974, "adj_close": 16.2975546038544, "high": 16.41, "adj_volume": 4742.0, "low": 16.1392, "date": "2016-09-22", "close": 16.41, "open": 16.25, "adj_high": 16.2975546038544, "split_ratio": 1.0}, {"ex_dividend": 0.0, "volume": 116.0, "adj_low": 16.1335859100642, "adj_open": 16.1335859100642, "adj_close": 16.1335859100642, "high": 16.2449, "adj_volume": 116.0, "low": 16.2449, "date": "2016-09-21", "close": 16.2449, "open": 16.2449, "adj_high": 16.1335859100642, "split_ratio": 1.0}, {"ex_dividend": 0.0, "volume": 2019.0, "adj_low": 16.1335859100642, "adj_open": 16.1585139186295, "adj_close": 16.1335859100642, "high": 16.27, "adj_volume": 2019.0, "low": 16.2449, "date": "2016-09-20", "close": 16.2449, "open": 16.27, "adj_high": 16.1585139186295, "split_ratio": 1.0}, {"ex_dividend": 0.0, "volume": 36.0, "adj_low": 16.1628837687366, "adj_open": 16.1628837687366, "adj_close": 16.1628837687366, "high": 16.2744, "adj_volume": 36.0, "low": 16.2744, "date": "2016-09-19", "close": 16.2744, "open": 16.2744, "adj_high": 16.1628837687366, "split_ratio": 1.0}, {"ex_dividend": 0.16, "volume": 341.0, "adj_low": 16.1628837687366, "adj_open": 16.1628837687366, "adj_close": 16.1628837687366, "high": 16.2744, "adj_volume": 341.0, "low": 16.2744, "date": "2016-09-16", "close": 16.2744, "open": 16.2744, "adj_high": 16.1628837687366, "split_ratio": 1.0}, {"ex_dividend": 0.0, "volume": 2.0, "adj_low": 16.030704219832, "adj_open": 16.030704219832, "adj_close": 16.030704219832, "high": 16.3, "adj_volume": 2.0, "low": 16.3, "date": "2016-09-15", "close": 16.3, "open": 16.3, "adj_high": 16.030704219832, "split_ratio": 1.0}, {"ex_dividend": 0.0, "volume": 137.0, "adj_low": 16.030704219832, "adj_open": 16.030704219832, "adj_close": 16.030704219832, "high": 16.3, "adj_volume": 137.0, "low": 16.3, "date": "2016-09-14", "close": 16.3, "open": 16.3, "adj_high": 16.030704219832, "split_ratio": 1.0}, {"ex_dividend": 0.0, "volume": 1076.0, "adj_low": 16.030704219832, "adj_open": 16.030704219832, "adj_close": 16.030704219832, "high": 16.3, "adj_volume": 1076.0, "low": 16.3, "date": "2016-09-13", "close": 16.3, "open": 16.3, "adj_high": 16.030704219832, "split_ratio": 1.0}, {"ex_dividend": 0.0, "volume": 1266.0, "adj_low": 16.0501770998045, "adj_open": 16.1093825227514, "adj_close": 16.0501770998045, "high": 16.45, "adj_volume": 1266.0, "low": 16.3198, "date": "2016-09-12", "close": 16.3198, "open": 16.38, "adj_high": 16.1782260378059, "split_ratio": 1.0}, {"ex_dividend": 0.0, "volume": 1530.0, "adj_low": 15.7454953717491, "adj_open": 15.7454953717491, "adj_close": 15.8340084625334, "high": 16.2923, "adj_volume": 1530.0, "low": 16.01, "date": "2016-09-09", "close": 16.1, "open": 16.01, "adj_high": 16.023131433176, "split_ratio": 1.0}, {"ex_dividend": 0.0, "volume": 0.0, "adj_low": 15.7454953717491, "adj_open": 15.7454953717491, "adj_close": 15.7454953717491, "high": 16.01, "adj_volume": 0.0, "low": 16.01, "date": "2016-09-08", "close": 16.01, "open": 16.01, "adj_high": 15.7454953717491, "split_ratio": 1.0}, {"ex_dividend": 0.0, "volume": 7525.0, "adj_low": 15.7454953717491, "adj_open": 15.9815302805074, "adj_close": 15.7454953717491, "high": 16.25, "adj_volume": 7525.0, "low": 16.01, "date": "2016-09-07", "close": 16.01, "open": 16.25, "adj_high": 15.9815302805074, "split_ratio": 1.0}, {"ex_dividend": 0.0, "volume": 1700.0, "adj_low": 15.7258257960192, "adj_open": 15.9225215533178, "adj_close": 15.7258257960192, "high": 16.19, "adj_volume": 1700.0, "low": 15.99, "date": "2016-09-06", "close": 15.99, "open": 16.19, "adj_high": 15.9225215533178, "split_ratio": 1.0}, {"ex_dividend": 0.0, "volume": 460.0, "adj_low": 15.6963214324245, "adj_open": 15.8831824018581, "adj_close": 15.6963214324245, "high": 16.15, "adj_volume": 460.0, "low": 15.96, "date": "2016-09-02", "close": 15.96, "open": 16.15, "adj_high": 15.8831824018581, "split_ratio": 1.0}, {"ex_dividend": 0.0, "volume": 5257.0, "adj_low": 15.7848345232088, "adj_open": 15.8029305328803, "adj_close": 15.9028519775879, "high": 16.1899, "adj_volume": 5257.0, "low": 16.05, "date": "2016-09-01", "close": 16.17, "open": 16.0684, "adj_high": 15.9224232054391, "split_ratio": 1.0}, {"ex_dividend": 0.0, "volume": 788.0, "adj_low": 15.7258257960192, "adj_open": 15.7258257960192, "adj_close": 15.7405779778166, "high": 16.045, "adj_volume": 788.0, "low": 15.99, "date": "2016-08-31", "close": 16.005, "open": 15.99, "adj_high": 15.7799171292763, "split_ratio": 1.0}, {"ex_dividend": 0.0, "volume": 9337.0, "adj_low": 15.6766518566946, "adj_open": 15.8241736746685, "adj_close": 15.755330159614, "high": 16.1893, "adj_volume": 9337.0, "low": 15.94, "date": "2016-08-30", "close": 16.02, "open": 16.09, "adj_high": 15.9218331181672, "split_ratio": 1.0}, {"ex_dividend": 0.0, "volume": 75.0, "adj_low": 15.7356605838842, "adj_open": 15.7356605838842, "adj_close": 15.7356605838842, "high": 16.0, "adj_volume": 75.0, "low": 16.0, "date": "2016-08-29", "close": 16.0, "open": 16.0, "adj_high": 15.7356605838842, "split_ratio": 1.0}, {"ex_dividend": 0.0, "volume": 1200.0, "adj_low": 15.7258257960192, "adj_open": 15.7258257960192, "adj_close": 15.7356605838842, "high": 16.05, "adj_volume": 1200.0, "low": 15.99, "date": "2016-08-26", "close": 16.0, "open": 15.99, "adj_high": 15.7848345232088, "split_ratio": 1.0}, {"ex_dividend": 0.0, "volume": 417.0, "adj_low": 15.7338903220685, "adj_open": 15.7454953717491, "adj_close": 15.7338903220685, "high": 16.01, "adj_volume": 417.0, "low": 15.9982, "date": "2016-08-25", "close": 15.9982, "open": 16.01, "adj_high": 15.7454953717491, "split_ratio": 1.0}, {"ex_dividend": 0.0, "volume": 0.0, "adj_low": 15.8340084625334, "adj_open": 15.8340084625334, "adj_close": 15.8340084625334, "high": 16.1, "adj_volume": 0.0, "low": 16.1, "date": "2016-08-24", "close": 16.1, "open": 16.1, "adj_high": 15.8340084625334, "split_ratio": 1.0}, {"ex_dividend": 0.0, "volume": 2128.0, "adj_low": 15.6864866445595, "adj_open": 15.7454953717491, "adj_close": 15.8340084625334, "high": 16.1, "adj_volume": 2128.0, "low": 15.95, "date": "2016-08-23", "close": 16.1, "open": 16.01, "adj_high": 15.8340084625334, "split_ratio": 1.0}, {"ex_dividend": 0.0, "volume": 4798.0, "adj_low": 15.7454953717491, "adj_open": 15.7848345232088, "adj_close": 15.8340084625334, "high": 16.18, "adj_volume": 4798.0, "low": 16.01, "date": "2016-08-22", "close": 16.1, "open": 16.05, "adj_high": 15.9126867654529, "split_ratio": 1.0}, {"ex_dividend": 0.0, "volume": 3146.0, "adj_low": 15.6963214324245, "adj_open": 15.6963214324245, "adj_close": 15.7848345232088, "high": 16.1, "adj_volume": 3146.0, "low": 15.96, "date": "2016-08-19", "close": 16.05, "open": 15.96, "adj_high": 15.8340084625334, "split_ratio": 1.0}, {"ex_dividend": 0.0, "volume": 2214.0, "adj_low": 15.6963214324245, "adj_open": 15.6963214324245, "adj_close": 15.8241736746685, "high": 16.09, "adj_volume": 2214.0, "low": 15.96, "date": "2016-08-18", "close": 16.09, "open": 15.96, "adj_high": 15.8241736746685, "split_ratio": 1.0}, {"ex_dividend": 0.0, "volume": 2404.0, "adj_low": 15.7674269486879, "adj_open": 15.7674269486879, "adj_close": 15.8045040989387, "high": 16.0999, "adj_volume": 2404.0, "low": 16.0323, "date": "2016-08-17", "close": 16.07, "open": 16.0323, "adj_high": 15.8339101146548, "split_ratio": 1.0}, {"ex_dividend": 0.0, "volume": 18697.0, "adj_low": 15.7356605838842, "adj_open": 15.9477969581306, "adj_close": 15.7848345232088, "high": 16.25, "adj_volume": 18697.0, "low": 16.0, "date": "2016-08-16", "close": 16.05, "open": 16.2157, "adj_high": 15.9815302805074, "split_ratio": 1.0}, {"ex_dividend": 0.0, "volume": 4268.0, "adj_low": 15.8045040989387, "adj_open": 15.9225215533178, "adj_close": 15.8046024468173, "high": 16.38, "adj_volume": 4268.0, "low": 16.07, "date": "2016-08-15", "close": 16.0701, "open": 16.19, "adj_high": 16.1093825227514, "split_ratio": 1.0}, {"ex_dividend": 0.0, "volume": 2538.0, "adj_low": 15.8789534430762, "adj_open": 15.8789534430762, "adj_close": 16.0700433712917, "high": 16.35, "adj_volume": 2538.0, "low": 16.1457, "date": "2016-08-12", "close": 16.34, "open": 16.1457, "adj_high": 16.0798781591566, "split_ratio": 1.0}, {"ex_dividend": 0.0, "volume": 9449.0, "adj_low": 15.755330159614, "adj_open": 15.9421911290476, "adj_close": 15.9323563411827, "high": 16.26, "adj_volume": 9449.0, "low": 16.02, "date": "2016-08-11", "close": 16.2, "open": 16.21, "adj_high": 15.9913650683723, "split_ratio": 1.0}, {"ex_dividend": 0.0, "volume": 4512.0, "adj_low": 15.9520259169126, "adj_open": 15.9520259169126, "adj_close": 15.9815302805074, "high": 16.25, "adj_volume": 4512.0, "low": 16.22, "date": "2016-08-10", "close": 16.25, "open": 16.22, "adj_high": 15.9815302805074, "split_ratio": 1.0}, {"ex_dividend": 0.0, "volume": 2253.0, "adj_low": 15.8340084625334, "adj_open": 15.9716954926424, "adj_close": 15.9716954926424, "high": 16.25, "adj_volume": 2253.0, "low": 16.1, "date": "2016-08-09", "close": 16.24, "open": 16.24, "adj_high": 15.9815302805074, "split_ratio": 1.0}, {"ex_dividend": 0.0, "volume": 831.0, "adj_low": 15.9815302805074, "adj_open": 15.9815302805074, "adj_close": 15.9815302805074, "high": 16.25, "adj_volume": 831.0, "low": 16.25, "date": "2016-08-08", "close": 16.25, "open": 16.25, "adj_high": 15.9815302805074, "split_ratio": 1.0}, {"ex_dividend": 0.0, "volume": 2895.0, "adj_low": 15.7651649474789, "adj_open": 16.0520457094989, "adj_close": 16.0110346441021, "high": 16.37, "adj_volume": 2895.0, "low": 16.03, "date": "2016-08-05", "close": 16.28, "open": 16.3217, "adj_high": 16.0995477348865, "split_ratio": 1.0}, {"ex_dividend": 0.0, "volume": 9187.0, "adj_low": 15.6963214324245, "adj_open": 15.6963214324245, "adj_close": 15.8340084625334, "high": 16.2, "adj_volume": 9187.0, "low": 15.96, "date": "2016-08-04", "close": 16.1, "open": 15.96, "adj_high": 15.9323563411827, "split_ratio": 1.0}, {"ex_dividend": 0.0, "volume": 6575.0, "adj_low": 15.6963214324245, "adj_open": 15.9126867654529, "adj_close": 15.8340084625334, "high": 16.18, "adj_volume": 6575.0, "low": 15.96, "date": "2016-08-03", "close": 16.1, "open": 16.18, "adj_high": 15.9126867654529, "split_ratio": 1.0}, {"ex_dividend": 0.0, "volume": 4325.0, "adj_low": 15.9083594587923, "adj_open": 16.1290520984813, "adj_close": 15.9913650683723, "high": 16.4, "adj_volume": 4325.0, "low": 16.1756, "date": "2016-08-02", "close": 16.26, "open": 16.4, "adj_high": 16.1290520984813, "split_ratio": 1.0}, {"ex_dividend": 0.0, "volume": 7676.0, "adj_low": 15.6963214324245, "adj_open": 15.6963214324245, "adj_close": 15.9324546890614, "high": 16.2001, "adj_volume": 7676.0, "low": 15.96, "date": "2016-08-01", "close": 16.2001, "open": 15.96, "adj_high": 15.9324546890614, "split_ratio": 1.0}, {"ex_dividend": 0.0, "volume": 10876.0, "adj_low": 15.3422690692871, "adj_open": 15.489790887261, "adj_close": 15.5881387659102, "high": 16.02, "adj_volume": 10876.0, "low": 15.6, "date": "2016-07-29", "close": 15.85, "open": 15.75, "adj_high": 15.755330159614, "split_ratio": 1.0}, {"ex_dividend": 0.0, "volume": 2908.0, "adj_low": 15.4307821600714, "adj_open": 15.4307821600714, "adj_close": 15.617643129505, "high": 15.88, "adj_volume": 2908.0, "low": 15.69, "date": "2016-07-28", "close": 15.88, "open": 15.69, "adj_high": 15.617643129505, "split_ratio": 1.0}, {"ex_dividend": 0.0, "volume": 16513.0, "adj_low": 15.2734255542326, "adj_open": 15.8831824018581, "adj_close": 15.4789726206096, "high": 16.15, "adj_volume": 16513.0, "low": 15.53, "date": "2016-07-27", "close": 15.739, "open": 16.15, "adj_high": 15.8831824018581, "split_ratio": 1.0}, {"ex_dividend": 0.0, "volume": 2525.0, "adj_low": 15.6699642009464, "adj_open": 15.8831824018581, "adj_close": 15.6699642009464, "high": 16.15, "adj_volume": 2525.0, "low": 15.9332, "date": "2016-07-26", "close": 15.9332, "open": 16.15, "adj_high": 15.8831824018581, "split_ratio": 1.0}, {"ex_dividend": 0.0, "volume": 7414.0, "adj_low": 15.7946693110737, "adj_open": 15.8243703704258, "adj_close": 15.7995867050062, "high": 16.0916, "adj_volume": 7414.0, "low": 16.06, "date": "2016-07-25", "close": 16.065, "open": 16.0902, "adj_high": 15.8257472407269, "split_ratio": 1.0}, {"ex_dividend": 0.0, "volume": 4530.0, "adj_low": 15.8143388868036, "adj_open": 15.8830840539794, "adj_close": 15.8143388868036, "high": 16.1499, "adj_volume": 4530.0, "low": 16.08, "date": "2016-07-22", "close": 16.08, "open": 16.1499, "adj_high": 15.8830840539794, "split_ratio": 1.0}, {"ex_dividend": 0.0, "volume": 3759.0, "adj_low": 15.75926407476, "adj_open": 15.8831824018581, "adj_close": 15.75926407476, "high": 16.15, "adj_volume": 3759.0, "low": 16.024, "date": "2016-07-21", "close": 16.024, "open": 16.15, "adj_high": 15.8831824018581, "split_ratio": 1.0}, {"ex_dividend": 0.0, "volume": 1158.0, "adj_low": 15.9126867654529, "adj_open": 16.1192173106163, "adj_close": 15.9126867654529, "high": 16.39, "adj_volume": 1158.0, "low": 16.18, "date": "2016-07-20", "close": 16.18, "open": 16.39, "adj_high": 16.1192173106163, "split_ratio": 1.0}, {"ex_dividend": 0.0, "volume": 683.0, "adj_low": 15.8045040989387, "adj_open": 15.8045040989387, "adj_close": 15.9225215533178, "high": 16.19, "adj_volume": 683.0, "low": 16.07, "date": "2016-07-19", "close": 16.19, "open": 16.07, "adj_high": 15.9225215533178, "split_ratio": 1.0}, {"ex_dividend": 0.0, "volume": 5760.0, "adj_low": 15.983595585959, "adj_open": 16.0602085834268, "adj_close": 15.9913650683723, "high": 16.33, "adj_volume": 5760.0, "low": 16.2521, "date": "2016-07-18", "close": 16.26, "open": 16.33, "adj_high": 16.0602085834268, "split_ratio": 1.0}, {"ex_dividend": 0.0, "volume": 8451.0, "adj_low": 15.9225215533178, "adj_open": 15.9913650683723, "adj_close": 15.9913650683723, "high": 16.32, "adj_volume": 8451.0, "low": 16.19, "date": "2016-07-15", "close": 16.26, "open": 16.26, "adj_high": 16.0503737955618, "split_ratio": 1.0}, {"ex_dividend": 0.0, "volume": 10401.0, "adj_low": 15.9815302805074, "adj_open": 16.0995477348865, "adj_close": 15.9913650683723, "high": 16.37, "adj_volume": 10401.0, "low": 16.25, "date": "2016-07-14", "close": 16.26, "open": 16.37, "adj_high": 16.0995477348865, "split_ratio": 1.0}, {"ex_dividend": 0.0, "volume": 0.0, "adj_low": 15.9716954926424, "adj_open": 15.9716954926424, "adj_close": 15.9716954926424, "high": 16.24, "adj_volume": 0.0, "low": 16.24, "date": "2016-07-13", "close": 16.24, "open": 16.24, "adj_high": 15.9716954926424, "split_ratio": 1.0}, {"ex_dividend": 0.0, "volume": 2392.0, "adj_low": 15.8943940600241, "adj_open": 15.8943940600241, "adj_close": 15.9716954926424, "high": 16.3, "adj_volume": 2392.0, "low": 16.1614, "date": "2016-07-12", "close": 16.24, "open": 16.1614, "adj_high": 16.030704219832, "split_ratio": 1.0}, {"ex_dividend": 0.0, "volume": 12790.0, "adj_low": 15.7749997353439, "adj_open": 15.7848345232088, "adj_close": 15.8827890103435, "high": 16.1501, "adj_volume": 12790.0, "low": 16.04, "date": "2016-07-11", "close": 16.1496, "open": 16.05, "adj_high": 15.8832807497367, "split_ratio": 1.0}, {"ex_dividend": 0.0, "volume": 8286.0, "adj_low": 15.6864866445595, "adj_open": 15.8831824018581, "adj_close": 15.700943782721, "high": 16.15, "adj_volume": 8286.0, "low": 15.95, "date": "2016-07-08", "close": 15.9647, "open": 16.15, "adj_high": 15.8831824018581, "split_ratio": 1.0}, {"ex_dividend": 0.0, "volume": 0.0, "adj_low": 15.7356605838842, "adj_open": 15.7356605838842, "adj_close": 15.7356605838842, "high": 16.0, "adj_volume": 0.0, "low": 16.0, "date": "2016-07-07", "close": 16.0, "open": 16.0, "adj_high": 15.7356605838842, "split_ratio": 1.0}, {"ex_dividend": 0.0, "volume": 425.0, "adj_low": 15.6569822809647, "adj_open": 15.6569822809647, "adj_close": 15.7356605838842, "high": 16.0, "adj_volume": 425.0, "low": 15.92, "date": "2016-07-06", "close": 16.0, "open": 15.92, "adj_high": 15.7356605838842, "split_ratio": 1.0}, {"ex_dividend": 0.0, "volume": 924.0, "adj_low": 15.7843427838155, "adj_open": 15.9225215533178, "adj_close": 15.8241736746685, "high": 16.19, "adj_volume": 924.0, "low": 16.0495, "date": "2016-07-05", "close": 16.09, "open": 16.19, "adj_high": 15.9225215533178, "split_ratio": 1.0}, {"ex_dividend": 0.0, "volume": 1613.0, "adj_low": 15.8733476139931, "adj_open": 15.8733476139931, "adj_close": 15.8831824018581, "high": 16.15, "adj_volume": 1613.0, "low": 16.14, "date": "2016-07-01", "close": 16.15, "open": 16.14, "adj_high": 15.8831824018581, "split_ratio": 1.0}, {"ex_dividend": 0.0, "volume": 2614.0, "adj_low": 15.6865849924382, "adj_open": 15.6865849924382, "adj_close": 15.7356605838842, "high": 16.15, "adj_volume": 2614.0, "low": 15.9501, "date": "2016-06-30", "close": 16.0, "open": 15.9501, "adj_high": 15.8831824018581, "split_ratio": 1.0}, {"ex_dividend": 0.0, "volume": 4512.0, "adj_low": 15.6864866445595, "adj_open": 15.7356605838842, "adj_close": 15.7454953717491, "high": 16.01, "adj_volume": 4512.0, "low": 15.95, "date": "2016-06-29", "close": 16.01, "open": 16.0, "adj_high": 15.7454953717491, "split_ratio": 1.0}, {"ex_dividend": 0.0, "volume": 2050.0, "adj_low": 15.6833395124427, "adj_open": 15.8241736746685, "adj_close": 15.7749997353439, "high": 16.0999, "adj_volume": 2050.0, "low": 15.9468, "date": "2016-06-28", "close": 16.04, "open": 16.09, "adj_high": 15.8339101146548, "split_ratio": 1.0}, {"ex_dividend": 0.0, "volume": 4433.0, "adj_low": 15.4406169479363, "adj_open": 15.4406169479363, "adj_close": 15.489790887261, "high": 16.07, "adj_volume": 4433.0, "low": 15.7, "date": "2016-06-27", "close": 15.75, "open": 15.7, "adj_high": 15.8045040989387, "split_ratio": 1.0}, {"ex_dividend": 0.0, "volume": 17264.0, "adj_low": 15.5389648265856, "adj_open": 15.6374110531135, "adj_close": 15.5389648265856, "high": 16.0184, "adj_volume": 17264.0, "low": 15.8, "date": "2016-06-24", "close": 15.8, "open": 15.9001, "adj_high": 15.7537565935556, "split_ratio": 1.0}, {"ex_dividend": 0.0, "volume": 8453.0, "adj_low": 15.7749997353439, "adj_open": 15.7789336504898, "adj_close": 16.1192173106163, "high": 16.39, "adj_volume": 8453.0, "low": 16.04, "date": "2016-06-23", "close": 16.39, "open": 16.044, "adj_high": 16.1192173106163, "split_ratio": 1.0}, {"ex_dividend": 0.0, "volume": 609.0, "adj_low": 15.6471474930998, "adj_open": 15.6471474930998, "adj_close": 15.6668170688297, "high": 16.05, "adj_volume": 609.0, "low": 15.91, "date": "2016-06-22", "close": 15.93, "open": 15.91, "adj_high": 15.7848345232088, "split_ratio": 1.0}, {"ex_dividend": 0.0, "volume": 209.0, "adj_low": 15.7159910081543, "adj_open": 15.7159910081543, "adj_close": 15.8733476139931, "high": 16.14, "adj_volume": 209.0, "low": 15.98, "date": "2016-06-21", "close": 16.14, "open": 15.98, "adj_high": 15.8733476139931, "split_ratio": 1.0}, {"ex_dividend": 0.0, "volume": 789.0, "adj_low": 15.6373127052349, "adj_open": 15.6373127052349, "adj_close": 15.7471672856861, "high": 16.09, "adj_volume": 789.0, "low": 15.9, "date": "2016-06-20", "close": 16.0117, "open": 15.9, "adj_high": 15.8241736746685, "split_ratio": 1.0}, {"ex_dividend": 0.0, "volume": 3836.0, "adj_low": 15.6569822809647, "adj_open": 15.7159910081543, "adj_close": 15.6569822809647, "high": 15.98, "adj_volume": 3836.0, "low": 15.92, "date": "2016-06-17", "close": 15.92, "open": 15.98, "adj_high": 15.7159910081543, "split_ratio": 1.0}, {"ex_dividend": 0.16, "volume": 8254.0, "adj_low": 15.6864866445595, "adj_open": 15.7258257960192, "adj_close": 15.6864866445595, "high": 16.0, "adj_volume": 8254.0, "low": 15.95, "date": "2016-06-16", "close": 15.95, "open": 15.99, "adj_high": 15.7356605838842, "split_ratio": 1.0}, {"ex_dividend": 0.0, "volume": 0.0, "adj_low": 15.6445196939462, "adj_open": 15.6445196939462, "adj_close": 15.6445196939462, "high": 16.0669, "adj_volume": 0.0, "low": 16.0669, "date": "2016-06-15", "close": 16.0669, "open": 16.0669, "adj_high": 15.6445196939462, "split_ratio": 1.0}, {"ex_dividend": 0.0, "volume": 1845.0, "adj_low": 15.6341983557443, "adj_open": 15.6572753100259, "adj_close": 15.6445196939462, "high": 16.08, "adj_volume": 1845.0, "low": 16.0563, "date": "2016-06-14", "close": 16.0669, "open": 16.08, "adj_high": 15.6572753100259, "split_ratio": 1.0}, {"ex_dividend": 0.0, "volume": 9100.0, "adj_low": 15.618326863981, "adj_open": 15.7255324617195, "adj_close": 15.6280639754923, "high": 16.18, "adj_volume": 9100.0, "low": 16.04, "date": "2016-06-13", "close": 16.05, "open": 16.1501, "adj_high": 15.754646425138, "split_ratio": 1.0}, {"ex_dividend": 0.0, "volume": 202.0, "adj_low": 15.9201773208286, "adj_open": 15.9201773208286, "adj_close": 15.9201773208286, "high": 16.35, "adj_volume": 202.0, "low": 16.35, "date": "2016-06-10", "close": 16.35, "open": 16.35, "adj_high": 15.9201773208286, "split_ratio": 1.0}, {"ex_dividend": 0.0, "volume": 6223.0, "adj_low": 15.7254350906044, "adj_open": 15.9201773208286, "adj_close": 15.8130690942053, "high": 16.35, "adj_volume": 6223.0, "low": 16.15, "date": "2016-06-09", "close": 16.24, "open": 16.35, "adj_high": 15.9201773208286, "split_ratio": 1.0}, {"ex_dividend": 0.0, "volume": 4244.0, "adj_low": 15.7254350906044, "adj_open": 15.7254350906044, "adj_close": 15.7254350906044, "high": 16.2, "adj_volume": 4244.0, "low": 16.15, "date": "2016-06-08", "close": 16.15, "open": 16.15, "adj_high": 15.7741206481604, "split_ratio": 1.0}, {"ex_dividend": 0.0, "volume": 4924.0, "adj_low": 15.5793784179362, "adj_open": 15.5793784179362, "adj_close": 15.6961263849556, "high": 16.2, "adj_volume": 4924.0, "low": 16.0, "date": "2016-06-07", "close": 16.1199, "open": 16.0, "adj_high": 15.7741206481604, "split_ratio": 1.0}, {"ex_dividend": 0.0, "volume": 5177.0, "adj_low": 15.3944706703383, "adj_open": 15.3944706703383, "adj_close": 15.6378010870035, "high": 16.2, "adj_volume": 5177.0, "low": 15.8101, "date": "2016-06-06", "close": 16.06, "open": 15.8101, "adj_high": 15.7741206481604, "split_ratio": 1.0}, {"ex_dividend": 0.0, "volume": 1800.0, "adj_low": 15.4820073028241, "adj_open": 15.4820073028241, "adj_close": 15.5599041949138, "high": 16.0, "adj_volume": 1800.0, "low": 15.9, "date": "2016-06-03", "close": 15.98, "open": 15.9, "adj_high": 15.5793784179362, "split_ratio": 1.0}, {"ex_dividend": 0.0, "volume": 1045.0, "adj_low": 15.4333217452681, "adj_open": 15.4820073028241, "adj_close": 15.4333217452681, "high": 15.9, "adj_volume": 1045.0, "low": 15.85, "date": "2016-06-02", "close": 15.85, "open": 15.9, "adj_high": 15.4820073028241, "split_ratio": 1.0}, {"ex_dividend": 0.0, "volume": 3427.0, "adj_low": 15.5793784179362, "adj_open": 15.6767495330483, "adj_close": 15.5793784179362, "high": 16.1596, "adj_volume": 3427.0, "low": 16.0, "date": "2016-06-01", "close": 16.0, "open": 16.1, "adj_high": 15.7347827176551, "split_ratio": 1.0}, {"ex_dividend": 0.0, "volume": 3323.0, "adj_low": 15.569641306425, "adj_open": 15.8812288747837, "adj_close": 15.569641306425, "high": 16.3101, "adj_volume": 3323.0, "low": 15.99, "date": "2016-05-31", "close": 15.99, "open": 16.31, "adj_high": 15.8813262458988, "split_ratio": 1.0}, {"ex_dividend": 0.0, "volume": 1492.0, "adj_low": 15.6864866445595, "adj_open": 15.8714917632725, "adj_close": 15.8812288747837, "high": 16.33, "adj_volume": 1492.0, "low": 16.11, "date": "2016-05-27", "close": 16.31, "open": 16.3, "adj_high": 15.9007030978061, "split_ratio": 1.0}, {"ex_dividend": 0.0, "volume": 100.0, "adj_low": 15.9007030978061, "adj_open": 15.9007030978061, "adj_close": 15.9007030978061, "high": 16.33, "adj_volume": 100.0, "low": 16.33, "date": "2016-05-26", "close": 16.33, "open": 16.33, "adj_high": 15.9007030978061, "split_ratio": 1.0}, {"ex_dividend": 0.0, "volume": 130.0, "adj_low": 15.5793784179362, "adj_open": 15.5793784179362, "adj_close": 15.5793784179362, "high": 16.0, "adj_volume": 130.0, "low": 16.0, "date": "2016-05-25", "close": 16.0, "open": 16.0, "adj_high": 15.5793784179362, "split_ratio": 1.0}, {"ex_dividend": 0.0, "volume": 3317.0, "adj_low": 15.5306928603802, "adj_open": 15.5599041949138, "adj_close": 15.5793784179362, "high": 16.0, "adj_volume": 3317.0, "low": 15.95, "date": "2016-05-24", "close": 16.0, "open": 15.98, "adj_high": 15.5793784179362, "split_ratio": 1.0}, {"ex_dividend": 0.0, "volume": 599.0, "adj_low": 15.5307902314953, "adj_open": 15.5599041949138, "adj_close": 15.569641306425, "high": 15.99, "adj_volume": 599.0, "low": 15.9501, "date": "2016-05-23", "close": 15.99, "open": 15.98, "adj_high": 15.569641306425, "split_ratio": 1.0}, {"ex_dividend": 0.0, "volume": 18001.0, "adj_low": 15.335950630156, "adj_open": 15.4820073028241, "adj_close": 15.5793784179362, "high": 16.4, "adj_volume": 18001.0, "low": 15.75, "date": "2016-05-20", "close": 16.0, "open": 15.9, "adj_high": 15.9688628783846, "split_ratio": 1.0}, {"ex_dividend": 0.0, "volume": 5904.0, "adj_low": 15.3943732992232, "adj_open": 15.5793784179362, "adj_close": 15.5209557488689, "high": 16.0, "adj_volume": 5904.0, "low": 15.81, "date": "2016-05-19", "close": 15.94, "open": 16.0, "adj_high": 15.5793784179362, "split_ratio": 1.0}, {"ex_dividend": 0.0, "volume": 4298.0, "adj_low": 15.4439351968153, "adj_open": 15.5793784179362, "adj_close": 15.988337101407, "high": 16.42, "adj_volume": 4298.0, "low": 15.8609, "date": "2016-05-18", "close": 16.42, "open": 16.0, "adj_high": 15.988337101407, "split_ratio": 1.0}, {"ex_dividend": 0.0, "volume": 852.0, "adj_low": 15.4586382351972, "adj_open": 15.569641306425, "adj_close": 15.569641306425, "high": 15.99, "adj_volume": 852.0, "low": 15.876, "date": "2016-05-17", "close": 15.99, "open": 15.99, "adj_high": 15.569641306425, "split_ratio": 1.0}, {"ex_dividend": 0.0, "volume": 8519.0, "adj_low": 15.4246557160231, "adj_open": 15.5793784179362, "adj_close": 15.5793784179362, "high": 16.0058, "adj_volume": 8519.0, "low": 15.8411, "date": "2016-05-16", "close": 16.0, "open": 16.0, "adj_high": 15.5850259426127, "split_ratio": 1.0}, {"ex_dividend": 0.0, "volume": 12352.0, "adj_low": 15.1898939574878, "adj_open": 15.1898939574878, "adj_close": 15.5793784179362, "high": 16.0, "adj_volume": 12352.0, "low": 15.6, "date": "2016-05-13", "close": 16.0, "open": 15.6, "adj_high": 15.5793784179362, "split_ratio": 1.0}, {"ex_dividend": 0.0, "volume": 1400.0, "adj_low": 15.1898939574878, "adj_open": 15.1937888020923, "adj_close": 15.1898939574878, "high": 15.605, "adj_volume": 1400.0, "low": 15.6, "date": "2016-05-12", "close": 15.6, "open": 15.604, "adj_high": 15.1947625132434, "split_ratio": 1.0}, {"ex_dividend": 0.0, "volume": 1260.0, "adj_low": 15.150945511443, "adj_open": 15.5599041949138, "adj_close": 15.150945511443, "high": 15.98, "adj_volume": 1260.0, "low": 15.56, "date": "2016-05-11", "close": 15.56, "open": 15.98, "adj_high": 15.5599041949138, "split_ratio": 1.0}, {"ex_dividend": 0.0, "volume": 7200.0, "adj_low": 15.5501670834026, "adj_open": 15.5501670834026, "adj_close": 15.5793784179362, "high": 16.0, "adj_volume": 7200.0, "low": 15.97, "date": "2016-05-10", "close": 16.0, "open": 15.97, "adj_high": 15.5793784179362, "split_ratio": 1.0}, {"ex_dividend": 0.0, "volume": 1082.0, "adj_low": 15.335950630156, "adj_open": 15.5793784179362, "adj_close": 15.4917444143353, "high": 16.0, "adj_volume": 1082.0, "low": 15.75, "date": "2016-05-09", "close": 15.91, "open": 16.0, "adj_high": 15.5793784179362, "split_ratio": 1.0}, {"ex_dividend": 0.0, "volume": 5862.0, "adj_low": 15.335950630156, "adj_open": 15.4206635003035, "adj_close": 15.5208583777538, "high": 15.98, "adj_volume": 5862.0, "low": 15.75, "date": "2016-05-06", "close": 15.9399, "open": 15.837, "adj_high": 15.5599041949138, "split_ratio": 1.0}, {"ex_dividend": 0.0, "volume": 586.0, "adj_low": 15.384636187712, "adj_open": 15.384636187712, "adj_close": 15.4333217452681, "high": 15.85, "adj_volume": 586.0, "low": 15.8, "date": "2016-05-05", "close": 15.85, "open": 15.8, "adj_high": 15.4333217452681, "split_ratio": 1.0}, {"ex_dividend": 0.0, "volume": 6610.0, "adj_low": 15.3554248531784, "adj_open": 15.3554248531784, "adj_close": 15.3847335588271, "high": 16.0001, "adj_volume": 6610.0, "low": 15.77, "date": "2016-05-04", "close": 15.8001, "open": 15.77, "adj_high": 15.5794757890513, "split_ratio": 1.0}, {"ex_dividend": 0.0, "volume": 0.0, "adj_low": 15.3554248531784, "adj_open": 15.3554248531784, "adj_close": 15.3554248531784, "high": 15.77, "adj_volume": 0.0, "low": 15.77, "date": "2016-05-03", "close": 15.77, "open": 15.77, "adj_high": 15.3554248531784, "split_ratio": 1.0}, {"ex_dividend": 0.0, "volume": 3432.0, "adj_low": 15.3554248531784, "adj_open": 15.5793784179362, "adj_close": 15.3554248531784, "high": 16.0, "adj_volume": 3432.0, "low": 15.77, "date": "2016-05-02", "close": 15.77, "open": 16.0, "adj_high": 15.5793784179362, "split_ratio": 1.0}, {"ex_dividend": 0.0, "volume": 1.0, "adj_low": 15.5792810468211, "adj_open": 15.5792810468211, "adj_close": 15.5792810468211, "high": 15.9999, "adj_volume": 1.0, "low": 15.9999, "date": "2016-04-29", "close": 15.9999, "open": 15.9999, "adj_high": 15.5792810468211, "split_ratio": 1.0}, {"ex_dividend": 0.0, "volume": 725.0, "adj_low": 15.5792810468211, "adj_open": 15.5792810468211, "adj_close": 15.5792810468211, "high": 15.9999, "adj_volume": 725.0, "low": 15.9999, "date": "2016-04-28", "close": 15.9999, "open": 15.9999, "adj_high": 15.5792810468211, "split_ratio": 1.0}, {"ex_dividend": 0.0, "volume": 13827.0, "adj_low": 15.4820073028241, "adj_open": 15.6670124215371, "adj_close": 15.7741206481604, "high": 16.35, "adj_volume": 13827.0, "low": 15.9, "date": "2016-04-27", "close": 16.2, "open": 16.09, "adj_high": 15.9201773208286, "split_ratio": 1.0}, {"ex_dividend": 0.0, "volume": 451.0, "adj_low": 15.6280639754923, "adj_open": 15.8228062057165, "adj_close": 15.6280639754923, "high": 16.25, "adj_volume": 451.0, "low": 16.05, "date": "2016-04-26", "close": 16.05, "open": 16.25, "adj_high": 15.8228062057165, "split_ratio": 1.0}, {"ex_dividend": 0.0, "volume": 472.0, "adj_low": 15.2385795150439, "adj_open": 15.2385795150439, "adj_close": 15.2385795150439, "high": 15.65, "adj_volume": 472.0, "low": 15.65, "date": "2016-04-25", "close": 15.65, "open": 15.65, "adj_high": 15.2385795150439, "split_ratio": 1.0}, {"ex_dividend": 0.0, "volume": 10264.0, "adj_low": 15.1704197344654, "adj_open": 15.1704197344654, "adj_close": 15.2872650725999, "high": 15.7, "adj_volume": 10264.0, "low": 15.58, "date": "2016-04-22", "close": 15.7, "open": 15.58, "adj_high": 15.2872650725999, "split_ratio": 1.0}, {"ex_dividend": 0.0, "volume": 899.0, "adj_low": 15.150945511443, "adj_open": 15.150945511443, "adj_close": 15.1704197344654, "high": 15.58, "adj_volume": 899.0, "low": 15.56, "date": "2016-04-21", "close": 15.58, "open": 15.56, "adj_high": 15.1704197344654, "split_ratio": 1.0}, {"ex_dividend": 0.0, "volume": 0.0, "adj_low": 15.1483164913349, "adj_open": 15.1483164913349, "adj_close": 15.1483164913349, "high": 15.5573, "adj_volume": 0.0, "low": 15.5573, "date": "2016-04-20", "close": 15.5573, "open": 15.5573, "adj_high": 15.1483164913349, "split_ratio": 1.0}, {"ex_dividend": 0.0, "volume": 4020.0, "adj_low": 15.1119970653981, "adj_open": 15.335950630156, "adj_close": 15.1483164913349, "high": 15.75, "adj_volume": 4020.0, "low": 15.52, "date": "2016-04-19", "close": 15.5573, "open": 15.75, "adj_high": 15.335950630156, "split_ratio": 1.0}, {"ex_dividend": 0.0, "volume": 2444.0, "adj_low": 15.1022599538869, "adj_open": 15.1632142719471, "adj_close": 15.1022599538869, "high": 15.5726, "adj_volume": 2444.0, "low": 15.51, "date": "2016-04-18", "close": 15.51, "open": 15.5726, "adj_high": 15.1632142719471, "split_ratio": 1.0}, {"ex_dividend": 0.0, "volume": 2320.0, "adj_low": 15.1412083999318, "adj_open": 15.2288424035326, "adj_close": 15.3068366667374, "high": 15.7201, "adj_volume": 2320.0, "low": 15.55, "date": "2016-04-15", "close": 15.7201, "open": 15.64, "adj_high": 15.3068366667374, "split_ratio": 1.0}, {"ex_dividend": 0.0, "volume": 49.0, "adj_low": 15.1606826229542, "adj_open": 15.1606826229542, "adj_close": 15.1606826229542, "high": 15.57, "adj_volume": 49.0, "low": 15.57, "date": "2016-04-14", "close": 15.57, "open": 15.57, "adj_high": 15.1606826229542, "split_ratio": 1.0}, {"ex_dividend": 0.0, "volume": 430.0, "adj_low": 15.0925228423757, "adj_open": 15.0925228423757, "adj_close": 15.1606826229542, "high": 15.57, "adj_volume": 430.0, "low": 15.5, "date": "2016-04-13", "close": 15.57, "open": 15.5, "adj_high": 15.1606826229542, "split_ratio": 1.0}, {"ex_dividend": 0.0, "volume": 2736.0, "adj_low": 15.0925228423757, "adj_open": 15.1412083999318, "adj_close": 15.0926202134908, "high": 15.6, "adj_volume": 2736.0, "low": 15.5, "date": "2016-04-12", "close": 15.5001, "open": 15.55, "adj_high": 15.1898939574878, "split_ratio": 1.0}, {"ex_dividend": 0.0, "volume": 1163.0, "adj_low": 15.0925228423757, "adj_open": 15.335950630156, "adj_close": 15.1898939574878, "high": 15.7501, "adj_volume": 1163.0, "low": 15.5, "date": "2016-04-11", "close": 15.6, "open": 15.75, "adj_high": 15.3360480012711, "split_ratio": 1.0}, {"ex_dividend": 0.0, "volume": 7500.0, "adj_low": 15.1217341769093, "adj_open": 16.0857082165191, "adj_close": 15.4041104107344, "high": 16.75, "adj_volume": 7500.0, "low": 15.53, "date": "2016-04-08", "close": 15.82, "open": 16.52, "adj_high": 16.309661781277, "split_ratio": 1.0}, {"ex_dividend": 0.0, "volume": 200.0, "adj_low": 15.0925228423757, "adj_open": 15.0925228423757, "adj_close": 15.0926202134908, "high": 15.5001, "adj_volume": 200.0, "low": 15.5, "date": "2016-04-07", "close": 15.5001, "open": 15.5, "adj_high": 15.0926202134908, "split_ratio": 1.0}, {"ex_dividend": 0.0, "volume": 3320.0, "adj_low": 15.0437399137045, "adj_open": 15.0925228423757, "adj_close": 15.0904780489583, "high": 15.5064, "adj_volume": 3320.0, "low": 15.4499, "date": "2016-04-06", "close": 15.4979, "open": 15.5, "adj_high": 15.0987545937429, "split_ratio": 1.0}, {"ex_dividend": 0.0, "volume": 4335.0, "adj_low": 14.8490950545955, "adj_open": 14.9951517272636, "adj_close": 14.8490950545955, "high": 15.5615, "adj_volume": 4335.0, "low": 15.25, "date": "2016-04-05", "close": 15.25, "open": 15.4, "adj_high": 15.1524060781696, "split_ratio": 1.0}, {"ex_dividend": 0.0, "volume": 1423.0, "adj_low": 15.1672064876667, "adj_open": 15.1672064876667, "adj_close": 15.1672064876667, "high": 15.5767, "adj_volume": 1423.0, "low": 15.5767, "date": "2016-04-04", "close": 15.5767, "open": 15.5767, "adj_high": 15.1672064876667, "split_ratio": 1.0}, {"ex_dividend": 0.0, "volume": 33.0, "adj_low": 15.0925228423757, "adj_open": 15.0925228423757, "adj_close": 15.0925228423757, "high": 15.5, "adj_volume": 33.0, "low": 15.5, "date": "2016-04-01", "close": 15.5, "open": 15.5, "adj_high": 15.0925228423757, "split_ratio": 1.0}, {"ex_dividend": 0.0, "volume": 3447.0, "adj_low": 15.0925228423757, "adj_open": 15.0925228423757, "adj_close": 15.0925228423757, "high": 16.8299, "adj_volume": 3447.0, "low": 15.5, "date": "2016-03-31", "close": 15.5, "open": 15.5, "adj_high": 16.3874613022515, "split_ratio": 1.0}, {"ex_dividend": 0.0, "volume": 3226.0, "adj_low": 14.750555486102, "adj_open": 15.0826883597494, "adj_close": 15.0438372848197, "high": 15.5, "adj_volume": 3226.0, "low": 15.1488, "date": "2016-03-30", "close": 15.45, "open": 15.4899, "adj_high": 15.0925228423757, "split_ratio": 1.0}, {"ex_dividend": 0.0, "volume": 1715.0, "adj_low": 14.5569817092591, "adj_open": 14.5569817092591, "adj_close": 14.7322497164609, "high": 15.18, "adj_volume": 1715.0, "low": 14.95, "date": "2016-03-29", "close": 15.13, "open": 14.95, "adj_high": 14.780935274017, "split_ratio": 1.0}, {"ex_dividend": 0.0, "volume": 3264.0, "adj_low": 14.7419868279721, "adj_open": 14.7419868279721, "adj_close": 14.780935274017, "high": 15.46, "adj_volume": 3264.0, "low": 15.14, "date": "2016-03-28", "close": 15.18, "open": 15.14, "adj_high": 15.0535743963309, "split_ratio": 1.0}, {"ex_dividend": 0.0, "volume": 2177.0, "adj_low": 15.0714906815115, "adj_open": 15.2872650725999, "adj_close": 15.0826883597494, "high": 15.7, "adj_volume": 2177.0, "low": 15.4784, "date": "2016-03-24", "close": 15.4899, "open": 15.7, "adj_high": 15.2872650725999, "split_ratio": 1.0}, {"ex_dividend": 0.0, "volume": 4754.0, "adj_low": 14.9756775042412, "adj_open": 15.335950630156, "adj_close": 15.0048888387748, "high": 15.75, "adj_volume": 4754.0, "low": 15.38, "date": "2016-03-23", "close": 15.41, "open": 15.75, "adj_high": 15.335950630156, "split_ratio": 1.0}, {"ex_dividend": 0.0, "volume": 21148.0, "adj_low": 15.1801568459766, "adj_open": 15.384636187712, "adj_close": 15.3456877416672, "high": 16.0, "adj_volume": 21148.0, "low": 15.59, "date": "2016-03-22", "close": 15.76, "open": 15.8, "adj_high": 15.5793784179362, "split_ratio": 1.0}, {"ex_dividend": 0.0, "volume": 1519.0, "adj_low": 15.384636187712, "adj_open": 15.4430588567793, "adj_close": 15.384636187712, "high": 15.86, "adj_volume": 1519.0, "low": 15.8, "date": "2016-03-21", "close": 15.8, "open": 15.86, "adj_high": 15.4430588567793, "split_ratio": 1.0}, {"ex_dividend": 0.0, "volume": 0.0, "adj_low": 15.5214426044445, "adj_open": 15.5214426044445, "adj_close": 15.5214426044445, "high": 15.9405, "adj_volume": 0.0, "low": 15.9405, "date": "2016-03-18", "close": 15.9405, "open": 15.9405, "adj_high": 15.5214426044445, "split_ratio": 1.0}, {"ex_dividend": 0.16, "volume": 9986.0, "adj_low": 15.3650645935745, "adj_open": 15.4041104107344, "adj_close": 15.5214426044445, "high": 15.99, "adj_volume": 9986.0, "low": 15.7799, "date": "2016-03-17", "close": 15.9405, "open": 15.82, "adj_high": 15.569641306425, "split_ratio": 1.0}, {"ex_dividend": 0.0, "volume": 3411.0, "adj_low": 15.1835484003603, "adj_open": 15.1978161156825, "adj_close": 15.3088729268395, "high": 16.48, "adj_volume": 3411.0, "low": 15.75, "date": "2016-03-16", "close": 15.88, "open": 15.7648, "adj_high": 15.8872938182818, "split_ratio": 1.0}, {"ex_dividend": 0.0, "volume": 1034.0, "adj_low": 15.1835484003603, "adj_open": 15.1835484003603, "adj_close": 15.2116018135953, "high": 15.7791, "adj_volume": 1034.0, "low": 15.75, "date": "2016-03-15", "close": 15.7791, "open": 15.75, "adj_high": 15.2116018135953, "split_ratio": 1.0}, {"ex_dividend": 0.0, "volume": 2170.0, "adj_low": 15.1835484003603, "adj_open": 15.8342719032329, "adj_close": 15.1835484003603, "high": 16.425, "adj_volume": 2170.0, "low": 15.75, "date": "2016-03-14", "close": 15.75, "open": 16.425, "adj_high": 15.8342719032329, "split_ratio": 1.0}, {"ex_dividend": 0.0, "volume": 337.0, "adj_low": 15.2414868929864, "adj_open": 15.2414868929864, "adj_close": 15.2414868929864, "high": 15.8101, "adj_volume": 337.0, "low": 15.8101, "date": "2016-03-11", "close": 15.8101, "open": 15.8101, "adj_high": 15.2414868929864, "split_ratio": 1.0}, {"ex_dividend": 0.0, "volume": 4758.0, "adj_low": 15.2606711858859, "adj_open": 15.3609308070693, "adj_close": 15.2606711858859, "high": 16.25, "adj_volume": 4758.0, "low": 15.83, "date": "2016-03-10", "close": 15.83, "open": 15.934, "adj_high": 15.6655658098955, "split_ratio": 1.0}, {"ex_dividend": 0.0, "volume": 9483.0, "adj_low": 15.1835484003603, "adj_open": 15.2703115340766, "adj_close": 15.1835484003603, "high": 16.6, "adj_volume": 9483.0, "low": 15.75, "date": "2016-03-09", "close": 15.75, "open": 15.84, "adj_high": 16.0029779965702, "split_ratio": 1.0}, {"ex_dividend": 0.0, "volume": 2163.0, "adj_low": 15.2799518822673, "adj_open": 15.2799518822673, "adj_close": 15.2799518822673, "high": 15.8501, "adj_volume": 2163.0, "low": 15.85, "date": "2016-03-08", "close": 15.85, "open": 15.85, "adj_high": 15.2800482857493, "split_ratio": 1.0}, {"ex_dividend": 0.0, "volume": 436.0, "adj_low": 15.424460701646, "adj_open": 15.424460701646, "adj_close": 15.424460701646, "high": 15.9999, "adj_volume": 436.0, "low": 15.9999, "date": "2016-03-07", "close": 15.9999, "open": 15.9999, "adj_high": 15.424460701646, "split_ratio": 1.0}, {"ex_dividend": 0.0, "volume": 1301.0, "adj_low": 15.2413904895045, "adj_open": 15.2413904895045, "adj_close": 15.2799518822673, "high": 15.85, "adj_volume": 1301.0, "low": 15.81, "date": "2016-03-04", "close": 15.85, "open": 15.81, "adj_high": 15.2799518822673, "split_ratio": 1.0}, {"ex_dividend": 0.0, "volume": 177.0, "adj_low": 15.1835484003603, "adj_open": 15.1835484003603, "adj_close": 15.1835484003603, "high": 15.75, "adj_volume": 177.0, "low": 15.75, "date": "2016-03-03", "close": 15.75, "open": 15.75, "adj_high": 15.1835484003603, "split_ratio": 1.0}, {"ex_dividend": 0.0, "volume": 3200.0, "adj_low": 15.2799518822673, "adj_open": 15.2799518822673, "adj_close": 15.2799518822673, "high": 15.85, "adj_volume": 3200.0, "low": 15.85, "date": "2016-03-02", "close": 15.85, "open": 15.85, "adj_high": 15.2799518822673, "split_ratio": 1.0}, {"ex_dividend": 0.0, "volume": 0.0, "adj_low": 14.9425396955927, "adj_open": 14.9425396955927, "adj_close": 14.9425396955927, "high": 15.5, "adj_volume": 0.0, "low": 15.5, "date": "2016-03-01", "close": 15.5, "open": 15.5, "adj_high": 14.9425396955927, "split_ratio": 1.0}, {"ex_dividend": 0.0, "volume": 4256.0, "adj_low": 14.9425396955927, "adj_open": 15.2317501413138, "adj_close": 14.9425396955927, "high": 16.23, "adj_volume": 4256.0, "low": 15.5, "date": "2016-02-29", "close": 15.5, "open": 15.8, "adj_high": 15.6462851135141, "split_ratio": 1.0}, {"ex_dividend": 0.0, "volume": 3209.0, "adj_low": 15.2317501413138, "adj_open": 15.3185132750302, "adj_close": 15.2317501413138, "high": 16.0, "adj_volume": 3209.0, "low": 15.8, "date": "2016-02-26", "close": 15.8, "open": 15.89, "adj_high": 15.4245571051279, "split_ratio": 1.0}, {"ex_dividend": 0.0, "volume": 1303.0, "adj_low": 15.2799518822673, "adj_open": 15.2799518822673, "adj_close": 15.9740569519981, "high": 16.57, "adj_volume": 1303.0, "low": 15.85, "date": "2016-02-25", "close": 16.57, "open": 15.85, "adj_high": 15.9740569519981, "split_ratio": 1.0}, {"ex_dividend": 0.0, "volume": 555.0, "adj_low": 15.8400561121473, "adj_open": 15.848636022037, "adj_close": 15.8487324255189, "high": 16.44, "adj_volume": 555.0, "low": 16.431, "date": "2016-02-24", "close": 16.44, "open": 16.4399, "adj_high": 15.8487324255189, "split_ratio": 1.0}, {"ex_dividend": 0.0, "volume": 0.0, "adj_low": 15.8487324255189, "adj_open": 15.8487324255189, "adj_close": 15.8487324255189, "high": 16.44, "adj_volume": 0.0, "low": 16.44, "date": "2016-02-23", "close": 16.44, "open": 16.44, "adj_high": 15.8487324255189, "split_ratio": 1.0}, {"ex_dividend": 0.0, "volume": 773.0, "adj_low": 15.4033483391084, "adj_open": 15.4033483391084, "adj_close": 15.8487324255189, "high": 16.49, "adj_volume": 773.0, "low": 15.978, "date": "2016-02-22", "close": 16.44, "open": 15.978, "adj_high": 15.8969341664725, "split_ratio": 1.0}, {"ex_dividend": 0.0, "volume": 0.0, "adj_low": 15.2413904895045, "adj_open": 15.2413904895045, "adj_close": 15.2413904895045, "high": 15.81, "adj_volume": 0.0, "low": 15.81, "date": "2016-02-19", "close": 15.81, "open": 15.81, "adj_high": 15.2413904895045, "split_ratio": 1.0}, {"ex_dividend": 0.0, "volume": 18.0, "adj_low": 15.2413904895045, "adj_open": 15.2413904895045, "adj_close": 15.2413904895045, "high": 15.81, "adj_volume": 18.0, "low": 15.81, "date": "2016-02-18", "close": 15.81, "open": 15.81, "adj_high": 15.2413904895045, "split_ratio": 1.0}, {"ex_dividend": 0.0, "volume": 0.0, "adj_low": 15.2413904895045, "adj_open": 15.2413904895045, "adj_close": 15.2413904895045, "high": 15.81, "adj_volume": 0.0, "low": 15.81, "date": "2016-02-17", "close": 15.81, "open": 15.81, "adj_high": 15.2413904895045, "split_ratio": 1.0}, {"ex_dividend": 0.0, "volume": 2553.0, "adj_low": 15.2317501413138, "adj_open": 17.2080215204083, "adj_close": 15.2413904895045, "high": 17.85, "adj_volume": 2553.0, "low": 15.8, "date": "2016-02-16", "close": 15.81, "open": 17.85, "adj_high": 17.2080215204083, "split_ratio": 1.0}, {"ex_dividend": 0.0, "volume": 336.0, "adj_low": 15.2510308376952, "adj_open": 15.2510308376952, "adj_close": 15.3088729268395, "high": 15.88, "adj_volume": 336.0, "low": 15.82, "date": "2016-02-12", "close": 15.88, "open": 15.82, "adj_high": 15.3088729268395, "split_ratio": 1.0}, {"ex_dividend": 0.0, "volume": 211.0, "adj_low": 17.3044250023154, "adj_open": 17.3044250023154, "adj_close": 17.3186927176376, "high": 17.9648, "adj_volume": 211.0, "low": 17.95, "date": "2016-02-11", "close": 17.9648, "open": 17.95, "adj_high": 17.3186927176376, "split_ratio": 1.0}, {"ex_dividend": 0.0, "volume": 271.0, "adj_low": 15.2799518822673, "adj_open": 15.288628195639, "adj_close": 15.2799518822673, "high": 15.859, "adj_volume": 271.0, "low": 15.85, "date": "2016-02-10", "close": 15.85, "open": 15.859, "adj_high": 15.288628195639, "split_ratio": 1.0}, {"ex_dividend": 0.0, "volume": 1034.0, "adj_low": 15.8373568146539, "adj_open": 15.9065745146632, "adj_close": 15.8373568146539, "high": 16.5, "adj_volume": 1034.0, "low": 16.4282, "date": "2016-02-09", "close": 16.4282, "open": 16.5, "adj_high": 15.9065745146632, "split_ratio": 1.0}, {"ex_dividend": 0.0, "volume": 110.0, "adj_low": 15.9547762556167, "adj_open": 15.9547762556167, "adj_close": 15.9547762556167, "high": 16.55, "adj_volume": 110.0, "low": 16.55, "date": "2016-02-08", "close": 16.55, "open": 16.55, "adj_high": 15.9547762556167, "split_ratio": 1.0}, {"ex_dividend": 0.0, "volume": 2319.0, "adj_low": 15.2413904895045, "adj_open": 15.2413904895045, "adj_close": 15.2799518822673, "high": 15.85, "adj_volume": 2319.0, "low": 15.81, "date": "2016-02-05", "close": 15.85, "open": 15.81, "adj_high": 15.2799518822673, "split_ratio": 1.0}, {"ex_dividend": 0.0, "volume": 310.0, "adj_low": 15.4496220104238, "adj_open": 16.041539389333, "adj_close": 15.4496220104238, "high": 16.64, "adj_volume": 310.0, "low": 16.026, "date": "2016-02-04", "close": 16.026, "open": 16.64, "adj_high": 16.041539389333, "split_ratio": 1.0}, {"ex_dividend": 0.0, "volume": 10.0, "adj_low": 15.2317501413138, "adj_open": 15.2317501413138, "adj_close": 15.2317501413138, "high": 15.8, "adj_volume": 10.0, "low": 15.8, "date": "2016-02-03", "close": 15.8, "open": 15.8, "adj_high": 15.2317501413138, "split_ratio": 1.0}, {"ex_dividend": 0.0, "volume": 2888.0, "adj_low": 15.1353466594068, "adj_open": 15.1353466594068, "adj_close": 15.2317501413138, "high": 16.3831, "adj_volume": 2888.0, "low": 15.7, "date": "2016-02-02", "close": 15.8, "open": 15.7, "adj_high": 15.7938788443138, "split_ratio": 1.0}, {"ex_dividend": 0.0, "volume": 1273.0, "adj_low": 15.9065745146632, "adj_open": 15.9065745146632, "adj_close": 15.9065745146632, "high": 16.5, "adj_volume": 1273.0, "low": 16.5, "date": "2016-02-01", "close": 16.5, "open": 16.5, "adj_high": 15.9065745146632, "split_ratio": 1.0}, {"ex_dividend": 0.0, "volume": 2093.0, "adj_low": 14.9425396955927, "adj_open": 14.9425396955927, "adj_close": 15.4920395424629, "high": 16.5, "adj_volume": 2093.0, "low": 15.5, "date": "2016-01-29", "close": 16.07, "open": 15.5, "adj_high": 15.9065745146632, "split_ratio": 1.0}, {"ex_dividend": 0.0, "volume": 4936.0, "adj_low": 14.5183643752017, "adj_open": 15.4245571051279, "adj_close": 14.5665661161552, "high": 16.0, "adj_volume": 4936.0, "low": 15.06, "date": "2016-01-28", "close": 15.11, "open": 16.0, "adj_high": 15.4245571051279, "split_ratio": 1.0}, {"ex_dividend": 0.0, "volume": 100.0, "adj_low": 16.1379428712401, "adj_open": 16.1379428712401, "adj_close": 16.1379428712401, "high": 16.74, "adj_volume": 100.0, "low": 16.74, "date": "2016-01-27", "close": 16.74, "open": 16.74, "adj_high": 16.1379428712401, "split_ratio": 1.0}, {"ex_dividend": 0.0, "volume": 8701.0, "adj_low": 14.0749083584292, "adj_open": 16.3934120982938, "adj_close": 16.1379428712401, "high": 17.005, "adj_volume": 8701.0, "low": 14.6, "date": "2016-01-26", "close": 16.74, "open": 17.005, "adj_high": 16.3934120982938, "split_ratio": 1.0}, {"ex_dividend": 0.0, "volume": 914.0, "adj_low": 15.9547762556167, "adj_open": 15.9547762556167, "adj_close": 15.9548726590986, "high": 16.5501, "adj_volume": 914.0, "low": 16.55, "date": "2016-01-25", "close": 16.5501, "open": 16.55, "adj_high": 15.9548726590986, "split_ratio": 1.0}, {"ex_dividend": 0.0, "volume": 17909.0, "adj_low": 16.1475832194308, "adj_open": 16.1572235676215, "adj_close": 16.205425308575, "high": 16.84, "adj_volume": 17909.0, "low": 16.75, "date": "2016-01-22", "close": 16.81, "open": 16.76, "adj_high": 16.2343463531471, "split_ratio": 1.0}, {"ex_dividend": 0.0, "volume": 3100.0, "adj_low": 16.2921884422914, "adj_open": 16.2921884422914, "adj_close": 16.2921884422914, "high": 16.94, "adj_volume": 3100.0, "low": 16.9, "date": "2016-01-21", "close": 16.9, "open": 16.9, "adj_high": 16.3307498350542, "split_ratio": 1.0}, {"ex_dividend": 0.0, "volume": 8935.0, "adj_low": 16.1475832194308, "adj_open": 16.3982322723891, "adj_close": 16.3982322723891, "high": 17.01, "adj_volume": 8935.0, "low": 16.75, "date": "2016-01-20", "close": 17.01, "open": 17.01, "adj_high": 16.3982322723891, "split_ratio": 1.0}, {"ex_dividend": 0.0, "volume": 2665.0, "adj_low": 16.629600628966, "adj_open": 17.7671617154692, "adj_close": 16.629600628966, "high": 18.43, "adj_volume": 2665.0, "low": 17.25, "date": "2016-01-19", "close": 17.25, "open": 18.43, "adj_high": 17.7671617154692, "split_ratio": 1.0}, {"ex_dividend": 0.0, "volume": 4270.0, "adj_low": 17.4567425037285, "adj_open": 18.0756528575718, "adj_close": 17.9572693817899, "high": 18.89, "adj_volume": 4270.0, "low": 18.108, "date": "2016-01-15", "close": 18.6272, "open": 18.75, "adj_high": 18.2106177322417, "split_ratio": 1.0}, {"ex_dividend": 0.0, "volume": 2200.0, "adj_low": 17.9888897238554, "adj_open": 18.0852932057625, "adj_close": 17.9888897238554, "high": 18.76, "adj_volume": 2200.0, "low": 18.66, "date": "2016-01-14", "close": 18.66, "open": 18.76, "adj_high": 18.0852932057625, "split_ratio": 1.0}, {"ex_dividend": 0.0, "volume": 1429.0, "adj_low": 18.0756528575718, "adj_open": 18.0756528575718, "adj_close": 18.0756528575718, "high": 18.78, "adj_volume": 1429.0, "low": 18.75, "date": "2016-01-13", "close": 18.75, "open": 18.75, "adj_high": 18.1045739021439, "split_ratio": 1.0}, {"ex_dividend": 0.0, "volume": 9460.0, "adj_low": 17.969609027474, "adj_open": 19.0395912731604, "adj_close": 18.3166615623394, "high": 19.75, "adj_volume": 9460.0, "low": 18.64, "date": "2016-01-12", "close": 19.0, "open": 19.7499, "adj_high": 19.0396876766423, "split_ratio": 1.0}, {"ex_dividend": 0.0, "volume": 1975.0, "adj_low": 18.0756528575718, "adj_open": 18.3166615623394, "adj_close": 18.0756528575718, "high": 19.0, "adj_volume": 1975.0, "low": 18.75, "date": "2016-01-11", "close": 18.75, "open": 19.0, "adj_high": 18.3166615623394, "split_ratio": 1.0}, {"ex_dividend": 0.0, "volume": 1147.0, "adj_low": 18.1238545985253, "adj_open": 18.6567730465075, "adj_close": 18.1238545985253, "high": 19.3528, "adj_volume": 1147.0, "low": 18.8, "date": "2016-01-08", "close": 18.8, "open": 19.3528, "adj_high": 18.6567730465075, "split_ratio": 1.0}, {"ex_dividend": 0.0, "volume": 3522.0, "adj_low": 18.0852932057625, "adj_open": 18.8371439611556, "adj_close": 18.1238545985253, "high": 19.5399, "adj_volume": 3522.0, "low": 18.76, "date": "2016-01-07", "close": 18.8, "open": 19.5399, "adj_high": 18.8371439611556, "split_ratio": 1.0}, {"ex_dividend": 0.0, "volume": 433.0, "adj_low": 18.9240034983538, "adj_open": 18.9240034983538, "adj_close": 19.0106702285883, "high": 19.7199, "adj_volume": 433.0, "low": 19.63, "date": "2016-01-06", "close": 19.7199, "open": 19.63, "adj_high": 19.0106702285883, "split_ratio": 1.0}, {"ex_dividend": 0.0, "volume": 707.0, "adj_low": 18.6733544453955, "adj_open": 18.6733544453955, "adj_close": 18.7986789718747, "high": 19.5499, "adj_volume": 707.0, "low": 19.37, "date": "2016-01-05", "close": 19.5, "open": 19.37, "adj_high": 18.8467843093463, "split_ratio": 1.0}, {"ex_dividend": 0.0, "volume": 14.0, "adj_low": 18.0756528575718, "adj_open": 18.0756528575718, "adj_close": 18.0756528575718, "high": 18.75, "adj_volume": 14.0, "low": 18.75, "date": "2016-01-04", "close": 18.75, "open": 18.75, "adj_high": 18.0756528575718, "split_ratio": 1.0}, {"ex_dividend": 0.0, "volume": 110.0, "adj_low": 18.0756528575718, "adj_open": 18.0756528575718, "adj_close": 18.0756528575718, "high": 18.75, "adj_volume": 110.0, "low": 18.75, "date": "2015-12-31", "close": 18.75, "open": 18.75, "adj_high": 18.0756528575718, "split_ratio": 1.0}, {"ex_dividend": 0.0, "volume": 1312.0, "adj_low": 18.7456570568258, "adj_open": 19.0396876766423, "adj_close": 18.9424165633981, "high": 19.89, "adj_volume": 1312.0, "low": 19.445, "date": "2015-12-30", "close": 19.6491, "open": 19.75, "adj_high": 19.1746525513121, "split_ratio": 1.0}, {"ex_dividend": 0.0, "volume": 2978.0, "adj_low": 18.7119158381583, "adj_open": 18.7119158381583, "adj_close": 19.1553718549307, "high": 20.0, "adj_volume": 2978.0, "low": 19.41, "date": "2015-12-29", "close": 19.87, "open": 19.41, "adj_high": 19.2806963814099, "split_ratio": 1.0}, {"ex_dividend": 0.0, "volume": 1436.0, "adj_low": 19.2806963814099, "adj_open": 19.2806963814099, "adj_close": 19.2903367296006, "high": 20.02, "adj_volume": 1436.0, "low": 20.0, "date": "2015-12-28", "close": 20.01, "open": 20.0, "adj_high": 19.2999770777913, "split_ratio": 1.0}, {"ex_dividend": 0.0, "volume": 800.0, "adj_low": 19.2806963814099, "adj_open": 19.2806963814099, "adj_close": 19.2806963814099, "high": 20.0, "adj_volume": 800.0, "low": 20.0, "date": "2015-12-24", "close": 20.0, "open": 20.0, "adj_high": 19.2806963814099, "split_ratio": 1.0}, {"ex_dividend": 0.0, "volume": 1905.0, "adj_low": 19.2517753368378, "adj_open": 19.2517753368378, "adj_close": 19.2903367296006, "high": 20.01, "adj_volume": 1905.0, "low": 19.97, "date": "2015-12-23", "close": 20.01, "open": 19.97, "adj_high": 19.2903367296006, "split_ratio": 1.0}, {"ex_dividend": 0.16, "volume": 3867.0, "adj_low": 17.969609027474, "adj_open": 17.969609027474, "adj_close": 19.1842928995029, "high": 20.01, "adj_volume": 3867.0, "low": 18.64, "date": "2015-12-22", "close": 19.9, "open": 18.64, "adj_high": 19.2903367296006, "split_ratio": 1.0}, {"ex_dividend": 0.0, "volume": 3118.0, "adj_low": 18.0367738042828, "adj_open": 18.1036223622926, "adj_close": 20.733572784707, "high": 21.73, "adj_volume": 3118.0, "low": 18.8601, "date": "2015-12-21", "close": 21.68, "open": 18.93, "adj_high": 20.7813900651145, "split_ratio": 1.0}, {"ex_dividend": 0.0, "volume": 17465.0, "adj_low": 18.1992569231076, "adj_open": 18.4096529569008, "adj_close": 18.8878257609761, "high": 19.75, "adj_volume": 17465.0, "low": 19.03, "date": "2015-12-18", "close": 19.75, "open": 19.25, "adj_high": 18.8878257609761, "split_ratio": 1.0}, {"ex_dividend": 0.0, "volume": 3147.0, "adj_low": 18.6009220785309, "adj_open": 18.8399128460078, "adj_close": 18.8686988488131, "high": 19.73, "adj_volume": 3147.0, "low": 19.45, "date": "2015-12-17", "close": 19.73, "open": 19.6999, "adj_high": 18.8686988488131, "split_ratio": 1.0}, {"ex_dividend": 0.0, "volume": 2763.0, "adj_low": 18.734810463672, "adj_open": 18.8590397581708, "adj_close": 18.734810463672, "high": 19.75, "adj_volume": 2763.0, "low": 19.59, "date": "2015-12-16", "close": 19.59, "open": 19.7199, "adj_high": 18.8878257609761, "split_ratio": 1.0}, {"ex_dividend": 0.0, "volume": 32913.0, "adj_low": 17.9793930677938, "adj_open": 17.9793930677938, "adj_close": 18.8878257609761, "high": 19.75, "adj_volume": 32913.0, "low": 18.8001, "date": "2015-12-15", "close": 19.75, "open": 18.8001, "adj_high": 18.8878257609761, "split_ratio": 1.0}, {"ex_dividend": 0.0, "volume": 9225.0, "adj_low": 17.9888608893145, "adj_open": 18.8400084805686, "adj_close": 18.8782623048946, "high": 19.75, "adj_volume": 9225.0, "low": 18.81, "date": "2015-12-14", "close": 19.74, "open": 19.7, "adj_high": 18.8878257609761, "split_ratio": 1.0}, {"ex_dividend": 0.0, "volume": 1115.0, "adj_low": 18.055805081885, "adj_open": 19.0790948826063, "adj_close": 18.6296124467755, "high": 19.95, "adj_volume": 1115.0, "low": 18.88, "date": "2015-12-11", "close": 19.48, "open": 19.95, "adj_high": 19.0790948826063, "split_ratio": 1.0}, {"ex_dividend": 0.0, "volume": 153.0, "adj_low": 18.5817951663679, "adj_open": 18.5817951663679, "adj_close": 18.5817951663679, "high": 19.43, "adj_volume": 153.0, "low": 19.43, "date": "2015-12-10", "close": 19.43, "open": 19.43, "adj_high": 18.5817951663679, "split_ratio": 1.0}, {"ex_dividend": 0.0, "volume": 322.0, "adj_low": 17.7689013994398, "adj_open": 18.6664317526893, "adj_close": 17.7689013994398, "high": 19.5185, "adj_volume": 322.0, "low": 18.58, "date": "2015-12-09", "close": 18.58, "open": 19.5185, "adj_high": 18.6664317526893, "split_ratio": 1.0}, {"ex_dividend": 0.0, "volume": 6700.0, "adj_low": 17.6637033825433, "adj_open": 19.6146484231707, "adj_close": 19.1269121630138, "high": 20.55, "adj_volume": 6700.0, "low": 18.47, "date": "2015-12-08", "close": 20.0, "open": 20.51, "adj_high": 19.6529022474967, "split_ratio": 1.1}, {"ex_dividend": 0.0, "volume": 2895.0, "adj_low": 18.0401557901153, "adj_open": 18.3879178294428, "adj_close": 18.3618356764933, "high": 21.15, "adj_volume": 3184.5, "low": 20.75, "date": "2015-12-07", "close": 21.12, "open": 21.15, "adj_high": 18.3879178294428, "split_ratio": 1.0}, {"ex_dividend": 0.0, "volume": 415.0, "adj_low": 18.0246803793652, "adj_open": 18.3705297274764, "adj_close": 18.2571593026557, "high": 21.13, "adj_volume": 456.5, "low": 20.7322, "date": "2015-12-04", "close": 20.9996, "open": 21.13, "adj_high": 18.3705297274764, "split_ratio": 1.0}, {"ex_dividend": 0.0, "volume": 2910.0, "adj_low": 18.1792606058463, "adj_open": 18.4313011438489, "adj_close": 18.3705297274764, "high": 21.2, "adj_volume": 3201.0, "low": 20.91, "date": "2015-12-03", "close": 21.13, "open": 21.1999, "adj_high": 18.4313880843588, "split_ratio": 1.0}, {"ex_dividend": 0.0, "volume": 13462.0, "adj_low": 17.9966855351994, "adj_open": 18.6487393589385, "adj_close": 17.9966855351994, "high": 21.45, "adj_volume": 14808.2, "low": 20.7, "date": "2015-12-02", "close": 20.7, "open": 21.45, "adj_high": 18.6487393589385, "split_ratio": 1.0}, {"ex_dividend": 0.0, "volume": 8988.0, "adj_low": 17.4750424762081, "adj_open": 17.8227175750258, "adj_close": 17.979297433233, "high": 20.68, "adj_volume": 9886.8, "low": 20.1, "date": "2015-12-01", "close": 20.68, "open": 20.4999, "adj_high": 17.979297433233, "split_ratio": 1.0}, {"ex_dividend": 0.0, "volume": 3648.0, "adj_low": 17.4924305781745, "adj_open": 17.6402294448887, "adj_close": 17.6489234958718, "high": 20.3, "adj_volume": 4012.8, "low": 20.12, "date": "2015-11-30", "close": 20.3, "open": 20.29, "adj_high": 17.6489234958718, "split_ratio": 1.0}, {"ex_dividend": 0.0, "volume": 445.0, "adj_low": 17.4315722212921, "adj_open": 17.6706586233298, "adj_close": 17.4315722212921, "high": 20.325, "adj_volume": 489.5, "low": 20.05, "date": "2015-11-27", "close": 20.05, "open": 20.325, "adj_high": 17.6706586233298, "split_ratio": 1.0}, {"ex_dividend": 0.0, "volume": 4001.0, "adj_low": 17.5445948840736, "adj_open": 17.56198298604, "adj_close": 17.56198298604, "high": 20.2, "adj_volume": 4401.1, "low": 20.18, "date": "2015-11-25", "close": 20.2, "open": 20.2, "adj_high": 17.56198298604, "split_ratio": 1.0}, {"ex_dividend": 0.0, "volume": 27202.0, "adj_low": 17.4663484252249, "adj_open": 17.4663484252249, "adj_close": 17.518512731124, "high": 20.5, "adj_volume": 29922.2, "low": 20.09, "date": "2015-11-24", "close": 20.15, "open": 20.09, "adj_high": 17.8228045155356, "split_ratio": 1.0}, {"ex_dividend": 0.0, "volume": 501.0, "adj_low": 17.56198298604, "adj_open": 17.56198298604, "adj_close": 17.56198298604, "high": 20.2, "adj_volume": 551.1, "low": 20.2, "date": "2015-11-23", "close": 20.2, "open": 20.2, "adj_high": 17.56198298604, "split_ratio": 1.0}, {"ex_dividend": 0.0, "volume": 18070.0, "adj_low": 17.4305289351742, "adj_open": 17.4305289351742, "adj_close": 17.8141104645524, "high": 20.49, "adj_volume": 19877.0, "low": 20.0488, "date": "2015-11-20", "close": 20.49, "open": 20.0488, "adj_high": 17.8141104645524, "split_ratio": 1.0}, {"ex_dividend": 0.0, "volume": 3933.0, "adj_low": 17.4750424762081, "adj_open": 17.4750424762081, "adj_close": 17.8228045155356, "high": 20.51, "adj_volume": 4326.3, "low": 20.1, "date": "2015-11-19", "close": 20.5, "open": 20.1, "adj_high": 17.8314985665188, "split_ratio": 1.0}, {"ex_dividend": 0.0, "volume": 2340.0, "adj_low": 17.2750793035948, "adj_open": 17.2750793035948, "adj_close": 17.2750793035948, "high": 19.9707, "adj_volume": 2574.0, "low": 19.87, "date": "2015-11-18", "close": 19.87, "open": 19.87, "adj_high": 17.3626283969955, "split_ratio": 1.0}, {"ex_dividend": 0.0, "volume": 4445.0, "adj_low": 17.240303099662, "adj_open": 17.2750793035948, "adj_close": 17.379407915393, "high": 19.99, "adj_volume": 4889.5, "low": 19.83, "date": "2015-11-17", "close": 19.99, "open": 19.87, "adj_high": 17.379407915393, "split_ratio": 1.0}, {"ex_dividend": 0.0, "volume": 2716.0, "adj_low": 16.7360481426371, "adj_open": 16.7534362446035, "adj_close": 16.7360481426371, "high": 19.27, "adj_volume": 2987.6, "low": 19.25, "date": "2015-11-16", "close": 19.25, "open": 19.27, "adj_high": 16.7534362446035, "split_ratio": 1.0}, {"ex_dividend": 0.0, "volume": 359.0, "adj_low": 17.5966722494629, "adj_open": 17.5966722494629, "adj_close": 17.5966722494629, "high": 20.2399, "adj_volume": 394.9, "low": 20.2399, "date": "2015-11-13", "close": 20.2399, "open": 20.2399, "adj_high": 17.5966722494629, "split_ratio": 1.0}, {"ex_dividend": 0.0, "volume": 0.0, "adj_low": 16.3448158483936, "adj_open": 16.3448158483936, "adj_close": 16.3448158483936, "high": 18.8, "adj_volume": 0.0, "low": 18.8, "date": "2015-11-12", "close": 18.8, "open": 18.8, "adj_high": 16.3448158483936, "split_ratio": 1.0}, {"ex_dividend": 0.0, "volume": 5.0, "adj_low": 16.3448158483936, "adj_open": 16.3448158483936, "adj_close": 16.3448158483936, "high": 18.8, "adj_volume": 5.5, "low": 18.8, "date": "2015-11-11", "close": 18.8, "open": 18.8, "adj_high": 16.3448158483936, "split_ratio": 1.0}, {"ex_dividend": 0.0, "volume": 483.0, "adj_low": 16.2144050836458, "adj_open": 16.2144050836458, "adj_close": 16.3448158483936, "high": 18.9, "adj_volume": 531.3, "low": 18.65, "date": "2015-11-10", "close": 18.8, "open": 18.65, "adj_high": 16.4317563582255, "split_ratio": 1.0}, {"ex_dividend": 0.0, "volume": 9536.0, "adj_low": 15.6928489651643, "adj_open": 16.3882861033096, "adj_close": 17.3359376604771, "high": 20.44, "adj_volume": 10489.6, "low": 18.0501, "date": "2015-11-09", "close": 19.94, "open": 18.85, "adj_high": 17.7706402096365, "split_ratio": 1.0}, {"ex_dividend": 0.0, "volume": 28648.0, "adj_low": 16.0753002679148, "adj_open": 16.7360481426371, "adj_close": 16.7099659896875, "high": 19.77, "adj_volume": 31512.8, "low": 18.49, "date": "2015-11-06", "close": 19.22, "open": 19.25, "adj_high": 17.1881387937629, "split_ratio": 1.0}], "result_count": 315}}